Workbook

Sheet Intro
A2: Financial Model Guide
A3: =+TODAY() -> 44539
A9: COLOR CODING
A11: Inputs/assumptions | B11: BLUE | C11: Inputs, or any hard-coded data, such as historical values, assumptions, and drivers.
A12: Formulas/results | B12: BLACK | C12: Formulas, calculations, or references deriving from inputs
A15: CONTENTS
A17: LL Settings | C17: Lady Loans settings
A18: Settings | C18: General settings
A19: Projections | C19: Use this sheet to summarize the variables that directly affect the business projections
A20: FS-Annual | C20: Projected annual financial statements
A21: FS-Month | C21: Projected monthly financial statements
A22: Revenue | C22: Detailed monthly revenue assumptions & projections
A23: COGS | C23: Detailed monthly cost of goods sold (COGS) assumptions & projections
A24: SG&A | C24: Detailed monthly selling, general & administrative expenses (SG&A) assumptions & projections
A25: WK+CAPEX | C25: Detailed monthly working capital (WK) & capital expenditures (CAPEX) assumptions & projections

Sheet CSS Settings
A3: Client Settings | B3: Year 0 | C3: Year 1 | D3: Year 2 | E3: Year 3 | F3: Year 4 | G3: Year 5 | H3: Expense Settings
H4: Salaries and Wages | R4: Questions
A5: Number of Loans in Month 1 | B5: 150 | H5: EIR (part time) | I5: -55000 | R5: If Ladies payout or roll to collections, do they stay in the Sisterhood? If so, for how long?
A6: New Cosign Loans Percentage Growth Per Month | B6: 0.005 | C6: 0.015 | D6: 0.03 | E6: 0.03 | F6: 0.02 | G6: 0.02 | H6: Growth Operations Manager | I6: -60000 | R6: Why cap growth at 100 ladies per month?
A7: Average Loan Written | B7: 4300 | C7: 4200 | D7: 5000 | E7: 5500 | F7: 6000 | G7: 6000 | H7: Business Analyst | I7: -50000 | R7: Any other employees?
A8: Borrower Calls (Charge Off %) BK & Judgement | B8: 0.04 | H8: Collector | I8: -50000 | R8: Hire triggers for Deputy and Assistants?
A9: Therefore, Monthly Borrower Calls (WriteOff %) | B9: =+B8/12 -> 0.0033333333
A10: Monthly Payout/Paydown % | B10: 0.04 | H10: Benefits, CPP, WCB, and EI Expenses as % of Wages | I10: 0.14
A11: Monthly Increase % | B11: 0.0375 | H11: Performance Pay Weekly ($) Per Employee | I11: 0 | J11: Per Employee
A12: Cosign Borrower Fee Charged | B12: 0.1 | H12: Digital Marketing | I12: 500 | J12: Overall
A13: Lender Calls 210+ Days | Lender Fee | B13: 0 | C13: 0.1
A14: Lender Calls 150+ Days | Lender Fee | B14: 0 | C14: 0.15
A15: Lender Calls 45+ Days | Lender Fee | B15: 0 | C15: 0.2 | H15: Rent | I15: 0
A16: Interest Rate Charged | B16: 0.4899 | H16: Repairs & Maintenance | I16: 0
A17: Recoverable % from Loans in Judgement | B17: 0.2 | H17: Insurance Expense - Corporate | I17: 150
A18: Bankruptcy % | B18: 0.8
A19: Cosign Reserve Account Cap of Call Fees | B19: 0.25
A20: NSF Payment % | B20: 0
A21: NSF Fee Charge | B21: 0
H22: Telephone Expense - Voip and Cell | I22: =29.99*1.33 -> 39.8867 | J22: Per Month
A23: Loan Discount (as Percentage of Int. Rev) | B23: 0.01 | H23: Internet Expense | I23: 0
A24: Commissions (as % of Int Rev) | B24: 0 | H24: Utilities Expense | I24: 0
A25: Avg Loan Payout Program Payout (from BST) | B25: 0 | H25: Bank Charges | I25: 50
A26: Game Changer Foundation Contribution | B26: 0.01 | H26: Computer & Licensing Expense | I26: 150 | J26: Per Employee
H27: Courier/Postage | I27: 0
A28: Lender Admin Fee | B28: 0.25 | H28: Credit / Collections Expense | I28: 0.25
A29: % of Loans Eligible for Admin Fee | B29: 0.5
A30: Borower Payout Bonus | B30: 0.25 | H30: Office Expense | I30: 50
A31: % of Loans Eligible for Payout Bonus | B31: 0.05 | H31: Travel | I31: 0 | J31: Per Employee
H32: Meals and Entertainment | I32: 50 | J32: Per Employee
H34: Legal | I34: 150
H35: Professional | I35: 150
H36: Accounting | I36: 0
H37: Other | I37: 0
H39: CashCo Agency Agreement | I39: 2000 | J39: Per Month
H42: Annual Interest Rate (on Debt) | I42: 0.1
H44: Credit Card Fees | I44: 0.029

Sheet Settings
A1: Item | B1: Format | C1: Input | D1: Notes
A4: GENERAL
A5: Company Name | C5: CosignSimple
A6: Currency | C6: CAD
A7: Model Start Date | C7: 43831 | D7: Model can only start on calendar years.
A10: FS-MONTH
A11: Initial Cash Balance | B11: =Settings!$C$6 -> CAD | C11: 0
A13: FS-ANNUAL
A15: Taxes & Inflation
A16: Income tax rate | B16: % | C16: =0.15+0.08 -> 0.23 | D16: Will be used to estimate the the annual tax payment, that will be added to FS-Month
A17: Inflation | B17: % | C17: 0.015 | D17: Used for buiness valuation calculations and depretiation repurchases
A19: Valuation
A20: Business terminal value | C20: xEBITDA | D20: This model will estimate your current business valuation based on a Discounted Cash Flow Model:
A21: Discount rate - Today | B21: % | C21: 0.25 | D21: https://www.investopedia.com/terms/d/dcf.asp#:~:text=Discounted%20cash%20flow%20(DCF)%20is,will%20generate%20in%20the%20future.
A22: xEBITDA | B22: Multiplier | C22: 8
A23: Debt/Capital Ratio | B23: % | C23: 0
A24: Debt interest rate | B24: % | C24: 0.1
A26: CAPEX
A28: Operating Cash
A29: Balance | B29: =Settings!$C$6 -> CAD | C29: 0
A30: Percentage of revenues | B30: % | C30: 0.1
A32: Accounts Receivable
A33: Pending Income/Total Income | B33: % | C33: 0
A35: Pre-paid expenses
A36: Pre-paid Days Outstanding | B36: days | C36: 30
A38: Accounts Payable
A39: A/P as % of total COGS | B39: % | C39: 0
A41: CAPITAL EXPENDITURES
A42: Automatically estimate new computer purchases for new employees | B42: Dropdown | C42: YES
A43: Price per computer | B43: =$C$6 -> CAD | C43: 999
A45: TIME FOR ASSETS TO DEPRECIATE
A46: Office fixings | B46: Years | C46: 10
A47: Office furniture | B47: Years | C47: 5
A48: Computers | B48: Years | C48: 3
A49: Telecom equipment | B49: Years | C49: 5
A50: Servers & other tech infrastructure | B50: Years | C50: 5
A51: Other | B51: Years | C51: 5

Sheet Projections
A1: Item | B1: Format | C1: Input | D1: Scenario A | E1: Scenario B | F1: Scenario C | G1: Notes
A2: General Settings
A4: Fundraising Close Date | B4: Date | D4: 44197 | E4: 44197 | F4: 44197
A5: Investment Amount | B5: USD | D5: 0 | E5: 0 | F5: 0
A10: REVENUE
A17: SG&A
A19: Office > Per Desk Cost | B19: =Settings!$C$6 -> CAD | C19: 0
A22: COGS
A26: CAPEX

Sheet Data for Charts
A1: =Settings!C5 -> CosignSimple
A2: Data for Charts
A3: =+TODAY() -> 44539
D6: ='FS-Month'!C6 -> 43831 | E6: ='FS-Month'!D6 -> 43862 | F6: ='FS-Month'!E6 -> 43891 | G6: ='FS-Month'!F6 -> 43922 | H6: ='FS-Month'!G6 -> 43952 | I6: ='FS-Month'!H6 -> 43983 | J6: ='FS-Month'!I6 -> 44013 | K6: ='FS-Month'!J6 -> 44044 | ... U6: ='FS-Month'!T6 -> 44348 | V6: ='FS-Month'!#REF! -> #REF! | W6: ='FS-Month'!#REF! -> #REF! | X6: ='FS-Month'!#REF! -> #REF! | Y6: ='FS-Month'!#REF! -> #REF! | Z6: ='FS-Month'!#REF! -> #REF! | AA6: ='FS-Month'!#REF! -> #REF! | AB6: ='FS-Month'!#REF! -> #REF! | AC6: ='FS-Month'!#REF! -> #REF! | ... CI6: ='FS-Month'!#REF! -> #REF!
D7: ='FS-Month'!C7 -> 1 | E7: ='FS-Month'!D7 -> 2 | F7: ='FS-Month'!E7 -> 3 | G7: ='FS-Month'!F7 -> 4 | H7: ='FS-Month'!G7 -> 5 | I7: ='FS-Month'!H7 -> 1 | J7: ='FS-Month'!I7 -> 2 | K7: ='FS-Month'!J7 -> 3 | ... U7: ='FS-Month'!T7 -> 13 | V7: ='FS-Month'!#REF! -> #REF! | W7: ='FS-Month'!#REF! -> #REF! | X7: ='FS-Month'!#REF! -> #REF! | Y7: ='FS-Month'!#REF! -> #REF! | Z7: ='FS-Month'!#REF! -> #REF! | AA7: ='FS-Month'!#REF! -> #REF! | AB7: ='FS-Month'!#REF! -> #REF! | AC7: ='FS-Month'!#REF! -> #REF! | ... CI7: ='FS-Month'!#REF! -> #REF!
A11: P&L Bar Chart
A13: ='FS-Month'!A24 -> Revenue | D13: ='FS-Month'!C24 -> #REF! | E13: ='FS-Month'!D24 -> #REF! | F13: ='FS-Month'!E24 -> #REF! | G13: ='FS-Month'!F24 -> #REF! | H13: ='FS-Month'!G24 -> #REF! | I13: ='FS-Month'!H24 -> 11019.37 | J13: ='FS-Month'!I24 -> 40182.38 | K13: ='FS-Month'!J24 -> 71359.875 | ... U13: ='FS-Month'!T24 -> 106334.6 | V13: ='FS-Month'!#REF! -> #REF! | W13: ='FS-Month'!#REF! -> #REF! | X13: ='FS-Month'!#REF! -> #REF! | Y13: ='FS-Month'!#REF! -> #REF! | Z13: ='FS-Month'!#REF! -> #REF! | AA13: ='FS-Month'!#REF! -> #REF! | AB13: ='FS-Month'!#REF! -> #REF! | AC13: ='FS-Month'!#REF! -> #REF! | ... CI13: ='FS-Month'!#REF! -> #REF!
A14: ='FS-Month'!A29 -> COS | D14: ='FS-Month'!C29*-1 -> #REF! | E14: ='FS-Month'!D29*-1 -> #REF! | F14: ='FS-Month'!E29*-1 -> #REF! | G14: ='FS-Month'!F29*-1 -> #REF! | H14: ='FS-Month'!G29*-1 -> #REF! | I14: ='FS-Month'!H29*-1 -> 0 | J14: ='FS-Month'!I29*-1 -> 0 | K14: ='FS-Month'!J29*-1 -> 0 | ... U14: ='FS-Month'!T29*-1 -> 0 | V14: ='FS-Month'!#REF!*-1 -> #REF! | W14: ='FS-Month'!#REF!*-1 -> #REF! | X14: ='FS-Month'!#REF!*-1 -> #REF! | Y14: ='FS-Month'!#REF!*-1 -> #REF! | Z14: ='FS-Month'!#REF!*-1 -> #REF! | AA14: ='FS-Month'!#REF!*-1 -> #REF! | AB14: ='FS-Month'!#REF!*-1 -> #REF! | AC14: ='FS-Month'!#REF!*-1 -> #REF! | ... CI14: ='FS-Month'!#REF!*-1 -> #REF!
A15: ='FS-Month'!A35 -> SG&A | D15: ='FS-Month'!C35*-1 -> 0 | E15: ='FS-Month'!D35*-1 -> 0 | F15: ='FS-Month'!E35*-1 -> 0 | G15: ='FS-Month'!F35*-1 -> 0 | H15: ='FS-Month'!G35*-1 -> 0 | I15: ='FS-Month'!H35*-1 -> 739.8867 | J15: ='FS-Month'!I35*-1 -> 739.8867 | K15: ='FS-Month'!J35*-1 -> 739.8867 | ... U15: ='FS-Month'!T35*-1 -> 12099.887 | V15: ='FS-Month'!#REF!*-1 -> #REF! | W15: ='FS-Month'!#REF!*-1 -> #REF! | X15: ='FS-Month'!#REF!*-1 -> #REF! | Y15: ='FS-Month'!#REF!*-1 -> #REF! | Z15: ='FS-Month'!#REF!*-1 -> #REF! | AA15: ='FS-Month'!#REF!*-1 -> #REF! | AB15: ='FS-Month'!#REF!*-1 -> #REF! | AC15: ='FS-Month'!#REF!*-1 -> #REF! | ... CI15: ='FS-Month'!#REF!*-1 -> #REF!
A16: CAPEX | D16: ='FS-Month'!C98*-1 -> 0 | E16: ='FS-Month'!D98*-1 -> 0 | F16: ='FS-Month'!E98*-1 -> 0 | G16: ='FS-Month'!F98*-1 -> 0 | H16: ='FS-Month'!G98*-1 -> 0 | I16: ='FS-Month'!H98*-1 -> 0 | J16: ='FS-Month'!I98*-1 -> 0 | K16: ='FS-Month'!J98*-1 -> 0 | ... U16: ='FS-Month'!T98*-1 -> 0 | V16: ='FS-Month'!#REF!*-1 -> #REF! | W16: ='FS-Month'!#REF!*-1 -> #REF! | X16: ='FS-Month'!#REF!*-1 -> #REF! | Y16: ='FS-Month'!#REF!*-1 -> #REF! | Z16: ='FS-Month'!#REF!*-1 -> #REF! | AA16: ='FS-Month'!#REF!*-1 -> #REF! | AB16: ='FS-Month'!#REF!*-1 -> #REF! | AC16: ='FS-Month'!#REF!*-1 -> #REF! | ... CI16: ='FS-Month'!#REF!*-1 -> #REF!
A19: Cash in the Bank
A20: Cash in the Bank | D20: ='FS-Month'!C101 -> #REF! | E20: ='FS-Month'!D101 -> #REF! | F20: ='FS-Month'!E101 -> #REF! | G20: ='FS-Month'!F101 -> #REF! | H20: ='FS-Month'!G101 -> #REF! | I20: ='FS-Month'!H101 -> 10279.483 | J20: ='FS-Month'!I101 -> 49721.977 | K20: ='FS-Month'!J101 -> 120341.96 | ... U20: ='FS-Month'!T101 -> 754284.64 | V20: ='FS-Month'!#REF! -> #REF! | W20: ='FS-Month'!#REF! -> #REF! | X20: ='FS-Month'!#REF! -> #REF! | Y20: ='FS-Month'!#REF! -> #REF! | Z20: ='FS-Month'!#REF! -> #REF! | AA20: ='FS-Month'!#REF! -> #REF! | AB20: ='FS-Month'!#REF! -> #REF! | AC20: ='FS-Month'!#REF! -> #REF! | ... CI20: ='FS-Month'!#REF! -> #REF!
A24: Use of Funds - first 18 months
A26: SG&A
A27: Ops | D27: =SUMIF('COS and SG&A'!#REF!,$A27,'COS and SG&A'!C:C) -> #REF! | E27: =SUMIF('COS and SG&A'!#REF!,$A27,'COS and SG&A'!D:D) -> #REF! | F27: =SUMIF('COS and SG&A'!#REF!,$A27,'COS and SG&A'!E:E) -> #REF! | G27: =SUMIF('COS and SG&A'!#REF!,$A27,'COS and SG&A'!F:F) -> #REF! | H27: =SUMIF('COS and SG&A'!#REF!,$A27,'COS and SG&A'!G:G) -> #REF! | I27: =SUMIF('COS and SG&A'!#REF!,$A27,'COS and SG&A'!H:H) -> #REF! | J27: =SUMIF('COS and SG&A'!#REF!,$A27,'COS and SG&A'!I:I) -> #REF! | K27: =SUMIF('COS and SG&A'!#REF!,$A27,'COS and SG&A'!J:J) -> #REF! | L27: =SUMIF('COS and SG&A'!#REF!,$A27,'COS and SG&A'!K:K) -> #REF! | M27: =SUMIF('COS and SG&A'!#REF!,$A27,'COS and SG&A'!L:L) -> #REF! | N27: =SUMIF('COS and SG&A'!#REF!,$A27,'COS and SG&A'!M:M) -> #REF! | O27: =SUMIF('COS and SG&A'!#REF!,$A27,'COS and SG&A'!N:N) -> #REF! | P27: =SUMIF('COS and SG&A'!#REF!,$A27,'COS and SG&A'!O:O) -> #REF! | Q27: =SUMIF('COS and SG&A'!#REF!,$A27,'COS and SG&A'!P:P) -> #REF! | R27: =SUMIF('COS and SG&A'!#REF!,$A27,'COS and SG&A'!Q:Q) -> #REF! | S27: =SUMIF('COS and SG&A'!#REF!,$A27,'COS and SG&A'!R:R) -> #REF! | T27: =SUMIF('COS and SG&A'!#REF!,$A27,'COS and SG&A'!S:S) -> #REF! | U27: =SUMIF('COS and SG&A'!#REF!,$A27,'COS and SG&A'!T:T) -> #REF!
A28: R&D | D28: =SUMIF('COS and SG&A'!#REF!,$A28,'COS and SG&A'!C:C) -> #REF! | E28: =SUMIF('COS and SG&A'!#REF!,$A28,'COS and SG&A'!D:D) -> #REF! | F28: =SUMIF('COS and SG&A'!#REF!,$A28,'COS and SG&A'!E:E) -> #REF! | G28: =SUMIF('COS and SG&A'!#REF!,$A28,'COS and SG&A'!F:F) -> #REF! | H28: =SUMIF('COS and SG&A'!#REF!,$A28,'COS and SG&A'!G:G) -> #REF! | I28: =SUMIF('COS and SG&A'!#REF!,$A28,'COS and SG&A'!H:H) -> #REF! | J28: =SUMIF('COS and SG&A'!#REF!,$A28,'COS and SG&A'!I:I) -> #REF! | K28: =SUMIF('COS and SG&A'!#REF!,$A28,'COS and SG&A'!J:J) -> #REF! | L28: =SUMIF('COS and SG&A'!#REF!,$A28,'COS and SG&A'!K:K) -> #REF! | M28: =SUMIF('COS and SG&A'!#REF!,$A28,'COS and SG&A'!L:L) -> #REF! | N28: =SUMIF('COS and SG&A'!#REF!,$A28,'COS and SG&A'!M:M) -> #REF! | O28: =SUMIF('COS and SG&A'!#REF!,$A28,'COS and SG&A'!N:N) -> #REF! | P28: =SUMIF('COS and SG&A'!#REF!,$A28,'COS and SG&A'!O:O) -> #REF! | Q28: =SUMIF('COS and SG&A'!#REF!,$A28,'COS and SG&A'!P:P) -> #REF! | R28: =SUMIF('COS and SG&A'!#REF!,$A28,'COS and SG&A'!Q:Q) -> #REF! | S28: =SUMIF('COS and SG&A'!#REF!,$A28,'COS and SG&A'!R:R) -> #REF! | T28: =SUMIF('COS and SG&A'!#REF!,$A28,'COS and SG&A'!S:S) -> #REF! | U28: =SUMIF('COS and SG&A'!#REF!,$A28,'COS and SG&A'!T:T) -> #REF!
A29: Growth | D29: =SUMIF('COS and SG&A'!#REF!,$A29,'COS and SG&A'!C:C) -> #REF! | E29: =SUMIF('COS and SG&A'!#REF!,$A29,'COS and SG&A'!D:D) -> #REF! | F29: =SUMIF('COS and SG&A'!#REF!,$A29,'COS and SG&A'!E:E) -> #REF! | G29: =SUMIF('COS and SG&A'!#REF!,$A29,'COS and SG&A'!F:F) -> #REF! | H29: =SUMIF('COS and SG&A'!#REF!,$A29,'COS and SG&A'!G:G) -> #REF! | I29: =SUMIF('COS and SG&A'!#REF!,$A29,'COS and SG&A'!H:H) -> #REF! | J29: =SUMIF('COS and SG&A'!#REF!,$A29,'COS and SG&A'!I:I) -> #REF! | K29: =SUMIF('COS and SG&A'!#REF!,$A29,'COS and SG&A'!J:J) -> #REF! | L29: =SUMIF('COS and SG&A'!#REF!,$A29,'COS and SG&A'!K:K) -> #REF! | M29: =SUMIF('COS and SG&A'!#REF!,$A29,'COS and SG&A'!L:L) -> #REF! | N29: =SUMIF('COS and SG&A'!#REF!,$A29,'COS and SG&A'!M:M) -> #REF! | O29: =SUMIF('COS and SG&A'!#REF!,$A29,'COS and SG&A'!N:N) -> #REF! | P29: =SUMIF('COS and SG&A'!#REF!,$A29,'COS and SG&A'!O:O) -> #REF! | Q29: =SUMIF('COS and SG&A'!#REF!,$A29,'COS and SG&A'!P:P) -> #REF! | R29: =SUMIF('COS and SG&A'!#REF!,$A29,'COS and SG&A'!Q:Q) -> #REF! | S29: =SUMIF('COS and SG&A'!#REF!,$A29,'COS and SG&A'!R:R) -> #REF! | T29: =SUMIF('COS and SG&A'!#REF!,$A29,'COS and SG&A'!S:S) -> #REF! | U29: =SUMIF('COS and SG&A'!#REF!,$A29,'COS and SG&A'!T:T) -> #REF!
A31: COGS
A32: Ops | D32: =SUMIF(#REF!,$A32,#REF!) -> #REF! | E32: =SUMIF(#REF!,$A32,#REF!) -> #REF! | F32: =SUMIF(#REF!,$A32,#REF!) -> #REF! | G32: =SUMIF(#REF!,$A32,#REF!) -> #REF! | H32: =SUMIF(#REF!,$A32,#REF!) -> #REF! | I32: =SUMIF(#REF!,$A32,#REF!) -> #REF! | J32: =SUMIF(#REF!,$A32,#REF!) -> #REF! | K32: =SUMIF(#REF!,$A32,#REF!) -> #REF! | ... U32: =SUMIF(#REF!,$A32,#REF!) -> #REF!
A33: R&D | D33: =SUMIF(#REF!,$A33,#REF!) -> #REF! | E33: =SUMIF(#REF!,$A33,#REF!) -> #REF! | F33: =SUMIF(#REF!,$A33,#REF!) -> #REF! | G33: =SUMIF(#REF!,$A33,#REF!) -> #REF! | H33: =SUMIF(#REF!,$A33,#REF!) -> #REF! | I33: =SUMIF(#REF!,$A33,#REF!) -> #REF! | J33: =SUMIF(#REF!,$A33,#REF!) -> #REF! | K33: =SUMIF(#REF!,$A33,#REF!) -> #REF! | ... U33: =SUMIF(#REF!,$A33,#REF!) -> #REF!
A34: Growth | D34: =SUMIF(#REF!,$A34,#REF!) -> #REF! | E34: =SUMIF(#REF!,$A34,#REF!) -> #REF! | F34: =SUMIF(#REF!,$A34,#REF!) -> #REF! | G34: =SUMIF(#REF!,$A34,#REF!) -> #REF! | H34: =SUMIF(#REF!,$A34,#REF!) -> #REF! | I34: =SUMIF(#REF!,$A34,#REF!) -> #REF! | J34: =SUMIF(#REF!,$A34,#REF!) -> #REF! | K34: =SUMIF(#REF!,$A34,#REF!) -> #REF! | ... U34: =SUMIF(#REF!,$A34,#REF!) -> #REF!
A37: Total
A38: Ops | D38: =D27+D32 -> #REF! | E38: =E27+E32 -> #REF! | F38: =F27+F32 -> #REF! | G38: =G27+G32 -> #REF! | H38: =H27+H32 -> #REF! | I38: =I27+I32 -> #REF! | J38: =J27+J32 -> #REF! | K38: =K27+K32 -> #REF! | ... U38: =U27+U32 -> #REF!
A39: R&D | D39: =D28+D33 -> #REF! | E39: =E28+E33 -> #REF! | F39: =F28+F33 -> #REF! | G39: =G28+G33 -> #REF! | H39: =H28+H33 -> #REF! | I39: =I28+I33 -> #REF! | J39: =J28+J33 -> #REF! | K39: =K28+K33 -> #REF! | ... U39: =U28+U33 -> #REF!
A40: Growth | D40: =D29+D34 -> #REF! | E40: =E29+E34 -> #REF! | F40: =F29+F34 -> #REF! | G40: =G29+G34 -> #REF! | H40: =H29+H34 -> #REF! | I40: =I29+I34 -> #REF! | J40: =J29+J34 -> #REF! | K40: =K29+K34 -> #REF! | ... U40: =U29+U34 -> #REF!
A41: Other | D41: =D42-D38-D39-D40 -> #REF! | E41: =E42-E38-E39-E40 -> #REF! | F41: =F42-F38-F39-F40 -> #REF! | G41: =G42-G38-G39-G40 -> #REF! | H41: =H42-H38-H39-H40 -> #REF! | I41: =I42-I38-I39-I40 -> #REF! | J41: =J42-J38-J39-J40 -> #REF! | K41: =K42-K38-K39-K40 -> #REF! | ... U41: =U42-U38-U39-U40 -> #REF!
A42: Total Expenses | D42: ='FS-Month'!C35+'FS-Month'!C29 -> #REF! | E42: ='FS-Month'!D35+'FS-Month'!D29 -> #REF! | F42: ='FS-Month'!E35+'FS-Month'!E29 -> #REF! | G42: ='FS-Month'!F35+'FS-Month'!F29 -> #REF! | H42: ='FS-Month'!G35+'FS-Month'!G29 -> #REF! | I42: ='FS-Month'!H35+'FS-Month'!H29 -> -739.8867 | J42: ='FS-Month'!I35+'FS-Month'!I29 -> -739.8867 | K42: ='FS-Month'!J35+'FS-Month'!J29 -> -739.8867 | ... U42: ='FS-Month'!T35+'FS-Month'!T29 -> -12099.887
A45: Pie Chart
A46: Ops | C46: =D46/D$50 -> #REF! | D46: =SUM(38:38) -> #REF!
A47: R&D | C47: =D47/D$50 -> #REF! | D47: =SUM(39:39) -> #REF!
A48: Growth | C48: =D48/D$50 -> #REF! | D48: =SUM(40:40) -> #REF!
A49: Other | C49: =D49/D$50 -> #REF! | D49: =SUM(41:41) -> #REF!
A50: Total Expenses | D50: =SUM(42:42) -> #REF!

Sheet FS-Month
A1: =Settings!C5 -> CosignSimple
A2: Financial Statement (Monthly)
A3: =+TODAY() -> 44539 | AD3: Year End Jan 31
Z4: ***Forcast*** | AD4: H:O | AE4: P:AA
C6: =Settings!$C$7 -> 43831 | D6: =EDATE(C6,1) -> 43862 | E6: =EDATE(D6,1) -> 43891 | F6: =EDATE(E6,1) -> 43922 | G6: =EDATE(F6,1) -> 43952 | H6: =EDATE(G6,1) -> 43983 | I6: =EDATE(H6,1) -> 44013 | J6: =EDATE(I6,1) -> 44044 | K6: =EDATE(J6,1) -> 44075 | ... AA6: =EDATE(Z6,1) -> 44562 | AC6: Total | AD6: Total | AE6: Total
B7: Unit | C7: 1 | D7: =C7+1 -> 2 | E7: =D7+1 -> 3 | F7: =E7+1 -> 4 | G7: =F7+1 -> 5 | H7: 1 | I7: =H7+1 -> 2 | J7: =I7+1 -> 3 | K7: =J7+1 -> 4 | L7: =K7+1 -> 5 | M7: =L7+1 -> 6 | N7: =M7+1 -> 7 | O7: =N7+1 -> 8 | P7: =O7+1 -> 9 | ... AA7: =Z7+1 -> 20 | AC7: LTD | AD7: FY2020 | AE7: FY2021(YTD)
A9: KEY INDICATORS
A11: =Revenue!A11 -> # of Loans | C11: =Revenue!C11 -> 0 | D11: =Revenue!D11 -> 0 | E11: =Revenue!E11 -> 0 | F11: =Revenue!F11 -> 0 | G11: =Revenue!G11 -> 0 | H11: =Revenue!H11 -> 31 | I11: =Revenue!I11 -> 114 | J11: =Revenue!J11 -> 167 | ... AA11: =Revenue!AA11 -> 381.37687 | AC11: =SUM(H11:AA11) -> 4306.4519 | AD11: =SUM(H11:O11) -> 847 | AE11: =SUM(P11:AA11) -> 3459.4519
A12: =Revenue!A12 -> Total # of Loans | C12: =Revenue!C12 -> 0 | D12: =Revenue!D12 -> 0 | E12: =Revenue!E12 -> 0 | F12: =Revenue!F12 -> 0 | G12: =Revenue!G12 -> 0 | H12: =Revenue!H12 -> 31 | I12: =Revenue!I12 -> 145 | J12: =Revenue!J12 -> 312 | ... AA12: =Revenue!AA12 -> 4306.4519 | AC12: =AA12 -> 4306.4519 | AD12: =O12 -> 847 | AE12: =AA12 -> 4306.4519
A14: =Revenue!A14 -> Total $ on Loan (Outstanding Loans) BOM | C14: =Revenue!C14 -> 0 | D14: =Revenue!D14 -> 0 | E14: =Revenue!E14 -> 0 | F14: =Revenue!F14 -> 0 | G14: =Revenue!G14 -> 0 | H14: =Revenue!H14 -> 0 | I14: =Revenue!I14 -> 110193.7 | J14: =Revenue!J14 -> 512017.5 | ... AA14: =Revenue!AA14 -> 14922264 | AC14: =+AA20 -> 16562185 | AD14: =O20 -> 3929213.9 | AE14: =AA20 -> 16562185
A15: =Revenue!A15 -> New Loans Written | C15: =Revenue!C15 -> 0 | D15: =Revenue!D15 -> 0 | E15: =Revenue!E15 -> 0 | F15: =Revenue!F15 -> 0 | G15: =Revenue!G15 -> 0 | H15: =Revenue!H15 -> 110193.7 | I15: =Revenue!I15 -> 401823.8 | J15: =Revenue!J15 -> 713598.75 | ... AA15: =Revenue!AA15 -> 1639920.6 | AC15: =SUM(H15:AA15) -> 16679821 | AD15: =SUM(H15:O15) -> 3929213.9 | AE15: =SUM(P15:AA15) -> 12750607
A17: =Revenue!A17 -> CS Collect | C17: =Revenue!C17 -> 0 | D17: =Revenue!D17 -> 0 | E17: =Revenue!E17 -> 0 | F17: =Revenue!F17 -> 0 | G17: =Revenue!G17 -> 0 | H17: =Revenue!H17 -> 0 | I17: =Revenue!I17 -> 0 | J17: =Revenue!J17 -> 0 | ... AA17: =Revenue!AA17 -> 0 | AC17: =SUM(H17:AA17) -> -117635.97 | AD17: =SUM(H17:O17) -> 0 | AE17: =SUM(P17:AA17) -> -117635.97
A18: =Revenue!A18 -> Cosign Reserve Account | C18: =Revenue!C18 -> 0 | D18: =Revenue!D18 -> 0 | E18: =Revenue!E18 -> 0 | F18: =Revenue!F18 -> 0 | G18: =Revenue!G18 -> 0 | H18: =Revenue!H18 -> 2754.8425 | I18: =Revenue!I18 -> 10045.595 | J18: =Revenue!J18 -> 17839.969 | ... AA18: =Revenue!AA18 -> 40998.014 | AC18: =SUM(H18:AA18) -> 416995.52 | AD18: =SUM(H18:O18) -> 98230.348 | AE18: =SUM(P18:AA18) -> 318765.17
A19: =Revenue!A19 -> Total $ in Reserve Account EOM | C19: =Revenue!C19 -> 0 | D19: =Revenue!D19 -> 0 | E19: =Revenue!E19 -> 0 | F19: =Revenue!F19 -> 0 | G19: =Revenue!G19 -> 0 | H19: =Revenue!H19 -> 2754.8425 | I19: =Revenue!I19 -> 12800.438 | J19: =Revenue!J19 -> 30640.406 | ... AA19: =Revenue!AA19 -> 299359.55 | AC19: =+AA19 -> 299359.55 | AD19: =+O19 -> 98230.348 | AE19: =+AA19 -> 299359.55
A20: =Revenue!A20 -> Total $ on Loan (Outstanding Loans) EOM | C20: =Revenue!C20 -> 0 | D20: =Revenue!D20 -> 0 | E20: =Revenue!E20 -> 0 | F20: =Revenue!F20 -> 0 | G20: =Revenue!G20 -> 0 | H20: =Revenue!H20 -> 110193.7 | I20: =Revenue!I20 -> 512017.5 | J20: =Revenue!J20 -> 1225616.2 | ... AA20: =Revenue!AA20 -> 16562185 | AC20: =+AA20 -> 16562185 | AD20: =+O20 -> 3929213.9 | AE20: =+AA20 -> 16562185
A22: INCOME STATEMENT
A24: Revenue | B24: =Settings!$C$6 -> CAD | C24: =SUM(C25:C27) -> #REF! | D24: =SUM(D25:D27) -> #REF! | E24: =SUM(E25:E27) -> #REF! | F24: =SUM(F25:F27) -> #REF! | G24: =SUM(G25:G27) -> #REF! | H24: =SUM(H25:H27) -> 11019.37 | I24: =SUM(I25:I27) -> 40182.38 | J24: =SUM(J25:J27) -> 71359.875 | ... AA24: =SUM(AA25:AA27) -> 163992.06 | AC24: =SUM(H24:AA24) -> 1667982.1 | AD24: =SUM(H24:O24) -> 392921.39 | AE24: =SUM(P24:AA24) -> 1275060.7
A25: =+Revenue!A25 -> Borrower Fees | B25: =Settings!$C$6 -> CAD | C25: =Revenue!#REF! -> #REF! | D25: =Revenue!#REF! -> #REF! | E25: =Revenue!#REF! -> #REF! | F25: =Revenue!#REF! -> #REF! | G25: =Revenue!#REF! -> #REF! | H25: =+Revenue!H25 -> 11019.37 | I25: =+Revenue!I25 -> 40182.38 | J25: =+Revenue!J25 -> 71359.875 | K25: =+Revenue!K25 -> 64513.301 | L25: =+Revenue!L25 -> 48562.917 | M25: =+Revenue!M25 -> 58672.416 | N25: =+Revenue!N25 -> 55357.984 | O25: =+Revenue!O25 -> 43253.15 | ... AA25: =+Revenue!AA25 -> 163992.06 | AC25: =SUM(H25:AA25) -> 1667982.1 | AD25: =SUM(H25:O25) -> 392921.39 | AE25: =SUM(P25:AA25) -> 1275060.7
A26: =+Revenue!A26 -> Collected on Defaulted Loans | B26: =Settings!$C$6 -> CAD | C26: =Revenue!#REF! -> #REF! | D26: =Revenue!#REF! -> #REF! | E26: =Revenue!#REF! -> #REF! | F26: =Revenue!#REF! -> #REF! | G26: =Revenue!#REF! -> #REF! | H26: =+Revenue!H26 -> 0 | I26: =+Revenue!I26 -> 0 | J26: =+Revenue!J26 -> 0 | K26: =+Revenue!K26 -> 0 | L26: =+Revenue!L26 -> 0 | M26: =+Revenue!M26 -> 0 | N26: =+Revenue!N26 -> 0 | O26: =+Revenue!O26 -> 0 | ... AA26: =+Revenue!AA26 -> 0 | AC26: =SUM(H26:AA26) -> 0 | AD26: =SUM(H26:O26) -> 0 | AE26: =SUM(P26:AA26) -> 0
A27: =+Revenue!A27 -> NSF Fees Collected | B27: =Settings!$C$6 -> CAD | C27: =Revenue!#REF! -> #REF! | D27: =Revenue!#REF! -> #REF! | E27: =Revenue!#REF! -> #REF! | F27: =Revenue!#REF! -> #REF! | G27: =Revenue!#REF! -> #REF! | H27: =+Revenue!H27 -> 0 | I27: =+Revenue!I27 -> 0 | J27: =+Revenue!J27 -> 0 | K27: =+Revenue!K27 -> 0 | L27: =+Revenue!L27 -> 0 | M27: =+Revenue!M27 -> 0 | N27: =+Revenue!N27 -> 0 | O27: =+Revenue!O27 -> 0 | ... AA27: =+Revenue!AA27 -> 0 | AC27: =SUM(H27:AA27) -> 0 | AD27: =SUM(H27:O27) -> 0 | AE27: =SUM(P27:AA27) -> 0
AC28: =SUM(H28:AA28) -> 0 | AD28: =SUM(H28:O28) -> 0 | AE28: =SUM(P28:AA28) -> 0
A29: COS | B29: =Settings!$C$6 -> CAD | C29: =SUM(C30:C31) -> #REF! | D29: =SUM(D30:D31) -> #REF! | E29: =SUM(E30:E31) -> #REF! | F29: =SUM(F30:F31) -> #REF! | G29: =SUM(G30:G31) -> #REF! | H29: =SUM(H30:H31) -> 0 | I29: =SUM(I30:I31) -> 0 | J29: =SUM(J30:J31) -> 0 | ... AA29: =SUM(AA30:AA31) -> 0 | AC29: =SUM(H29:AA29) -> -161992.15 | AD29: =SUM(H29:O29) -> 0 | AE29: =SUM(P29:AA29) -> -161992.15
A30: ='COS and SG&A'!A34 -> Lender Admin Fee | B30: =Settings!$C$6 -> CAD | C30: ='COS and SG&A'!C34 -> 0 | D30: ='COS and SG&A'!D34 -> 0 | E30: ='COS and SG&A'!E34 -> 0 | F30: ='COS and SG&A'!F34 -> 0 | G30: ='COS and SG&A'!G34 -> 0 | H30: ='COS and SG&A'!H34 -> 0 | I30: ='COS and SG&A'!I34 -> 0 | J30: ='COS and SG&A'!J34 -> 0 | ... T30: ='COS and SG&A'!T34 -> 0 | U30: ='COS and SG&A'!AB34 -> 0 | V30: ='COS and SG&A'!AC34 -> -80996.077 | W30: ='COS and SG&A'!AD34 -> 0 | X30: ='COS and SG&A'!AE34 -> -80996.077 | Y30: ='COS and SG&A'!AF34 -> 0 | Z30: ='COS and SG&A'!AG34 -> 0 | AA30: ='COS and SG&A'!AH34 -> 0 | AC30: =SUM(H30:AA30) -> -161992.15 | AD30: =SUM(H30:O30) -> 0 | AE30: =SUM(P30:AA30) -> -161992.15
A31: ='COS and SG&A'!A35 -> Borower Payout Bonus | B31: =Settings!$C$6 -> CAD | C31: ='COS and SG&A'!C35 -> #REF! | D31: ='COS and SG&A'!D35 -> #REF! | E31: ='COS and SG&A'!E35 -> #REF! | F31: ='COS and SG&A'!F35 -> #REF! | G31: ='COS and SG&A'!G35 -> #REF! | H31: ='COS and SG&A'!H35 -> 0 | I31: ='COS and SG&A'!I35 -> 0 | J31: ='COS and SG&A'!J35 -> 0 | ... T31: ='COS and SG&A'!T35 -> 0 | U31: ='COS and SG&A'!AB35 -> 0 | V31: ='COS and SG&A'!AC35 -> 0 | W31: ='COS and SG&A'!AD35 -> 0 | X31: ='COS and SG&A'!AE35 -> 0 | Y31: ='COS and SG&A'!AF35 -> 0 | Z31: ='COS and SG&A'!AG35 -> 0 | AA31: ='COS and SG&A'!AH35 -> 0 | AC31: =SUM(H31:AA31) -> 0 | AD31: =SUM(H31:O31) -> 0 | AE31: =SUM(P31:AA31) -> 0
A32: Gross Profit | B32: =Settings!$C$6 -> CAD | C32: =C24+C29 -> #REF! | D32: =D24+D29 -> #REF! | E32: =E24+E29 -> #REF! | F32: =F24+F29 -> #REF! | G32: =G24+G29 -> #REF! | H32: =H24+H29 -> 11019.37 | I32: =I24+I29 -> 40182.38 | J32: =J24+J29 -> 71359.875 | ... AA32: =AA24+AA29 -> 163992.06 | AC32: =AC24+AC29 -> 1505989.9 | AD32: =AD24+AD29 -> 392921.39 | AE32: =AE24+AE29 -> 1113068.5
A33: Gross margin | B33: % | C33: =IFERROR(C32/C$24,"-") -> - | D33: =IFERROR(D32/D$24,"-") -> - | E33: =IFERROR(E32/E$24,"-") -> - | F33: =IFERROR(F32/F$24,"-") -> - | G33: =IFERROR(G32/G$24,"-") -> - | H33: =IFERROR(H32/H$24,"-") -> 1 | I33: =IFERROR(I32/I$24,"-") -> 1 | J33: =IFERROR(J32/J$24,"-") -> 1 | ... AA33: =IFERROR(AA32/AA$24,"-") -> 1 | AC33: =IFERROR(AC32/AC$24,"-") -> 0.90288136 | AD33: =IFERROR(AD32/AD$24,"-") -> 1 | AE33: =IFERROR(AE32/AE$24,"-") -> 0.87295338
A35: SG&A | B35: =Settings!$C$6 -> CAD | C35: =SUM(C36:C42) -> 0 | D35: =SUM(D36:D42) -> 0 | E35: =SUM(E36:E42) -> 0 | F35: =SUM(F36:F42) -> 0 | G35: =SUM(G36:G42) -> 0 | H35: =SUM(H36:H42) -> -739.8867 | I35: =SUM(I36:I42) -> -739.8867 | J35: =SUM(J36:J42) -> -739.8867 | ... AA35: =SUM(AA36:AA42) -> -55429.901 | AC35: =SUM(H35:AA35) -> -234370.75 | AD35: =SUM(H35:O35) -> -16369.094 | AE35: =SUM(P35:AA35) -> -218001.66
A36: ='COS and SG&A'!A23 -> COST OF SERVICE | B36: =Settings!$C$6 -> CAD | H36: ='COS and SG&A'!H23 -> 0 | I36: ='COS and SG&A'!I23 -> 0 | J36: ='COS and SG&A'!J23 -> 0 | K36: ='COS and SG&A'!K23 -> 0 | L36: ='COS and SG&A'!L23 -> 0 | M36: ='COS and SG&A'!M23 -> 0 | N36: ='COS and SG&A'!N23 -> 0 | O36: ='COS and SG&A'!O23 -> 0 | ... AA36: ='COS and SG&A'!AA23 -> -40998.014
A37: ='COS and SG&A'!A24 -> PAYROLL | B37: =Settings!$C$6 -> CAD | C37: ='COS and SG&A'!C24 -> 0 | D37: ='COS and SG&A'!D24 -> 0 | E37: ='COS and SG&A'!E24 -> 0 | F37: ='COS and SG&A'!F24 -> 0 | G37: ='COS and SG&A'!G24 -> 0 | H37: ='COS and SG&A'!H24 -> 0 | I37: ='COS and SG&A'!I24 -> 0 | J37: ='COS and SG&A'!J24 -> 0 | ... AA37: ='COS and SG&A'!AA24 -> -9975 | AC37: =SUM(H37:T37) -> -47975 | AD37: =SUM(I37:U37) -> -58900 | AE37: =SUM(J37:V37) -> -69825
A38: ='COS and SG&A'!A25 -> MARKETING & GROWTH | B38: =Settings!$C$6 -> CAD | C38: ='COS and SG&A'!C25 -> 0 | D38: ='COS and SG&A'!D25 -> 0 | E38: ='COS and SG&A'!E25 -> 0 | F38: ='COS and SG&A'!F25 -> 0 | G38: ='COS and SG&A'!G25 -> 0 | H38: ='COS and SG&A'!H25 -> 0 | I38: ='COS and SG&A'!I25 -> 0 | J38: ='COS and SG&A'!J25 -> 0 | ... AA38: ='COS and SG&A'!AA25 -> -3717 | AC38: =SUM(H38:T38) -> -435 | AD38: =SUM(I38:U38) -> -1199.43 | AE38: =SUM(J38:V38) -> -2087.36
A39: ='COS and SG&A'!A26 -> ADVISORY & PROF. SERVICES | B39: =Settings!$C$6 -> CAD | C39: ='COS and SG&A'!C26 -> 0 | D39: ='COS and SG&A'!D26 -> 0 | E39: ='COS and SG&A'!E26 -> 0 | F39: ='COS and SG&A'!F26 -> 0 | G39: ='COS and SG&A'!G26 -> 0 | H39: ='COS and SG&A'!H26 -> -300 | I39: ='COS and SG&A'!I26 -> -300 | J39: ='COS and SG&A'!J26 -> -300 | ... AA39: ='COS and SG&A'!AA26 -> -300 | AC39: =SUM(H39:T39) -> -3900 | AD39: =SUM(I39:U39) -> -3900 | AE39: =SUM(J39:V39) -> -3900
A40: ='COS and SG&A'!A27 -> RENT | B40: =Settings!$C$6 -> CAD | C40: ='COS and SG&A'!C27 -> 0 | D40: ='COS and SG&A'!D27 -> 0 | E40: ='COS and SG&A'!E27 -> 0 | F40: ='COS and SG&A'!F27 -> 0 | G40: ='COS and SG&A'!G27 -> 0 | H40: ='COS and SG&A'!H27 -> 0 | I40: ='COS and SG&A'!I27 -> 0 | J40: ='COS and SG&A'!J27 -> 0 | ... AA40: ='COS and SG&A'!AA27 -> 0 | AC40: =SUM(H40:T40) -> 0 | AD40: =SUM(I40:U40) -> 0 | AE40: =SUM(J40:V40) -> 0
A41: ='COS and SG&A'!A28 -> SERVICE AGREEMENTS | B41: =Settings!$C$6 -> CAD | C41: ='COS and SG&A'!C28 -> 0 | D41: ='COS and SG&A'!D28 -> 0 | E41: ='COS and SG&A'!E28 -> 0 | F41: ='COS and SG&A'!F28 -> 0 | G41: ='COS and SG&A'!G28 -> 0 | H41: ='COS and SG&A'!H28 -> 0 | I41: ='COS and SG&A'!I28 -> 0 | J41: ='COS and SG&A'!J28 -> 0 | ... AA41: ='COS and SG&A'!AA28 -> 0 | AC41: =SUM(H41:T41) -> 0 | AD41: =SUM(I41:U41) -> 0 | AE41: =SUM(J41:V41) -> 0
A42: ='COS and SG&A'!A29 -> OTHER EXPENSES | B42: =Settings!$C$6 -> CAD | C42: ='COS and SG&A'!C29 -> 0 | D42: ='COS and SG&A'!D29 -> 0 | E42: ='COS and SG&A'!E29 -> 0 | F42: ='COS and SG&A'!F29 -> 0 | G42: ='COS and SG&A'!G29 -> 0 | H42: ='COS and SG&A'!H29 -> -439.8867 | I42: ='COS and SG&A'!I29 -> -439.8867 | J42: ='COS and SG&A'!J29 -> -439.8867 | ... AA42: ='COS and SG&A'!AA29 -> -439.8867 | AC42: =SUM(H42:T42) -> -5718.5271 | AD42: =SUM(I42:U42) -> -5718.5271 | AE42: =SUM(J42:V42) -> -5718.5271
A43: EBITDA | B43: =Settings!$C$6 -> CAD | C43: =C32+C35 -> #REF! | D43: =D32+D35 -> #REF! | E43: =E32+E35 -> #REF! | F43: =F32+F35 -> #REF! | G43: =G32+G35 -> #REF! | H43: =H32+H35 -> 10279.483 | I43: =I32+I35 -> 39442.493 | J43: =J32+J35 -> 70619.988 | ... AA43: =AA32+AA35 -> 108562.16 | AC43: =AC32+AC35 -> 1271619.2 | AD43: =AD32+AD35 -> 376552.3 | AE43: =AE32+AE35 -> 895066.88
A44: EBITDA margin | B44: % | C44: =IFERROR(MAX((C43/C$24),0),"-") -> - | D44: =IFERROR(MAX((D43/D$24),0),"-") -> - | E44: =IFERROR(MAX((E43/E$24),0),"-") -> - | F44: =IFERROR(MAX((F43/F$24),0),"-") -> - | G44: =IFERROR(MAX((G43/G$24),0),"-") -> - | H44: =IFERROR(MAX((H43/H$24),0),"-") -> 0.93285581 | I44: =IFERROR(MAX((I43/I$24),0),"-") -> 0.98158679 | J44: =IFERROR(MAX((J43/J$24),0),"-") -> 0.98963161 | ... AA44: =IFERROR(MAX((AA43/AA$24),0),"-") -> 0.66199643 | AC44: =IFERROR(MAX((AC43/AC$24),0),"-") -> 0.76236981 | AD44: =IFERROR(MAX((AD43/AD$24),0),"-") -> 0.95834003 | AE44: =IFERROR(MAX((AE43/AE$24),0),"-") -> 0.70197982
A46: D&A | B46: =Settings!$C$6 -> CAD | C46: ='WK+CAPEX'!C71 -> 0 | D46: ='WK+CAPEX'!D71 -> 0 | E46: ='WK+CAPEX'!E71 -> 0 | F46: ='WK+CAPEX'!F71 -> 0 | G46: ='WK+CAPEX'!G71 -> 0 | H46: ='WK+CAPEX'!H71 -> 0 | I46: ='WK+CAPEX'!I71 -> 0 | J46: ='WK+CAPEX'!J71 -> 0 | ... AA46: ='WK+CAPEX'!AA71 -> 0
A47: EBIT | B47: =Settings!$C$6 -> CAD | C47: =C43+C46 -> #REF! | D47: =D43+D46 -> #REF! | E47: =E43+E46 -> #REF! | F47: =F43+F46 -> #REF! | G47: =G43+G46 -> #REF! | H47: =H43+H46 -> 10279.483 | I47: =I43+I46 -> 39442.493 | J47: =J43+J46 -> 70619.988 | ... AA47: =AA43+AA46 -> 108562.16 | AC47: =AC43+AC46 -> 1271619.2 | AD47: =AD43+AD46 -> 376552.3 | AE47: =AE43+AE46 -> 895066.88
A48: EBIT margin | C48: =IFERROR(MAX((C47/C$24),0),"-") -> - | D48: =IFERROR(MAX((D47/D$24),0),"-") -> - | E48: =IFERROR(MAX((E47/E$24),0),"-") -> - | F48: =IFERROR(MAX((F47/F$24),0),"-") -> - | G48: =IFERROR(MAX((G47/G$24),0),"-") -> - | H48: =IFERROR(MAX((H47/H$24),0),"-") -> 0.93285581 | I48: =IFERROR(MAX((I47/I$24),0),"-") -> 0.98158679 | J48: =IFERROR(MAX((J47/J$24),0),"-") -> 0.98963161 | ... AA48: =IFERROR(MAX((AA47/AA$24),0),"-") -> 0.66199643 | AC48: =IFERROR(MAX((AC47/AC$24),0),"-") -> 0.76236981 | AD48: =IFERROR(MAX((AD47/AD$24),0),"-") -> 0.95834003 | AE48: =IFERROR(MAX((AE47/AE$24),0),"-") -> 0.70197982
A50: Interest expense | B50: =Settings!$C$6 -> CAD | C50: =C73*(Settings!$C$24/12) -> 0 | D50: =D73*(Settings!$C$24/12) -> 0 | E50: =E73*(Settings!$C$24/12) -> 0 | F50: =F73*(Settings!$C$24/12) -> 0 | G50: =G73*(Settings!$C$24/12) -> 0 | H50: =H73*(Settings!$C$24/12) -> 0 | I50: =I73*(Settings!$C$24/12) -> 0 | J50: =J73*(Settings!$C$24/12) -> 0 | ... AA50: =AA73*(Settings!$C$24/12) -> 0 | AC50: =AC73*(Settings!$C$24/12) -> 0 | AD50: =AD73*(Settings!$C$24/12) -> 0 | AE50: =AE73*(Settings!$C$24/12) -> 0
A51: Income taxes | B51: =Settings!$C$6 -> CAD
A52: Net income | B52: =Settings!$C$6 -> CAD | C52: =C47-C50-C51 -> #REF! | D52: =D47-D50-D51 -> #REF! | E52: =E47-E50-E51 -> #REF! | F52: =F47-F50-F51 -> #REF! | G52: =G47-G50-G51 -> #REF! | H52: =H47-H50-H51 -> 10279.483 | I52: =I47-I50-I51 -> 39442.493 | J52: =J47-J50-J51 -> 70619.988 | ... AA52: =AA47-AA50-AA51 -> 108562.16 | AC52: =AC47-AC50-AC51 -> 1271619.2 | AD52: =AD47-AD50-AD51 -> 376552.3 | AE52: =AE47-AE50-AE51 -> 895066.88
A53: Net margin | C53: =IFERROR(MAX((C52/C$24),0),"-") -> - | D53: =IFERROR(MAX((D52/D$24),0),"-") -> - | E53: =IFERROR(MAX((E52/E$24),0),"-") -> - | F53: =IFERROR(MAX((F52/F$24),0),"-") -> - | G53: =IFERROR(MAX((G52/G$24),0),"-") -> - | H53: =IFERROR(MAX((H52/H$24),0),"-") -> 0.93285581 | I53: =IFERROR(MAX((I52/I$24),0),"-") -> 0.98158679 | J53: =IFERROR(MAX((J52/J$24),0),"-") -> 0.98963161 | ... AA53: =IFERROR(MAX((AA52/AA$24),0),"-") -> 0.66199643 | AC53: =IFERROR(MAX((AC52/AC$24),0),"-") -> 0.76236981 | AD53: =IFERROR(MAX((AD52/AD$24),0),"-") -> 0.95834003 | AE53: =IFERROR(MAX((AE52/AE$24),0),"-") -> 0.70197982
A56: BALANCE SHEET
A58: Operating cash | B58: =Settings!$C$6 -> CAD | C58: ='WK+CAPEX'!C20 -> 0 | D58: ='WK+CAPEX'!D20 -> 0 | E58: ='WK+CAPEX'!E20 -> 0 | F58: ='WK+CAPEX'!F20 -> 0 | G58: ='WK+CAPEX'!G20 -> 0 | H58: ='WK+CAPEX'!H20 -> 0 | I58: ='WK+CAPEX'!I20 -> 0 | J58: ='WK+CAPEX'!J20 -> 0 | ... AA58: ='WK+CAPEX'!AA20 -> 0 | AC58: =SUM(H58:T58) -> 0 | AD58: =SUM(I58:U58) -> 0 | AE58: =SUM(J58:V58) -> 0
A59: Excess cash | B59: =Settings!$C$6 -> CAD | C59: =SUM(C84-SUM(C58,C60:C62,C69)) -> #REF! | D59: =SUM(D84-SUM(D58,D60:D62,D69)) -> #REF! | E59: =SUM(E84-SUM(E58,E60:E62,E69)) -> #REF! | F59: =SUM(F84-SUM(F58,F60:F62,F69)) -> #REF! | G59: =SUM(G84-SUM(G58,G60:G62,G69)) -> #REF! | H59: =SUM(H84-SUM(H58,H60:H62,H69)) -> -3494.7292 | I59: =SUM(I84-SUM(I58,I60:I62,I69)) -> -505.9984 | J59: =SUM(J84-SUM(J58,J60:J62,J69)) -> 31142.121 | ... AA59: =SUM(AA84-SUM(AA58,AA60:AA62,AA69)) -> 1066629.1 | AC59: =+T59 -> 619529.86 | AD59: =+U59 -> 699237.93 | AE59: =+V59 -> 732167.82
A60: Accounts receivable | B60: =Settings!$C$6 -> CAD | C60: ='WK+CAPEX'!C25 -> #REF! | D60: ='WK+CAPEX'!D25 -> #REF! | E60: ='WK+CAPEX'!E25 -> #REF! | F60: ='WK+CAPEX'!F25 -> #REF! | G60: ='WK+CAPEX'!G25 -> #REF! | H60: =+H25 -> 11019.37 | I60: =+I25 -> 40182.38 | J60: =+J25 -> 71359.875 | K60: =+K25 -> 64513.301 | L60: =+L25 -> 48562.917 | M60: =+M25 -> 58672.416 | N60: =+N25 -> 55357.984 | O60: =+O25 -> 43253.15 | ... AA60: =+AA25 -> 163992.06 | AC60: =SUM(H60:T60) -> 812313.17 | AD60: =SUM(I60:U60) -> 932134.1 | AE60: =SUM(J60:V60) -> 1018751.7
A61: Inventories | B61: =Settings!$C$6 -> CAD
A62: Prepaid expenses | B62: =Settings!$C$6 -> CAD
A63: Current Assets | B63: =Settings!$C$6 -> CAD | C63: =SUM(C58:C62) -> #REF! | D63: =SUM(D58:D62) -> #REF! | E63: =SUM(E58:E62) -> #REF! | F63: =SUM(F58:F62) -> #REF! | G63: =SUM(G58:G62) -> #REF! | H63: =SUM(H58:H62) -> 7524.6408 | I63: =SUM(I58:I62) -> 39676.382 | J63: =SUM(J58:J62) -> 102502 | ... AA63: =SUM(AA58:AA62) -> 1230621.2 | AC63: =SUM(AC58:AC62) -> 1431843 | AD63: =SUM(AD58:AD62) -> 1631372 | AE63: =SUM(AE58:AE62) -> 1750919.5
A65: PP&E (net) | B65: =Settings!$C$6 -> CAD | C65: ='WK+CAPEX'!C37 -> 0 | D65: ='WK+CAPEX'!D37 -> 0 | E65: ='WK+CAPEX'!E37 -> 0 | F65: ='WK+CAPEX'!F37 -> 0 | G65: ='WK+CAPEX'!G37 -> 0 | H65: ='WK+CAPEX'!H37 -> 0 | I65: ='WK+CAPEX'!I37 -> 0 | J65: ='WK+CAPEX'!J37 -> 0 | ... AA65: ='WK+CAPEX'!AA37 -> 0 | AC65: =SUM(H65:T65) -> 0 | AD65: =SUM(I65:U65) -> 0 | AE65: =SUM(J65:V65) -> 0
A66: Intangible assets | B66: =Settings!$C$6 -> CAD
A67: Investments | B67: =Settings!$C$6 -> CAD
A68: Other assets (net) | B68: =Settings!$C$6 -> CAD
A69: Non-Current Assets | B69: =Settings!$C$6 -> CAD | C69: =SUM(C65:C68) -> 0 | D69: =SUM(D65:D68) -> 0 | E69: =SUM(E65:E68) -> 0 | F69: =SUM(F65:F68) -> 0 | G69: =SUM(G65:G68) -> 0 | H69: =SUM(H65:H68) -> 0 | I69: =SUM(I65:I68) -> 0 | J69: =SUM(J65:J68) -> 0 | ... AA69: =SUM(AA65:AA68) -> 0 | AC69: =SUM(AC65:AC68) -> 0 | AD69: =SUM(AD65:AD68) -> 0 | AE69: =SUM(AE65:AE68) -> 0
B70: =Settings!$C$6 -> CAD
A71: Total Assets | B71: =Settings!$C$6 -> CAD | C71: =SUM(C63,C69) -> #REF! | D71: =SUM(D63,D69) -> #REF! | E71: =SUM(E63,E69) -> #REF! | F71: =SUM(F63,F69) -> #REF! | G71: =SUM(G63,G69) -> #REF! | H71: =SUM(H63,H69) -> 7524.6408 | I71: =SUM(I63,I69) -> 39676.382 | J71: =SUM(J63,J69) -> 102502 | ... AA71: =SUM(AA63,AA69) -> 1230621.2 | AC71: =SUM(AC63,AC69) -> 1431843 | AD71: =SUM(AD63,AD69) -> 1631372 | AE71: =SUM(AE63,AE69) -> 1750919.5
B72: =Settings!$C$6 -> CAD
A73: Financial obligations (Debt) | B73: =Settings!$C$6 -> CAD | C73: 0 | D73: =C73+D91/(1-Settings!$C$23)-D91 -> 0 | E73: =D73+E91/(1-Settings!$C$23)-E91 -> 0 | F73: =E73+F91/(1-Settings!$C$23)-F91 -> 0 | G73: =F73+G91/(1-Settings!$C$23)-G91 -> 0 | H73: =G73+H91/(1-Settings!$C$23)-H91 -> 0 | I73: =H73+I91/(1-Settings!$C$23)-I91 -> 0 | J73: =I73+J91/(1-Settings!$C$23)-J91 -> 0 | K73: =J73+K91/(1-Settings!$C$23)-K91 -> 0 | ... AA73: =Z73+AA91/(1-Settings!$C$23)-AA91 -> 0 | AC73: =T73+AC91/(1-Settings!$C$23)-AC91 -> 0 | AD73: =U73+AD91/(1-Settings!$C$23)-AD91 -> 0 | AE73: =V73+AE91/(1-Settings!$C$23)-AE91 -> 0
A74: Accounts payable | B74: =Settings!$C$6 -> CAD | C74: ='WK+CAPEX'!C33 -> 0 | D74: ='WK+CAPEX'!D33 -> 0 | E74: ='WK+CAPEX'!E33 -> 0 | F74: ='WK+CAPEX'!F33 -> 0 | G74: ='WK+CAPEX'!G33 -> 0 | H74: =H17 -> 0 | I74: =I17 -> 0 | J74: =J17 -> 0 | K74: =K17 -> 0 | L74: =L17 -> 0 | M74: =M17 -> 0 | N74: =N17 -> 0 | O74: =O17 -> 0 | ... AA74: =AA17 -> 0 | AC74: =SUM(H74:T74) -> -33799.06 | AD74: =SUM(I74:U74) -> -43706.38 | AE74: =SUM(J74:V74) -> -58985.29
A75: AFDA | B75: =Settings!$C$6 -> CAD | H75: =-H18 -> -2754.8425 | I75: =-I18 -> -10045.595 | J75: =-J18 -> -17839.969 | K75: =-K18 -> -16128.325 | L75: =-L18 -> -12140.729 | M75: =-M18 -> -14668.104 | N75: =-N18 -> -13839.496 | O75: =-O18 -> -10813.288 | ... AA75: =-AA18 -> -40998.014 | AC75: =SUM(H75:T75) -> -203078.29 | AD75: =SUM(I75:U75) -> -233033.53 | AE75: =SUM(J75:V75) -> -254687.93
A76: Unearned revenues | B76: =Settings!$C$6 -> CAD
A77: Total Liabilities | B77: =Settings!$C$6 -> CAD | C77: =SUM(C73:C76) -> 0 | D77: =SUM(D73:D76) -> 0 | E77: =SUM(E73:E76) -> 0 | F77: =SUM(F73:F76) -> 0 | G77: =SUM(G73:G76) -> 0 | H77: =SUM(H73:H76) -> -2754.8425 | I77: =SUM(I73:I76) -> -10045.595 | J77: =SUM(J73:J76) -> -17839.969 | ... AA77: =SUM(AA73:AA76) -> -40998.014 | AC77: =SUM(AC73:AC76) -> -236877.35 | AD77: =SUM(AD73:AD76) -> -276739.91 | AE77: =SUM(AE73:AE76) -> -313673.22
B78: =Settings!$C$6 -> CAD
A79: Common equity | B79: =Settings!$C$6 -> CAD | C79: =C91 -> 0 | D79: =C79+D91 -> 0 | E79: =D79+E91 -> 0 | F79: =E79+F91 -> 0 | G79: =F79+G91 -> 0 | H79: =G79+H91 -> 0 | I79: =H79+I91 -> 0 | J79: =I79+J91 -> 0 | K79: =J79+K91 -> 0 | ... AA79: =Z79+AA91 -> 0 | AC79: =SUM(H79:T79) -> 0 | AD79: =SUM(I79:U79) -> 0 | AE79: =SUM(J79:V79) -> 0
A80: Net earnings | B80: =Settings!$C$6 -> CAD | C80: =C52 -> #REF! | D80: =D52 -> #REF! | E80: =E52 -> #REF! | F80: =F52 -> #REF! | G80: =G52 -> #REF! | H80: =H52 -> 10279.483 | I80: =I52 -> 39442.493 | J80: =J52 -> 70619.988 | ... AA80: =AA52 -> 108562.16 | AC80: =+T80 -> 94234.713 | AD80: =+U80 -> 118410.98 | AE80: =+V80 -> 33251.107
A81: Retained earnings | B81: =Settings!$C$6 -> CAD | C81: 0 | D81: =SUM(C80:C81)-D100 -> #REF! | E81: =SUM(D80:D81)-E100 -> #REF! | F81: =SUM(E80:E81)-F100 -> #REF! | G81: =SUM(F80:F81)-G100 -> #REF! | H81: 0 | I81: =SUM(H80:H81)-I100 -> 10279.483 | J81: =SUM(I80:I81)-J100 -> 49721.977 | K81: =SUM(J80:J81)-K100 -> 120341.96 | L81: =SUM(K80:K81)-L100 -> 184115.38 | M81: =SUM(L80:L81)-M100 -> 231938.41 | N81: =SUM(M80:M81)-N100 -> 289870.94 | O81: =SUM(N80:N81)-O100 -> 339264.04 | P81: =SUM(O80:O81)-P100 -> 376552.3 | ... AA81: =SUM(Z80:Z81)-AA100 -> 1163057 | AC81: =+T81 -> 660049.93 | AD81: =+U81 -> 754284.64 | AE81: =+V81 -> 872695.63
A82: Total Equity | B82: =Settings!$C$6 -> CAD | C82: =SUM(C78:C81) -> #REF! | D82: =SUM(D78:D81) -> #REF! | E82: =SUM(E78:E81) -> #REF! | F82: =SUM(F78:F81) -> #REF! | G82: =SUM(G78:G81) -> #REF! | H82: =SUM(H78:H81) -> 10279.483 | I82: =SUM(I78:I81) -> 49721.977 | J82: =SUM(J78:J81) -> 120341.96 | ... AA82: =SUM(AA78:AA81) -> 1271619.2 | AC82: =SUM(AC78:AC81) -> 754284.64 | AD82: =SUM(AD78:AD81) -> 872695.63 | AE82: =SUM(AE78:AE81) -> 905946.73
B83: =Settings!$C$6 -> CAD
A84: Total Liabilities + Equity | B84: =Settings!$C$6 -> CAD | C84: =SUM(C77,C82) -> #REF! | D84: =SUM(D77,D82) -> #REF! | E84: =SUM(E77,E82) -> #REF! | F84: =SUM(F77,F82) -> #REF! | G84: =SUM(G77,G82) -> #REF! | H84: =SUM(H77,H82) -> 7524.6408 | I84: =SUM(I77,I82) -> 39676.382 | J84: =SUM(J77,J82) -> 102502 | ... AA84: =SUM(AA77,AA82) -> 1230621.2 | AC84: =+AC82+AC77 -> 517407.29 | AD84: =+AD82+AD77 -> 595955.72 | AE84: =+AE82+AE77 -> 592273.51
A85: Check | C85: =C84-C71 -> #REF! | D85: =D84-D71 -> #REF! | E85: =E84-E71 -> #REF! | F85: =F84-F71 -> #REF! | G85: =G84-G71 -> #REF! | H85: =H84-H71 -> 0 | I85: =I84-I71 -> 0 | J85: =J84-J71 -> 0 | ... AA85: =AA84-AA71 -> 0
A88: CASH FLOW
A90: Initial cash balance | B90: =Settings!$C$6 -> CAD | C90: =Settings!C11 -> 0 | D90: =C101 -> #REF! | E90: =D101 -> #REF! | F90: =E101 -> #REF! | G90: =F101 -> #REF! | H90: 0 | I90: =H101 -> 10279.483 | J90: =I101 -> 49721.977 | K90: =J101 -> 120341.96 | L90: =K101 -> 184115.38 | M90: =L101 -> 231938.41 | N90: =M101 -> 289870.94 | O90: =N101 -> 339264.04 | P90: =O101 -> 376552.3 | ... AA90: =Z101 -> 1163058 | AC90: =+H90 -> 0 | AD90: =+I90 -> 10279.483 | AE90: =+J90 -> 49721.977
A91: Cash infusions | B91: =Settings!$C$6 -> CAD | C91: =SUM(C93) -> 0 | D91: =SUM(D93) -> 0 | E91: =SUM(E93) -> 0 | F91: =SUM(F93) -> 0 | G91: =SUM(G93) -> 0 | H91: =SUM(H93) -> 0 | I91: =SUM(I93) -> 0 | J91: =SUM(J93) -> 0 | ... AA91: =SUM(AA93) -> 0 | AC91: =SUM(AC93) -> 0 | AD91: =SUM(AD93) -> 0 | AE91: =SUM(AE93) -> 0
A92: Capital calls (share of commitment) | B92: %
A93: Investor Cash | B93: =Settings!$C$6 -> CAD | C93: =IF(C$6=Projections!$C$4,Projections!$C$5,0) -> 0 | D93: =IF(D$6=Projections!$C$4,Projections!$C$5,0) -> 0 | E93: =IF(E$6=Projections!$C$4,Projections!$C$5,0) -> 0 | F93: =IF(F$6=Projections!$C$4,Projections!$C$5,0) -> 0 | G93: =IF(G$6=Projections!$C$4,Projections!$C$5,0) -> 0 | H93: =IF(H$6=Projections!$C$4,Projections!$C$5,0) -> 0 | I93: =IF(I$6=Projections!$C$4,Projections!$C$5,0) -> 0 | J93: =IF(J$6=Projections!$C$4,Projections!$C$5,0) -> 0 | ... AA93: =IF(AA$6=Projections!$C$4,Projections!$C$5,0) -> 0 | AC93: =IF(AC$6=Projections!$C$4,Projections!$C$5,0) -> 0 | AD93: =IF(AD$6=Projections!$C$4,Projections!$C$5,0) -> 0 | AE93: =IF(AE$6=Projections!$C$4,Projections!$C$5,0) -> 0
A94: Operating change in cash | B94: =Settings!$C$6 -> CAD | C94: =C95+C96+C97-C98+C99-C100 -> #REF! | D94: =D95+D96+D97-D98+D99-D100 -> #REF! | E94: =E95+E96+E97-E98+E99-E100 -> #REF! | F94: =F95+F96+F97-F98+F99-F100 -> #REF! | G94: =G95+G96+G97-G98+G99-G100 -> #REF! | H94: =H95+H96+H97-H98+H99-H100 -> 10279.483 | I94: =I95+I96+I97-I98+I99-I100 -> 39442.493 | J94: =J95+J96+J97-J98+J99-J100 -> 70619.988 | ... AA94: =AA95+AA96+AA97-AA98+AA99-AA100 -> 108564.16 | AC94: =SUM(H94:T94) -> 754284.64 | AD94: =SUM(I94:U94) -> 862416.14 | AE94: =SUM(J94:V94) -> 856224.76
A95: Net income | B95: =Settings!$C$6 -> CAD | C95: =C52 -> #REF! | D95: =D52 -> #REF! | E95: =E52 -> #REF! | F95: =F52 -> #REF! | G95: =G52 -> #REF! | H95: =H52 -> 10279.483 | I95: =I52 -> 39442.493 | J95: =J52 -> 70619.988 | ... AA95: =AA52 -> 108562.16 | AC95: =SUM(H95:T95) -> 754284.64 | AD95: =SUM(I95:U95) -> 862416.14 | AE95: =SUM(J95:V95) -> 856224.76
A96: (+) D&A | B96: =Settings!$C$6 -> CAD | C96: =C46 -> 0 | D96: =D46 -> 0 | E96: =E46 -> 0 | F96: =F46 -> 0 | G96: =G46 -> 0 | H96: =H46 -> 0 | I96: =I46 -> 0 | J96: =J46 -> 0 | ... AA96: =AA46 -> 0 | AC96: =SUM(H96:T96) -> 0 | AD96: =SUM(I96:U96) -> 0 | AE96: =SUM(J96:V96) -> 0
A97: (+) Change in WC | B97: =Settings!$C$6 -> CAD | C97: ='WK+CAPEX'!C51 -> 0 | D97: ='WK+CAPEX'!D51 -> #REF! | E97: ='WK+CAPEX'!E51 -> #REF! | F97: ='WK+CAPEX'!F51 -> #REF! | G97: ='WK+CAPEX'!G51 -> #REF! | H97: 0 | I97: 0 | J97: 0 | K97: 0 | L97: 0 | M97: 0 | N97: 0 | O97: 0 | P97: 0 | Q97: 0 | R97: 0 | S97: 0 | T97: 0 | U97: 0 | V97: 0 | W97: 0 | X97: 0 | Y97: 0 | Z97: 1 | AA97: 2 | AC97: =SUM(H97:T97) -> 0 | AD97: =SUM(I97:U97) -> 0 | AE97: =SUM(J97:V97) -> 0
A98: (-) CAPEX | B98: =Settings!$C$6 -> CAD | C98: ='WK+CAPEX'!C61 -> 0 | D98: ='WK+CAPEX'!D61 -> 0 | E98: ='WK+CAPEX'!E61 -> 0 | F98: ='WK+CAPEX'!F61 -> 0 | G98: ='WK+CAPEX'!G61 -> 0 | H98: ='WK+CAPEX'!H61 -> 0 | I98: ='WK+CAPEX'!I61 -> 0 | J98: ='WK+CAPEX'!J61 -> 0 | ... AA98: ='WK+CAPEX'!AA61 -> 0 | AC98: =SUM(H98:T98) -> 0 | AD98: =SUM(I98:U98) -> 0 | AE98: =SUM(J98:V98) -> 0
A99: (+) Change in debt | B99: =Settings!$C$6 -> CAD | C99: =C73 -> 0 | D99: =D73-C73 -> 0 | E99: =E73-D73 -> 0 | F99: =F73-E73 -> 0 | G99: =G73-F73 -> 0 | H99: =H73-G73 -> 0 | I99: =I73-H73 -> 0 | J99: =J73-I73 -> 0 | K99: =K73-J73 -> 0 | ... AA99: =AA73-Z73 -> 0 | AC99: =SUM(H99:T99) -> 0 | AD99: =SUM(I99:U99) -> 0 | AE99: =SUM(J99:V99) -> 0
A100: (-) Dividends | B100: =Settings!$C$6 -> CAD
A101: Ending cash balance | B101: =Settings!$C$6 -> CAD | C101: =SUM(C90,C91,C94) -> #REF! | D101: =SUM(D90,D91,D94) -> #REF! | E101: =SUM(E90,E91,E94) -> #REF! | F101: =SUM(F90,F91,F94) -> #REF! | G101: =SUM(G90,G91,G94) -> #REF! | H101: =SUM(H90,H91,H94) -> 10279.483 | I101: =SUM(I90,I91,I94) -> 49721.977 | J101: =SUM(J90,J91,J94) -> 120341.96 | ... AA101: =SUM(AA90,AA91,AA94) -> 1271622.2 | AC101: =SUM(AC90,AC91,AC94) -> 754284.64 | AD101: =SUM(AD90,AD91,AD94) -> 872695.63 | AE101: =SUM(AE90,AE91,AE94) -> 905946.73
A102: Total capital requirements | B102: =Settings!$C$6 -> CAD | C102: =MIN(C101:T101)-Projections!C5 -> #REF!
D103: =SUM($C$98:D98) -> 0 | E103: =SUM($C$98:E98) -> 0 | F103: =SUM($C$98:F98) -> 0 | G103: =SUM($C$98:G98) -> 0 | H103: =SUM($C$98:H98) -> 0 | I103: =SUM($C$98:I98) -> 0 | J103: =SUM($C$98:J98) -> 0 | K103: =SUM($C$98:K98) -> 0 | ... AA103: =SUM($C$98:AA98) -> 0 | AC103: =SUM($C$98:AC98) -> 0 | AD103: =SUM($C$98:AD98) -> 0 | AE103: =SUM($C$98:AE98) -> 0
A104: VALUATION
A106: EBIT | B106: =Settings!$C$6 -> CAD | C106: =C47 -> #REF! | D106: =D47 -> #REF! | E106: =E47 -> #REF! | F106: =F47 -> #REF! | G106: =G47 -> #REF! | H106: =H47 -> 10279.483 | I106: =I47 -> 39442.493 | J106: =J47 -> 70619.988 | ... T106: =T47 -> 94234.713 | AC106: =AC47 -> 1271619.2 | AD106: =AD47 -> 376552.3 | AE106: =AE47 -> 895066.88
A107: (-) Taxes | B107: =Settings!$C$6 -> CAD | C107: =C51 -> 0 | D107: =D51 -> 0 | E107: =E51 -> 0 | F107: =F51 -> 0 | G107: =G51 -> 0 | H107: =H51 -> 0 | I107: =I51 -> 0 | J107: =J51 -> 0 | ... T107: =T51 -> 0 | AC107: =AC51 -> 0 | AD107: =AD51 -> 0 | AE107: =AE51 -> 0
A108: EBIAT | B108: =Settings!$C$6 -> CAD | C108: =C106-C107 -> #REF! | D108: =D106-D107 -> #REF! | E108: =E106-E107 -> #REF! | F108: =F106-F107 -> #REF! | G108: =G106-G107 -> #REF! | H108: =H106-H107 -> 10279.483 | I108: =I106-I107 -> 39442.493 | J108: =J106-J107 -> 70619.988 | ... T108: =T106-T107 -> 94234.713 | AC108: =AC106-AC107 -> 1271619.2 | AD108: =AD106-AD107 -> 376552.3 | AE108: =AE106-AE107 -> 895066.88
A109: (+) D&A | B109: =Settings!$C$6 -> CAD | C109: =C46 -> 0 | D109: =D46 -> 0 | E109: =E46 -> 0 | F109: =F46 -> 0 | G109: =G46 -> 0 | H109: =H46 -> 0 | I109: =I46 -> 0 | J109: =J46 -> 0 | ... T109: =T46 -> 0 | AC109: =AC46 -> 0 | AD109: =AD46 -> 0 | AE109: =AE46 -> 0
A110: Gross cash flow | B110: =Settings!$C$6 -> CAD | C110: =C108+C109 -> #REF! | D110: =D108+D109 -> #REF! | E110: =E108+E109 -> #REF! | F110: =F108+F109 -> #REF! | G110: =G108+G109 -> #REF! | H110: =H108+H109 -> 10279.483 | I110: =I108+I109 -> 39442.493 | J110: =J108+J109 -> 70619.988 | ... T110: =T108+T109 -> 94234.713 | AC110: =AC108+AC109 -> 1271619.2 | AD110: =AD108+AD109 -> 376552.3 | AE110: =AE108+AE109 -> 895066.88
A111: (-) Change in WC | B111: =Settings!$C$6 -> CAD | C111: =C97 -> 0 | D111: =D97 -> #REF! | E111: =E97 -> #REF! | F111: =F97 -> #REF! | G111: =G97 -> #REF! | H111: =H97 -> 0 | I111: =I97 -> 0 | J111: =J97 -> 0 | ... T111: =T97 -> 0 | AC111: =AC97 -> 0 | AD111: =AD97 -> 0 | AE111: =AE97 -> 0
A112: (-) CAPEX | B112: =Settings!$C$6 -> CAD | C112: =C98 -> 0 | D112: =D98 -> 0 | E112: =E98 -> 0 | F112: =F98 -> 0 | G112: =G98 -> 0 | H112: =H98 -> 0 | I112: =I98 -> 0 | J112: =J98 -> 0 | ... T112: =T98 -> 0 | AC112: =AC98 -> 0 | AD112: =AD98 -> 0 | AE112: =AE98 -> 0
A113: Free cash flow | B113: =Settings!$C$6 -> CAD | C113: =C110+C111-C112 -> #REF! | D113: =D110+D111-D112 -> #REF! | E113: =E110+E111-E112 -> #REF! | F113: =F110+F111-F112 -> #REF! | G113: =G110+G111-G112 -> #REF! | H113: =H110+H111-H112 -> 10279.483 | I113: =I110+I111-I112 -> 39442.493 | J113: =J110+J111-J112 -> 70619.988 | ... T113: =T110+T111-T112 -> 94234.713 | AC113: =AC110+AC111-AC112 -> 1271619.2 | AD113: =AD110+AD111-AD112 -> 376552.3 | AE113: =AE110+AE111-AE112 -> 895066.88

Sheet Revenue
A1: Cosign Simple
A2: Revenue | AD2: Year End Jan 31
A3: =+TODAY() -> 44539 | AD3: H:O | AE3: P:AA
C6: ='FS-Month'!C6 -> 43831 | D6: ='FS-Month'!D6 -> 43862 | E6: ='FS-Month'!E6 -> 43891 | F6: ='FS-Month'!F6 -> 43922 | G6: ='FS-Month'!G6 -> 43952 | H6: ='FS-Month'!H6 -> 43983 | I6: ='FS-Month'!I6 -> 44013 | J6: ='FS-Month'!J6 -> 44044 | ... Z6: ='FS-Month'!Z6 -> 44531 | AA6: 44583 | AC6: Total | AD6: Total | AE6: Total
B7: Unit | C7: ='FS-Month'!C7 -> 1 | D7: ='FS-Month'!D7 -> 2 | E7: ='FS-Month'!E7 -> 3 | F7: ='FS-Month'!F7 -> 4 | G7: ='FS-Month'!G7 -> 5 | H7: ='FS-Month'!H7 -> 1 | I7: ='FS-Month'!I7 -> 2 | J7: ='FS-Month'!J7 -> 3 | ... Z7: ='FS-Month'!Z7 -> 19 | AA7: ='FS-Month'!AB7 -> 0 | AC7: LTD | AD7: FY2020 | AE7: FY2021(YTD)
A9: KEY INDICATORS
A11: # of Loans | C11: 0 | D11: 0 | E11: 0 | F11: 0 | G11: 0 | H11: 31 | I11: 114 | J11: 167 | K11: 136 | L11: 95 | M11: 113 | N11: 104 | O11: 87 | P11: 113 | Q11: 199 | R11: 234 | S11: 239 | T11: 284 | U11: 332 | V11: 341 | W11: 336 | X11: 265 | Y11: 363 | Z11: =+Y11*1.025 -> 372.075 | AA11: =+Z11*1.025 -> 381.37687 | AC11: =SUM(H11:AA11) -> 4306.4519 | AD11: =SUM(H11:O11) -> 847 | AE11: =SUM(P11:AA11) -> 3459.4519
A12: Total # of Loans | C12: =C11 -> 0 | D12: =+D11+C12 -> 0 | E12: =+E11+D12 -> 0 | F12: =+F11+E12 -> 0 | G12: =+G11+F12 -> 0 | H12: =+H11+G12 -> 31 | I12: =+I11+H12 -> 145 | J12: =+J11+I12 -> 312 | K12: =+K11+J12 -> 448 | ... AA12: =+AA11+Z12 -> 4306.4519 | AC12: =+AA12 -> 4306.4519 | AD12: =+O12 -> 847 | AE12: =+AA12 -> 4306.4519
A14: Total $ on Loan (Outstanding Loans) BOM | C14: 0 | D14: =+C20 -> 0 | E14: =+D20 -> 0 | F14: =+E20 -> 0 | G14: =+F20 -> 0 | H14: =+G20 -> 0 | I14: =+H20 -> 110193.7 | J14: =+I20 -> 512017.5 | K14: =+J20 -> 1225616.2 | ... AA14: =+Z20 -> 14922264 | AC14: =AA20 -> 16562185 | AD14: =O20 -> 3929213.9 | AE14: =AA20 -> 16562185
A15: New Loans Written | C15: =C11*'CSS Settings'!B7 -> 0 | D15: =+D11*'CSS Settings'!$B$7 -> 0 | E15: =+E11*'CSS Settings'!$B$7 -> 0 | F15: =+F11*'CSS Settings'!$B$7 -> 0 | G15: =+G11*'CSS Settings'!$B$7 -> 0 | H15: 110193.7 | I15: 401823.8 | J15: 713598.75 | K15: 645133.01 | L15: 485629.17 | M15: 586724.16 | N15: 553579.84 | O15: 432531.5 | P15: 470357.4 | Q15: 843630.28 | R15: 942528.59 | S15: 874055.51 | T15: 1063346 | U15: 1308403 | V15: 1268000 | W15: 126624.05 | X15: 1120389 | Y15: 1493430 | Z15: =+Z11*'CSS Settings'!$B$7 -> 1599922.5 | AA15: =+AA11*'CSS Settings'!$B$7 -> 1639920.6 | AC15: =SUM(H15:AA15) -> 16679821 | AD15: =SUM(H15:O15) -> 3929213.9 | AE15: =SUM(P15:AA15) -> 12750607
A17: CS Collect | C17: =+C14*-'CSS Settings'!$B$9 -> 0 | D17: =+D14*-'CSS Settings'!$B$9 -> 0 | E17: =+E14*-'CSS Settings'!$B$9 -> 0 | F17: =+F14*-'CSS Settings'!$B$9 -> 0 | G17: =+G14*-'CSS Settings'!$B$9 -> 0 | H17: =+H14*-'CSS Settings'!$B$9 -> 0 | I17: 0 | J17: 0 | K17: 0 | L17: 0 | M17: 0 | N17: 0 | O17: 0 | P17: -1953.87 | Q17: -6268.78 | R17: -5014.46 | S17: -18725.42 | T17: -1836.53 | U17: -9907.32 | V17: -15278.91 | W17: -9511.05 | X17: -25618.64 | Y17: -23520.99 | Z17: 0 | AA17: 0 | AC17: =SUM(H17:AA17) -> -117635.97 | AD17: =SUM(H17:O17) -> 0 | AE17: =SUM(P17:AA17) -> -117635.97
A18: Cosign Reserve Account | C18: =(SUM(C25:C25)*'CSS Settings'!$B$19) -> 0 | D18: =(SUM(D25:D25)*'CSS Settings'!$B$19) -> 0 | E18: =(SUM(E25:E25)*'CSS Settings'!$B$19) -> 0 | F18: =(SUM(F25:F25)*'CSS Settings'!$B$19) -> 0 | G18: =(SUM(G25:G25)*'CSS Settings'!$B$19) -> 0 | H18: =(SUM(H25:H25)*'CSS Settings'!$B$19) -> 2754.8425 | I18: =(SUM(I25:I25)*'CSS Settings'!$B$19) -> 10045.595 | J18: =(SUM(J25:J25)*'CSS Settings'!$B$19) -> 17839.969 | ... AA18: =(SUM(AA25:AA25)*'CSS Settings'!$B$19) -> 40998.014 | AC18: =SUM(H18:AA18) -> 416995.52 | AD18: =SUM(H18:O18) -> 98230.348 | AE18: =SUM(P18:AA18) -> 318765.17
A19: Total $ in Reserve Account EOM | C19: =C18+C17 -> 0 | D19: =D18+D17 -> 0 | E19: =E18+E17 -> 0 | F19: =F18+F17 -> 0 | G19: =G18+G17 -> 0 | H19: =H18+H17 -> 2754.8425 | I19: =H19+I18+I17 -> 12800.438 | J19: =I19+J18+J17 -> 30640.406 | K19: =J19+K18+K17 -> 46768.732 | L19: =K19+L18+L17 -> 58909.461 | M19: =L19+M18+M17 -> 73577.565 | N19: =M19+N18+N17 -> 87417.061 | O19: =N19+O18+O17 -> 98230.348 | P19: =O19+P18+P17 -> 108035.41 | ... AA19: =Z19+AA18+AA17 -> 299359.55 | AC19: =AA19 -> 299359.55 | AD19: =O19 -> 98230.348 | AE19: =AA19 -> 299359.55
A20: Total $ on Loan (Outstanding Loans) EOM | C20: =SUM(C14:C17) -> 0 | D20: =SUM(D14:D17) -> 0 | E20: =SUM(E14:E17) -> 0 | F20: =SUM(F14:F17) -> 0 | G20: =SUM(G14:G17) -> 0 | H20: =SUM(H14:H17) -> 110193.7 | I20: =SUM(I14:I17) -> 512017.5 | J20: =SUM(J14:J17) -> 1225616.2 | ... AA20: =SUM(AA14:AA17) -> 16562185 | AC20: =+AA20 -> 16562185 | AD20: =+O20 -> 3929213.9 | AE20: =+AA20 -> 16562185
A23: Cosign Revenue from Operations
A25: Borrower Fees | C25: =(C15*'CSS Settings'!$B$12) -> 0 | D25: =(D15*'CSS Settings'!$B$12) -> 0 | E25: =(E15*'CSS Settings'!$B$12) -> 0 | F25: =(F15*'CSS Settings'!$B$12) -> 0 | G25: =(G15*'CSS Settings'!$B$12) -> 0 | H25: =(H15*'CSS Settings'!$B$12) -> 11019.37 | I25: =(I15*'CSS Settings'!$B$12) -> 40182.38 | J25: =(J15*'CSS Settings'!$B$12) -> 71359.875 | ... AA25: =(AA15*'CSS Settings'!$B$12) -> 163992.06 | AC25: =(AC15*'CSS Settings'!$B$12) -> 1667982.1 | AD25: =(AD15*'CSS Settings'!$B$12) -> 392921.39 | AE25: =(AE15*'CSS Settings'!$B$12) -> 1275060.7
A26: Collected on Defaulted Loans | C26: =ABS(C17*(1-'CSS Settings'!$B$18)*'CSS Settings'!$B$17) -> 0 | D26: =ABS(D17*(1-'CSS Settings'!$B$18)*'CSS Settings'!$B$17) -> 0 | E26: =ABS(E17*(1-'CSS Settings'!$B$18)*'CSS Settings'!$B$17) -> 0 | F26: =ABS(F17*(1-'CSS Settings'!$B$18)*'CSS Settings'!$B$17) -> 0 | G26: =ABS(G17*(1-'CSS Settings'!$B$18)*'CSS Settings'!$B$17) -> 0 | H26: 0 | I26: 0 | J26: 0 | K26: 0 | L26: 0 | M26: 0 | N26: 0 | O26: 0 | P26: 0 | Q26: 0 | R26: 0 | S26: 0 | T26: 0 | U26: 0 | V26: 0 | W26: 0 | X26: 0 | Y26: 0 | Z26: 0 | AA26: 0 | AC26: =SUM(H26:AA26) -> 0 | AD26: =SUM(I26:AB26) -> 0 | AE26: =SUM(J26:AC26) -> 0
A27: NSF Fees Collected | C27: 0 | D27: 0 | E27: 0 | F27: 0 | G27: 0 | H27: 0 | I27: 0 | J27: 0 | K27: 0 | L27: 0 | M27: 0 | N27: 0 | O27: 0 | P27: 0 | Q27: 0 | R27: 0 | S27: 0 | T27: 0 | U27: 0 | V27: 0 | W27: 0 | X27: 0 | Y27: 0 | Z27: 0 | AA27: 0 | AC27: 0 | AD27: 0 | AE27: 0
A28: Total | B28: =Settings!$C$6 -> CAD | C28: =SUM(C25:C27) -> 0 | D28: =SUM(D25:D27) -> 0 | E28: =SUM(E25:E27) -> 0 | F28: =SUM(F25:F27) -> 0 | G28: =SUM(G25:G27) -> 0 | H28: =SUM(H25:H27) -> 11019.37 | I28: =SUM(I25:I27) -> 40182.38 | J28: =SUM(J25:J27) -> 71359.875 | ... Y28: =SUM(Y25:Y27) -> 149343 | AC28: =SUM(H28:AA28) -> 1343997.8 | AD28: =SUM(H28:O28) -> 392921.39 | AE28: =SUM(P28:AA28) -> 951076.38
Z30: ='FS-Month'!Z27 -> 0 | AA30: ='FS-Month'!AB27 -> 0
A31: Revenue Source 2 | Z31: ='FS-Month'!Z28 -> 0 | AA31: ='FS-Month'!AB28 -> 0
Z35: =+Y35*1.1 -> 0 | AA35: =+Z35*1.1 -> 0
Z36: =+Z35+Y36 -> 0 | AA36: =+AA35+Z36 -> 0
Z38: =+Y44 -> 0 | AA38: =+Z44 -> 0
A39: Total | B39: =Settings!$C$6 -> CAD | Z39: 0 | AA39: 0
Z41: 0 | AA41: 0
Z42: =(SUM(Z49:Z49)*'CSS Settings'!$B$19) -> 0 | AA42: =(SUM(AA49:AA49)*'CSS Settings'!$B$19) -> 0
Z43: =Y43+Z42+Z41 -> 0 | AA43: =Z43+AA42+AA41 -> 0

Sheet COS and SG&A
A1: CosginSimple
A2: Operating Expenses
A3: =+TODAY() -> 44539 | AD3: Year End Jan 31
AD4: H:O | AE4: P:AA
C6: ='FS-Month'!C6 -> 43831 | D6: ='FS-Month'!D6 -> 43862 | E6: ='FS-Month'!E6 -> 43891 | F6: ='FS-Month'!F6 -> 43922 | G6: ='FS-Month'!G6 -> 43952 | H6: ='FS-Month'!H6 -> 43983 | I6: ='FS-Month'!I6 -> 44013 | J6: ='FS-Month'!J6 -> 44044 | ... AA6: ='FS-Month'!AA6 -> 44562 | AC6: Total | AD6: Total | AE6: Total
B7: Unit | C7: ='FS-Month'!C7 -> 1 | D7: ='FS-Month'!D7 -> 2 | E7: ='FS-Month'!E7 -> 3 | F7: ='FS-Month'!F7 -> 4 | G7: ='FS-Month'!G7 -> 5 | H7: ='FS-Month'!H7 -> 1 | I7: ='FS-Month'!I7 -> 2 | J7: ='FS-Month'!J7 -> 3 | ... AA7: ='FS-Month'!AA7 -> 20 | AC7: LTD | AD7: FY2020 | AE7: FY2021(YTD)
A9: KEY INDICATORS
A11: =Revenue!A11 -> # of Loans | C11: =Revenue!C11 -> 0 | D11: =Revenue!D11 -> 0 | E11: =Revenue!E11 -> 0 | F11: =Revenue!F11 -> 0 | G11: =Revenue!G11 -> 0 | H11: =Revenue!H11 -> 31 | I11: =Revenue!I11 -> 114 | J11: =Revenue!J11 -> 167 | ... AA11: =Revenue!AA11 -> 381.37687 | AC11: =Revenue!AC11 -> 4306.4519 | AD11: =Revenue!AD11 -> 847 | AE11: =Revenue!AE11 -> 3459.4519
A12: =Revenue!A12 -> Total # of Loans | C12: =Revenue!C12 -> 0 | D12: =Revenue!D12 -> 0 | E12: =Revenue!E12 -> 0 | F12: =Revenue!F12 -> 0 | G12: =Revenue!G12 -> 0 | H12: =Revenue!H12 -> 31 | I12: =Revenue!I12 -> 145 | J12: =Revenue!J12 -> 312 | ... AA12: =Revenue!AA12 -> 4306.4519 | AC12: =Revenue!AC12 -> 4306.4519 | AD12: =Revenue!AD12 -> 847 | AE12: =Revenue!AE12 -> 4306.4519
A14: =Revenue!A14 -> Total $ on Loan (Outstanding Loans) BOM | C14: =Revenue!C14 -> 0 | D14: =Revenue!D14 -> 0 | E14: =Revenue!E14 -> 0 | F14: =Revenue!F14 -> 0 | G14: =Revenue!G14 -> 0 | H14: =Revenue!H14 -> 0 | I14: =Revenue!I14 -> 110193.7 | J14: =Revenue!J14 -> 512017.5 | ... AA14: =Revenue!AA14 -> 14922264 | AC14: =Revenue!AC14 -> 16562185 | AD14: =Revenue!AD14 -> 3929213.9 | AE14: =Revenue!AE14 -> 16562185
A15: =Revenue!A15 -> New Loans Written | C15: =Revenue!C15 -> 0 | D15: =Revenue!D15 -> 0 | E15: =Revenue!E15 -> 0 | F15: =Revenue!F15 -> 0 | G15: =Revenue!G15 -> 0 | H15: =Revenue!H15 -> 110193.7 | I15: =Revenue!I15 -> 401823.8 | J15: =Revenue!J15 -> 713598.75 | ... AA15: =Revenue!AA15 -> 1639920.6 | AC15: =Revenue!AC15 -> 16679821 | AD15: =Revenue!AD15 -> 3929213.9 | AE15: =Revenue!AE15 -> 12750607
A17: =Revenue!A17 -> CS Collect | C17: =Revenue!C17 -> 0 | D17: =Revenue!D17 -> 0 | E17: =Revenue!E17 -> 0 | F17: =Revenue!F17 -> 0 | G17: =Revenue!G17 -> 0 | H17: =Revenue!H17 -> 0 | I17: =Revenue!I17 -> 0 | J17: =Revenue!J17 -> 0 | ... AA17: =Revenue!AA17 -> 0 | AC17: =Revenue!AC17 -> -117635.97 | AD17: =Revenue!AD17 -> 0 | AE17: =Revenue!AE17 -> -117635.97
A18: =Revenue!A18 -> Cosign Reserve Account | C18: =Revenue!C18 -> 0 | D18: =Revenue!D18 -> 0 | E18: =Revenue!E18 -> 0 | F18: =Revenue!F18 -> 0 | G18: =Revenue!G18 -> 0 | H18: =Revenue!H18 -> 2754.8425 | I18: =Revenue!I18 -> 10045.595 | J18: =Revenue!J18 -> 17839.969 | ... AA18: =Revenue!AA18 -> 40998.014 | AC18: =Revenue!AC18 -> 416995.52 | AD18: =Revenue!AD18 -> 98230.348 | AE18: =Revenue!AE18 -> 318765.17
A19: =Revenue!A19 -> Total $ in Reserve Account EOM | C19: =Revenue!C19 -> 0 | D19: =Revenue!D19 -> 0 | E19: =Revenue!E19 -> 0 | F19: =Revenue!F19 -> 0 | G19: =Revenue!G19 -> 0 | H19: =Revenue!H19 -> 2754.8425 | I19: =Revenue!I19 -> 12800.438 | J19: =Revenue!J19 -> 30640.406 | ... AA19: =Revenue!AA19 -> 299359.55 | AC19: =Revenue!AC19 -> 299359.55 | AD19: =Revenue!AD19 -> 98230.348 | AE19: =Revenue!AE19 -> 299359.55
A20: =Revenue!A20 -> Total $ on Loan (Outstanding Loans) EOM | C20: =Revenue!C20 -> 0 | D20: =Revenue!D20 -> 0 | E20: =Revenue!E20 -> 0 | F20: =Revenue!F20 -> 0 | G20: =Revenue!G20 -> 0 | H20: =Revenue!H20 -> 110193.7 | I20: =Revenue!I20 -> 512017.5 | J20: =Revenue!J20 -> 1225616.2 | ... AA20: =Revenue!AA20 -> 16562185 | AC20: =Revenue!AC20 -> 16562185 | AD20: =Revenue!AD20 -> 3929213.9 | AE20: =Revenue!AE20 -> 16562185
C21: =Revenue!C21 -> 0 | D21: =Revenue!D21 -> 0 | E21: =Revenue!E21 -> 0 | F21: =Revenue!F21 -> 0 | G21: =Revenue!G21 -> 0
A22: CONSOLIDATED SG&A
A23: =A32 -> COST OF SERVICE | B23: =Settings!$C$6 -> CAD | C23: 0 | D23: 0 | E23: 0 | F23: 0 | G23: 0 | H23: =H37 -> 0 | I23: =I37 -> 0 | J23: =J37 -> 0 | K23: =K37 -> 0 | L23: =L37 -> 0 | M23: =M37 -> 0 | N23: =N37 -> 0 | O23: =O37 -> 0 | ... AA23: =AA37 -> -40998.014 | AC23: =SUM(H23:AA23) -> -80996.077 | AD23: =SUM(H23:O23) -> 0 | AE23: =SUM(P23:AA23) -> -80996.077
A24: =A38 -> PAYROLL | B24: =Settings!$C$6 -> CAD | C24: 0 | D24: 0 | E24: 0 | F24: 0 | G24: 0 | H24: =H47 -> 0 | I24: =I47 -> 0 | J24: =J47 -> 0 | K24: =K47 -> 0 | L24: =L47 -> 0 | M24: =M47 -> 0 | N24: =N47 -> -5225 | O24: =O47 -> -5225 | ... AA24: =AA47 -> -9975 | AC24: =SUM(H24:AA24) -> -122550 | AD24: =SUM(H24:O24) -> -10450 | AE24: =SUM(P24:AA24) -> -112100
A25: =A50 -> MARKETING & GROWTH | B25: =Settings!$C$6 -> CAD | C25: 0 | D25: 0 | E25: 0 | F25: 0 | G25: 0 | H25: =H68 -> 0 | I25: =I68 -> 0 | J25: =J68 -> 0 | K25: =K68 -> 0 | L25: =L68 -> 0 | M25: =M68 -> 0 | N25: =N68 -> 0 | O25: =O68 -> 0 | ... AA25: =AA68 -> -3717 | AC25: =SUM(H25:AA25) -> -16026.94 | AD25: =SUM(H25:O25) -> 0 | AE25: =SUM(P25:AA25) -> -16026.94
A26: =A70 -> ADVISORY & PROF. SERVICES | B26: =Settings!$C$6 -> CAD | C26: 0 | D26: 0 | E26: 0 | F26: 0 | G26: 0 | H26: =H78 -> -300 | I26: =I78 -> -300 | J26: =J78 -> -300 | K26: =K78 -> -300 | L26: =L78 -> -300 | M26: =M78 -> -300 | N26: =N78 -> -300 | O26: =O78 -> -300 | ... AA26: =AA78 -> -300 | AC26: =SUM(H26:AA26) -> -6000 | AD26: =SUM(H26:O26) -> -2400 | AE26: =SUM(P26:AA26) -> -3600
A27: =A80 -> RENT | B27: =Settings!$C$6 -> CAD | C27: 0 | D27: 0 | E27: 0 | F27: 0 | G27: 0 | H27: =H83 -> 0 | I27: =I83 -> 0 | J27: =J83 -> 0 | K27: =K83 -> 0 | L27: =L83 -> 0 | M27: =M83 -> 0 | N27: =N83 -> 0 | O27: =O83 -> 0 | ... Z27: =Z83 -> 0 | AA27: 0 | AC27: =SUM(H27:AA27) -> 0 | AD27: =SUM(H27:O27) -> 0 | AE27: =SUM(P27:AA27) -> 0
A28: =A86 -> SERVICE AGREEMENTS | B28: =Settings!$C$6 -> CAD | C28: 0 | D28: 0 | E28: 0 | F28: 0 | G28: 0 | H28: =H90 -> 0 | I28: =I90 -> 0 | J28: =J90 -> 0 | K28: =K90 -> 0 | L28: =L90 -> 0 | M28: =M90 -> 0 | N28: =N90 -> 0 | O28: =O90 -> 0 | ... Z28: =Z90 -> 0 | AA28: 0 | AC28: =SUM(H28:AA28) -> 0 | AD28: =SUM(H28:O28) -> 0 | AE28: =SUM(P28:AA28) -> 0
A29: =A92 -> OTHER EXPENSES | B29: =Settings!$C$6 -> CAD | C29: 0 | D29: 0 | E29: 0 | F29: 0 | G29: 0 | H29: =H103 -> -439.8867 | I29: =I103 -> -439.8867 | J29: =J103 -> -439.8867 | K29: =K103 -> -439.8867 | L29: =L103 -> -439.8867 | M29: =M103 -> -439.8867 | N29: =N103 -> -439.8867 | O29: =O103 -> -439.8867 | ... AA29: =AA103 -> -439.8867 | AC29: =SUM(H29:AA29) -> -8797.734 | AD29: =SUM(H29:O29) -> -3519.0936 | AE29: =SUM(P29:AA29) -> -5278.6404
A30: Total | B30: =Settings!$C$6 -> CAD | C30: =SUM(C23:C29) -> 0 | D30: =SUM(D23:D29) -> 0 | E30: =SUM(E23:E29) -> 0 | F30: =SUM(F23:F29) -> 0 | G30: =SUM(G23:G29) -> 0 | H30: =SUM(H23:H29) -> -739.8867 | I30: =SUM(I23:I29) -> -739.8867 | J30: =SUM(J23:J29) -> -739.8867 | ... AA30: =SUM(AA23:AA29) -> -55429.901 | AC30: =SUM(AC23:AC29) -> -234370.75 | AD30: =SUM(AD23:AD29) -> -16369.094 | AE30: =SUM(AE23:AE29) -> -218001.66
A32: COST OF SERVICE
A34: Lender Admin Fee | B34: =Settings!$C$6 -> CAD | C34: =C17 -> 0 | D34: =D17 -> 0 | E34: =E17 -> 0 | F34: =F17 -> 0 | G34: =G17 -> 0 | Z34: =-Z18 -> -39998.062 | AA34: =-AA18 -> -40998.014 | AC34: =SUM(H34:AA34) -> -80996.077 | AD34: =SUM(H34:O34) -> 0 | AE34: =SUM(P34:AA34) -> -80996.077
A35: Borower Payout Bonus | B35: =Settings!$C$6 -> CAD | C35: =-Revenue!#REF!*'CSS Settings'!$I$28 -> #REF! | D35: =-Revenue!#REF!*'CSS Settings'!$I$28 -> #REF! | E35: =-Revenue!#REF!*'CSS Settings'!$I$28 -> #REF! | F35: =-Revenue!#REF!*'CSS Settings'!$I$28 -> #REF! | G35: =-Revenue!#REF!*'CSS Settings'!$I$28 -> #REF! | H35: 0 | I35: 0 | J35: 0 | K35: 0 | L35: 0 | M35: 0 | N35: 0 | O35: 0 | P35: 0 | Q35: 0 | R35: 0 | S35: 0 | T35: 0 | U35: 0 | V35: 0 | W35: 0 | X35: 0 | Y35: 0 | Z35: 0 | AA35: 0 | AC35: =SUM(H35:AA35) -> 0 | AD35: =SUM(H35:O35) -> 0 | AE35: =SUM(P35:AA35) -> 0
A36: Other | B36: =Settings!$C$6 -> CAD | AC36: =SUM(H36:AA36) -> 0 | AD36: =SUM(H36:O36) -> 0 | AE36: =SUM(P36:AA36) -> 0
A37: Total Cost of Services | B37: =Settings!$C$6 -> CAD | C37: =SUM(C34:C36)+C33 -> #REF! | D37: =SUM(D34:D36)+D33 -> #REF! | E37: =SUM(E34:E36)+E33 -> #REF! | F37: =SUM(F34:F36)+F33 -> #REF! | G37: =SUM(G34:G36)+G33 -> #REF! | H37: =SUM(H34:H36)+H33 -> 0 | I37: =SUM(I34:I36)+I33 -> 0 | J37: =SUM(J34:J36)+J33 -> 0 | ... AA37: =SUM(AA34:AA36)+AA33 -> -40998.014 | AC37: =SUM(AC34:AC36)+AC33 -> -80996.077 | AD37: =SUM(AD34:AD36)+AD33 -> 0 | AE37: =SUM(AE34:AE36)+AE33 -> -80996.077
A38: PAYROLL
A39: General
A40: ='CSS Settings'!H5 -> EIR (part time) | B40: =Settings!$C$6 -> CAD | C40: 0 | D40: 0 | E40: 0 | F40: 0 | G40: 0 | H40: 0 | I40: 0 | J40: 0 | K40: 0 | L40: 0 | M40: 0 | N40: ='CSS Settings'!$I$5/12 -> -4583.3333 | O40: ='CSS Settings'!$I$5/12 -> -4583.3333 | P40: ='CSS Settings'!$I$5/12 -> -4583.3333 | Q40: ='CSS Settings'!$I$5/12 -> -4583.3333 | R40: ='CSS Settings'!$I$5/12 -> -4583.3333 | S40: ='CSS Settings'!$I$5/12 -> -4583.3333 | T40: ='CSS Settings'!$I$5/12 -> -4583.3333 | U40: ='CSS Settings'!$I$5/12 -> -4583.3333 | ... AA40: ='CSS Settings'!$I$5/12 -> -4583.3333 | AC40: =SUM(H40:AA40) -> -64166.667 | AD40: =SUM(H40:O40) -> -9166.6667 | AE40: =SUM(P40:AA40) -> -55000
A41: ='CSS Settings'!H6 -> Growth Operations Manager | B41: =Settings!$C$6 -> CAD | C41: 0 | D41: 0 | E41: 0 | F41: 0 | G41: 0 | H41: 0 | I41: 0 | J41: 0 | K41: 0 | L41: 0 | M41: 0 | N41: 0 | O41: 0 | P41: 0 | Q41: 0 | R41: 0 | S41: ='CSS Settings'!$I$6/12 -> -5000 | T41: ='CSS Settings'!$I$6/12 -> -5000 | U41: ='CSS Settings'!$I$6/12 -> -5000 | V41: ='CSS Settings'!$I$6/12 -> -5000 | W41: ='CSS Settings'!$I$6/12 -> -5000 | X41: ='CSS Settings'!$I$6/12 -> -5000 | Y41: ='CSS Settings'!$I$6/12 -> -5000 | Z41: 0 | AA41: 0 | AC41: =SUM(H41:AA41) -> -35000 | AD41: =SUM(H41:O41) -> 0 | AE41: =SUM(P41:AA41) -> -35000
A42: ='CSS Settings'!H7 -> Business Analyst | B42: =Settings!$C$6 -> CAD | C42: 0 | D42: 0 | E42: 0 | F42: 0 | G42: 0 | H42: 0 | I42: 0 | J42: 0 | K42: 0 | L42: 0 | M42: 0 | N42: 0 | O42: 0 | P42: 0 | Q42: 0 | R42: 0 | S42: 0 | T42: 0 | U42: 0 | V42: 0 | W42: 0 | X42: 0 | Y42: 0 | Z42: 0 | AA42: 0 | AC42: =SUM(H42:AA42) -> 0 | AD42: =SUM(H42:O42) -> 0 | AE42: =SUM(P42:AA42) -> 0
A43: ='CSS Settings'!H8 -> Collector | B43: =Settings!$C$6 -> CAD | C43: 0 | D43: 0 | E43: 0 | F43: 0 | G43: 0 | H43: 0 | I43: 0 | J43: 0 | K43: 0 | L43: 0 | M43: 0 | N43: 0 | O43: 0 | P43: 0 | Q43: 0 | R43: 0 | S43: 0 | T43: 0 | U43: 0 | V43: 0 | W43: 0 | X43: 0 | Y43: 0 | Z43: =+'CSS Settings'!$I$8/12 -> -4166.6667 | AA43: =+'CSS Settings'!$I$8/12 -> -4166.6667 | AC43: =SUM(H43:AA43) -> -8333.3333 | AD43: =SUM(H43:O43) -> 0 | AE43: =SUM(P43:AA43) -> -8333.3333
AC44: =SUM(H44:AA44) -> 0 | AD44: =SUM(H44:O44) -> 0 | AE44: =SUM(P44:AA44) -> 0
A45: Benefits, CPP, WCB, and EI Expenses as % of Wages | B45: =Settings!$C$6 -> CAD | C45: =SUM(C40:C44)*'CSS Settings'!$I$10 -> 0 | D45: =SUM(D40:D44)*'CSS Settings'!$I$10 -> 0 | E45: =SUM(E40:E44)*'CSS Settings'!$I$10 -> 0 | F45: =SUM(F40:F44)*'CSS Settings'!$I$10 -> 0 | G45: =SUM(G40:G44)*'CSS Settings'!$I$10 -> 0 | H45: =SUM(H40:H44)*'CSS Settings'!$I$10 -> 0 | I45: =SUM(I40:I44)*'CSS Settings'!$I$10 -> 0 | J45: =SUM(J40:J44)*'CSS Settings'!$I$10 -> 0 | ... AA45: =SUM(AA40:AA44)*'CSS Settings'!$I$10 -> -1225 | AC45: =SUM(H45:AA45) -> -15050 | AD45: =SUM(H45:O45) -> -1283.3333 | AE45: =SUM(P45:AA45) -> -13766.667
A46: Performance Pay ($) Per Employee | B46: =Settings!$C$6 -> CAD | C46: 0 | D46: 0 | E46: 0 | F46: 0 | G46: 0 | H46: 0 | I46: 0 | J46: 0 | K46: 0 | L46: 0 | M46: 0 | N46: =-'CSS Settings'!$I$11*4 -> 0 | O46: =-'CSS Settings'!$I$11*4 -> 0 | P46: =-'CSS Settings'!$I$11*4 -> 0 | Q46: =-'CSS Settings'!$I$11*4 -> 0 | R46: =-'CSS Settings'!$I$11*4 -> 0 | S46: =-'CSS Settings'!$I$11*4 -> 0 | T46: =-'CSS Settings'!$I$11*4 -> 0 | U46: =-'CSS Settings'!$I$11*4 -> 0 | ... AA46: =-'CSS Settings'!$I$11*4 -> 0 | AC46: =SUM(H46:AA46) -> 0 | AD46: =SUM(H46:O46) -> 0 | AE46: =SUM(P46:AA46) -> 0
A47: Total Payroll | B47: =Settings!$C$6 -> CAD | C47: =SUM(C40:C46)+C39 -> 0 | D47: =SUM(D40:D46)+D39 -> 0 | E47: =SUM(E40:E46)+E39 -> 0 | F47: =SUM(F40:F46)+F39 -> 0 | G47: =SUM(G40:G46)+G39 -> 0 | H47: =SUM(H40:H46)+H39 -> 0 | I47: =SUM(I40:I46)+I39 -> 0 | J47: =SUM(J40:J46)+J39 -> 0 | ... AA47: =SUM(AA40:AA46)+AA39 -> -9975 | AC47: =SUM(AC40:AC46)+AC39 -> -122550 | AD47: =SUM(AD40:AD46)+AD39 -> -10450 | AE47: =SUM(AE40:AE46)+AE39 -> -112100
A50: MARKETING & GROWTH
A52: Platforms
A53: Mailchimp | B53: =Settings!$C$6 -> CAD | C53: 0 | D53: =C53 -> 0 | E53: =D53 -> 0 | F53: =E53 -> 0 | G53: =F53 -> 0 | H53: =G53 -> 0 | I53: =H53 -> 0 | J53: =I53 -> 0 | K53: =J53 -> 0 | ... AA53: =Z53 -> 0 | AC53: =SUM(H53:AA53) -> 0 | AD53: =SUM(H53:O53) -> 0 | AE53: =SUM(P53:AA53) -> 0
A54: Hubspot | B54: =Settings!$C$6 -> CAD | C54: 0 | D54: =C54 -> 0 | E54: =D54 -> 0 | F54: =E54 -> 0 | G54: =F54 -> 0 | H54: =G54 -> 0 | I54: =H54 -> 0 | J54: =I54 -> 0 | K54: =J54 -> 0 | ... AA54: =Z54 -> 0 | AC54: =SUM(H54:AA54) -> 0 | AD54: =SUM(H54:O54) -> 0 | AE54: =SUM(P54:AA54) -> 0
A55: Platform 4 | B55: =Settings!$C$6 -> CAD | C55: 0 | D55: =C55 -> 0 | E55: =D55 -> 0 | F55: =E55 -> 0 | G55: =F55 -> 0 | H55: =G55 -> 0 | I55: =H55 -> 0 | J55: =I55 -> 0 | K55: =J55 -> 0 | ... AA55: =Z55 -> 0 | AC55: =SUM(H55:AA55) -> 0 | AD55: =SUM(H55:O55) -> 0 | AE55: =SUM(P55:AA55) -> 0
A56: Platform 4 | B56: =Settings!$C$6 -> CAD | C56: 0 | D56: =C56 -> 0 | E56: =D56 -> 0 | F56: =E56 -> 0 | G56: =F56 -> 0 | H56: =G56 -> 0 | I56: =H56 -> 0 | J56: =I56 -> 0 | K56: =J56 -> 0 | ... AA56: =Z56 -> 0 | AC56: =SUM(H56:AA56) -> 0 | AD56: =SUM(H56:O56) -> 0 | AE56: =SUM(P56:AA56) -> 0
A57: Platform 5 | B57: =Settings!$C$6 -> CAD | C57: 0 | D57: =C57 -> 0 | E57: =D57 -> 0 | F57: =E57 -> 0 | G57: =F57 -> 0 | H57: =G57 -> 0 | I57: =H57 -> 0 | J57: =I57 -> 0 | K57: =J57 -> 0 | ... AA57: =Z57 -> 0 | AC57: =SUM(H57:AA57) -> 0 | AD57: =SUM(H57:O57) -> 0 | AE57: =SUM(P57:AA57) -> 0
A58: Total | B58: =Settings!$C$6 -> CAD | C58: =SUM(C53:C57) -> 0 | D58: =SUM(D53:D57) -> 0 | E58: =SUM(E53:E57) -> 0 | F58: =SUM(F53:F57) -> 0 | G58: =SUM(G53:G57) -> 0 | H58: =SUM(H53:H57) -> 0 | I58: =SUM(I53:I57) -> 0 | J58: =SUM(J53:J57) -> 0 | ... AA58: =SUM(AA53:AA57) -> 0 | AC58: =SUM(AC53:AC57) -> 0 | AD58: =SUM(AD53:AD57) -> 0 | AE58: =SUM(AE53:AE57) -> 0
A60: Direct Response Campaigns
A61: Social Media Support | B61: =Settings!$C$6 -> CAD | C61: 0 | D61: =C61 -> 0 | E61: =D61 -> 0 | F61: =E61 -> 0 | G61: =F61 -> 0 | H61: =G61 -> 0 | I61: =H61 -> 0 | J61: =I61 -> 0 | K61: =J61 -> 0 | ... S61: =R61 -> 0 | T61: -367 | U61: -367 | V61: -367 | W61: -367 | X61: -367 | Y61: -367 | Z61: -367 | AA61: -367 | AC61: =SUM(H61:AA61) -> -2936 | AD61: =SUM(H61:O61) -> 0 | AE61: =SUM(P61:AA61) -> -2936
A62: Facebook Ads | B62: =Settings!$C$6 -> CAD | C62: 0 | D62: =C62 -> 0 | E62: =D62 -> 0 | F62: =E62 -> 0 | G62: =F62 -> 0 | H62: =G62 -> 0 | I62: =H62 -> 0 | J62: =I62 -> 0 | K62: =J62 -> 0 | ... S62: =R62 -> 0 | T62: -68 | U62: -397.43 | V62: -520.93 | W62: -662.15 | X62: -1772.26 | Y62: -2970.17 | Z62: -3000 | AA62: -3000 | AC62: =SUM(H62:AA62) -> -12390.94 | AD62: =SUM(H62:O62) -> 0 | AE62: =SUM(P62:AA62) -> -12390.94
A63: Google Ads | B63: =Settings!$C$6 -> CAD | C63: 0 | D63: =C63 -> 0 | E63: =D63 -> 0 | F63: =E63 -> 0 | G63: =F63 -> 0 | H63: =G63 -> 0 | I63: =H63 -> 0 | J63: =I63 -> 0 | K63: =J63 -> 0 | ... S63: =R63 -> 0 | T63: 0 | U63: 0 | V63: 0 | W63: 0 | X63: 0 | Y63: 0 | Z63: -350 | AA63: -350 | AC63: =SUM(H63:AA63) -> -700 | AD63: =SUM(H63:O63) -> 0 | AE63: =SUM(P63:AA63) -> -700
A64: Other | B64: =Settings!$C$6 -> CAD | C64: 0 | D64: =C64 -> 0 | E64: =D64 -> 0 | F64: =E64 -> 0 | G64: =F64 -> 0 | H64: =G64 -> 0 | I64: =H64 -> 0 | J64: =I64 -> 0 | K64: =J64 -> 0 | ... AA64: =Z64 -> 0 | AC64: =SUM(H64:AA64) -> 0 | AD64: =SUM(H64:O64) -> 0 | AE64: =SUM(P64:AA64) -> 0
A65: Other | B65: =Settings!$C$6 -> CAD | C65: 0 | D65: =C65 -> 0 | E65: =D65 -> 0 | F65: =E65 -> 0 | G65: =F65 -> 0 | H65: =G65 -> 0 | I65: =H65 -> 0 | J65: =I65 -> 0 | K65: =J65 -> 0 | ... AA65: =Z65 -> 0 | AC65: =SUM(H65:AA65) -> 0 | AD65: =SUM(H65:O65) -> 0 | AE65: =SUM(P65:AA65) -> 0
A66: Total | B66: =Settings!$C$6 -> CAD | C66: =SUM(C61:C65) -> 0 | D66: =SUM(D61:D65) -> 0 | E66: =SUM(E61:E65) -> 0 | F66: =SUM(F61:F65) -> 0 | G66: =SUM(G61:G65) -> 0 | H66: =SUM(H61:H65) -> 0 | I66: =SUM(I61:I65) -> 0 | J66: =SUM(J61:J65) -> 0 | ... AA66: =SUM(AA61:AA65) -> -3717 | AC66: =SUM(AC61:AC65) -> -16026.94 | AD66: 0 | AE66: =SUM(AE61:AE65) -> -16026.94
A68: Total Marketing & Growth | B68: =Settings!$C$6 -> CAD | C68: =C66+C58 -> 0 | D68: =D66+D58 -> 0 | E68: =E66+E58 -> 0 | F68: =F66+F58 -> 0 | G68: =G66+G58 -> 0 | H68: =H66+H58 -> 0 | I68: =I66+I58 -> 0 | J68: =J66+J58 -> 0 | ... AA68: =AA66+AA58 -> -3717 | AC68: =AC66+AC58 -> -16026.94 | AD68: =AD66+AD58 -> 0 | AE68: =AE66+AE58 -> -16026.94
A70: ADVISORY & PROF. SERVICES
A72: Recurring
A73: Legal | B73: =Settings!$C$6 -> CAD | C73: =-'CSS Settings'!$I$34 -> -150 | D73: =-'CSS Settings'!$I$34 -> -150 | E73: =-'CSS Settings'!$I$34 -> -150 | F73: =-'CSS Settings'!$I$34 -> -150 | G73: =-'CSS Settings'!$I$34 -> -150 | H73: =-'CSS Settings'!$I$34 -> -150 | I73: =-'CSS Settings'!$I$34 -> -150 | J73: =-'CSS Settings'!$I$34 -> -150 | ... AA73: =-'CSS Settings'!$I$34 -> -150 | AC73: =SUM(H73:AA73) -> -3000 | AD73: =SUM(H73:O73) -> -1200 | AE73: =SUM(P73:AA73) -> -1800
A74: Professional | B74: =Settings!$C$6 -> CAD | C74: =-'CSS Settings'!$I$35 -> -150 | D74: =-'CSS Settings'!$I$35 -> -150 | E74: =-'CSS Settings'!$I$35 -> -150 | F74: =-'CSS Settings'!$I$35 -> -150 | G74: =-'CSS Settings'!$I$35 -> -150 | H74: =-'CSS Settings'!$I$35 -> -150 | I74: =-'CSS Settings'!$I$35 -> -150 | J74: =-'CSS Settings'!$I$35 -> -150 | ... AA74: =-'CSS Settings'!$I$35 -> -150 | AC74: =SUM(H74:AA74) -> -3000 | AD74: =SUM(H74:O74) -> -1200 | AE74: =SUM(P74:AA74) -> -1800
A75: Accounting | B75: =Settings!$C$6 -> CAD | C75: =+'CSS Settings'!$I$36 -> 0 | D75: =+'CSS Settings'!$I$36 -> 0 | E75: =+'CSS Settings'!$I$36 -> 0 | F75: =+'CSS Settings'!$I$36 -> 0 | G75: =+'CSS Settings'!$I$36 -> 0 | H75: =+'CSS Settings'!$I$36 -> 0 | I75: =+'CSS Settings'!$I$36 -> 0 | J75: =+'CSS Settings'!$I$36 -> 0 | ... AA75: =+'CSS Settings'!$I$36 -> 0 | AC75: =SUM(H75:AA75) -> 0 | AD75: =SUM(H75:O75) -> 0 | AE75: =SUM(P75:AA75) -> 0
A76: Other | B76: =Settings!$C$6 -> CAD | C76: =-'CSS Settings'!$I$37 -> 0 | D76: =-'CSS Settings'!$I$37 -> 0 | E76: =-'CSS Settings'!$I$37 -> 0 | F76: =-'CSS Settings'!$I$37 -> 0 | G76: =-'CSS Settings'!$I$37 -> 0 | H76: =-'CSS Settings'!$I$37 -> 0 | I76: =-'CSS Settings'!$I$37 -> 0 | J76: =-'CSS Settings'!$I$37 -> 0 | ... AA76: =-'CSS Settings'!$I$37 -> 0 | AC76: =SUM(H76:AA76) -> 0 | AD76: =SUM(H76:O76) -> 0 | AE76: =SUM(P76:AA76) -> 0
AC77: =SUM(H77:AA77) -> 0 | AD77: =SUM(H77:O77) -> 0 | AE77: =SUM(P77:AA77) -> 0
A78: Total Advisory & Prof | B78: =Settings!$C$6 -> CAD | C78: =SUM(C73:C77) -> -300 | D78: =SUM(D73:D77) -> -300 | E78: =SUM(E73:E77) -> -300 | F78: =SUM(F73:F77) -> -300 | G78: =SUM(G73:G77) -> -300 | H78: =SUM(H73:H77) -> -300 | I78: =SUM(I73:I77) -> -300 | J78: =SUM(J73:J77) -> -300 | ... AA78: =SUM(AA73:AA77) -> -300 | AC78: =SUM(AC73:AC77) -> -6000 | AD78: =SUM(AD73:AD77) -> -2400 | AE78: =SUM(AE73:AE77) -> -3600
A80: RENT
A81: Office | B81: =Settings!$C$6 -> CAD | C81: =+'CSS Settings'!$I$15 -> 0 | D81: =+'CSS Settings'!$I$15 -> 0 | E81: =+'CSS Settings'!$I$15 -> 0 | F81: =+'CSS Settings'!$I$15 -> 0 | G81: =+'CSS Settings'!$I$15 -> 0 | H81: =+'CSS Settings'!$I$15 -> 0 | I81: =+'CSS Settings'!$I$15 -> 0 | J81: =+'CSS Settings'!$I$15 -> 0 | ... AA81: =+'CSS Settings'!$I$15 -> 0 | AC81: =SUM(H81:AA81) -> 0 | AD81: =SUM(H81:O81) -> 0 | AE81: =SUM(P81:AA81) -> 0
A82: Other | B82: =Settings!$C$6 -> CAD | C82: 0 | D82: 0 | E82: 0 | F82: 0 | G82: 0 | H82: 0 | I82: 0 | J82: 0 | K82: 0 | L82: 0 | M82: 0 | N82: 0 | O82: 0 | P82: 0 | Q82: 0 | R82: 0 | S82: 0 | T82: 0 | U82: 0 | V82: 0 | W82: 0 | X82: 0 | Y82: 0 | Z82: 0 | AA82: 0 | AC82: =SUM(H82:AA82) -> 0 | AD82: =SUM(H82:O82) -> 0 | AE82: =SUM(P82:AA82) -> 0
A83: Total Rent | B83: =Settings!$C$6 -> CAD | C83: =SUM(C81:C82) -> 0 | D83: =SUM(D81:D82) -> 0 | E83: =SUM(E81:E82) -> 0 | F83: =SUM(F81:F82) -> 0 | G83: =SUM(G81:G82) -> 0 | H83: =SUM(H81:H82) -> 0 | I83: =SUM(I81:I82) -> 0 | J83: =SUM(J81:J82) -> 0 | ... AA83: =SUM(AA81:AA82) -> 0 | AC83: =SUM(AC81:AC82) -> 0 | AD83: =SUM(AD81:AD82) -> 0 | AE83: =SUM(AE81:AE82) -> 0
A86: SERVICE AGREEMENTS
A87: CashCo Management Services Agreement | B87: =Settings!$C$6 -> CAD | C87: =-'CSS Settings'!$I$39 -> -2000 | D87: =-'CSS Settings'!$I$39 -> -2000 | E87: =-'CSS Settings'!$I$39 -> -2000 | F87: =-'CSS Settings'!$I$39 -> -2000 | G87: =-'CSS Settings'!$I$39 -> -2000 | H87: 0 | I87: 0 | J87: 0 | K87: 0 | L87: 0 | M87: 0 | N87: 0 | O87: 0 | P87: 0 | Q87: 0 | R87: 0 | S87: 0 | T87: 0 | U87: 0 | V87: 0 | W87: 0 | X87: 0 | Y87: 0 | Z87: 0 | AA87: 0 | AC87: =SUM(H87:AA87) -> 0 | AD87: =SUM(H87:O87) -> 0 | AE87: =SUM(P87:AA87) -> 0
A88: Service Agreement 2 | B88: =Settings!$C$6 -> CAD | C88: 0 | D88: 0 | E88: 0 | F88: 0 | G88: 0 | H88: 0 | I88: 0 | J88: 0 | K88: 0 | L88: 0 | M88: 0 | N88: 0 | O88: 0 | P88: 0 | Q88: 0 | R88: 0 | S88: 0 | T88: 0 | U88: 0 | V88: 0 | W88: 0 | X88: 0 | Y88: 0 | Z88: 0 | AA88: 0 | AC88: =SUM(H88:AA88) -> 0 | AD88: =SUM(H88:O88) -> 0 | AE88: =SUM(P88:AA88) -> 0
A89: Service Agreement 3 | B89: =Settings!$C$6 -> CAD | C89: 0 | D89: =C89 -> 0 | E89: =D89 -> 0 | F89: =E89 -> 0 | G89: =F89 -> 0 | H89: =G89 -> 0 | I89: =H89 -> 0 | J89: =I89 -> 0 | K89: =J89 -> 0 | ... AA89: =Z89 -> 0 | AC89: =SUM(H89:AA89) -> 0 | AD89: =SUM(H89:O89) -> 0 | AE89: =SUM(P89:AA89) -> 0
A90: Total General | B90: =Settings!$C$6 -> CAD | C90: =SUM(C87:C89) -> -2000 | D90: =SUM(D87:D89) -> -2000 | E90: =SUM(E87:E89) -> -2000 | F90: =SUM(F87:F89) -> -2000 | G90: =SUM(G87:G89) -> -2000 | H90: =SUM(H87:H89) -> 0 | I90: =SUM(I87:I89) -> 0 | J90: =SUM(J87:J89) -> 0 | ... AA90: =SUM(AA87:AA89) -> 0 | AC90: =SUM(AC87:AC89) -> 0 | AD90: =SUM(AD87:AD89) -> 0 | AE90: =SUM(AE87:AE89) -> 0
A92: OTHER EXPENSES
A93: ='CSS Settings'!H17 -> Insurance Expense - Corporate | B93: =Settings!$C$6 -> CAD | C93: =-'CSS Settings'!$I$17 -> -150 | D93: =-'CSS Settings'!$I$17 -> -150 | E93: =-'CSS Settings'!$I$17 -> -150 | F93: =-'CSS Settings'!$I$17 -> -150 | G93: =-'CSS Settings'!$I$17 -> -150 | H93: =-'CSS Settings'!$I$17 -> -150 | I93: =-'CSS Settings'!$I$17 -> -150 | J93: =-'CSS Settings'!$I$17 -> -150 | ... AA93: =-'CSS Settings'!$I$17 -> -150 | AC93: =SUM(H93:AA93) -> -3000 | AD93: =SUM(H93:O93) -> -1200 | AE93: =SUM(P93:AA93) -> -1800
A94: ='CSS Settings'!H22 -> Telephone Expense - Voip and Cell | B94: CAD | C94: =-'CSS Settings'!$I$22 -> -39.8867 | D94: =-'CSS Settings'!$I$22 -> -39.8867 | E94: =-'CSS Settings'!$I$22 -> -39.8867 | F94: =-'CSS Settings'!$I$22 -> -39.8867 | G94: =-'CSS Settings'!$I$22 -> -39.8867 | H94: =-'CSS Settings'!$I$22 -> -39.8867 | I94: =-'CSS Settings'!$I$22 -> -39.8867 | J94: =-'CSS Settings'!$I$22 -> -39.8867 | ... AA94: =-'CSS Settings'!$I$22 -> -39.8867 | AC94: =SUM(H94:AA94) -> -797.734 | AD94: =SUM(H94:O94) -> -319.0936 | AE94: =SUM(P94:AA94) -> -478.6404
A95: ='CSS Settings'!H23 -> Internet Expense | B95: =Settings!$C$6 -> CAD | C95: =-'CSS Settings'!$I$23 -> 0 | D95: =-'CSS Settings'!$I$23 -> 0 | E95: =-'CSS Settings'!$I$23 -> 0 | F95: =-'CSS Settings'!$I$23 -> 0 | G95: =-'CSS Settings'!$I$23 -> 0 | H95: =-'CSS Settings'!$I$23 -> 0 | I95: =-'CSS Settings'!$I$23 -> 0 | J95: =-'CSS Settings'!$I$23 -> 0 | ... AA95: =-'CSS Settings'!$I$23 -> 0 | AC95: =SUM(H95:AA95) -> 0 | AD95: =SUM(H95:O95) -> 0 | AE95: =SUM(P95:AA95) -> 0
A96: ='CSS Settings'!H24 -> Utilities Expense | B96: =Settings!$C$6 -> CAD | C96: =-'CSS Settings'!$I$24 -> 0 | D96: =-'CSS Settings'!$I$24 -> 0 | E96: =-'CSS Settings'!$I$24 -> 0 | F96: =-'CSS Settings'!$I$24 -> 0 | G96: =-'CSS Settings'!$I$24 -> 0 | H96: =-'CSS Settings'!$I$24 -> 0 | I96: =-'CSS Settings'!$I$24 -> 0 | J96: =-'CSS Settings'!$I$24 -> 0 | ... AA96: =-'CSS Settings'!$I$24 -> 0 | AC96: =SUM(H96:AA96) -> 0 | AD96: =SUM(H96:O96) -> 0 | AE96: =SUM(P96:AA96) -> 0
A97: ='CSS Settings'!H25 -> Bank Charges | B97: =Settings!$C$6 -> CAD | C97: =-'CSS Settings'!$I$25 -> -50 | D97: =-'CSS Settings'!$I$25 -> -50 | E97: =-'CSS Settings'!$I$25 -> -50 | F97: =-'CSS Settings'!$I$25 -> -50 | G97: =-'CSS Settings'!$I$25 -> -50 | H97: =-'CSS Settings'!$I$25 -> -50 | I97: =-'CSS Settings'!$I$25 -> -50 | J97: =-'CSS Settings'!$I$25 -> -50 | ... AA97: =-'CSS Settings'!$I$25 -> -50 | AC97: =SUM(H97:AA97) -> -1000 | AD97: =SUM(H97:O97) -> -400 | AE97: =SUM(P97:AA97) -> -600
A98: ='CSS Settings'!H26 -> Computer & Licensing Expense | B98: =Settings!$C$6 -> CAD | C98: =-'CSS Settings'!$I$26 -> -150 | D98: =-'CSS Settings'!$I$26 -> -150 | E98: =-'CSS Settings'!$I$26 -> -150 | F98: =-'CSS Settings'!$I$26 -> -150 | G98: =-'CSS Settings'!$I$26 -> -150 | H98: =-'CSS Settings'!$I$26 -> -150 | I98: =-'CSS Settings'!$I$26 -> -150 | J98: =-'CSS Settings'!$I$26 -> -150 | ... AA98: =-'CSS Settings'!$I$26 -> -150 | AC98: =SUM(H98:AA98) -> -3000 | AD98: =SUM(H98:O98) -> -1200 | AE98: =SUM(P98:AA98) -> -1800
A99: ='CSS Settings'!H27 -> Courier/Postage | B99: =Settings!$C$6 -> CAD | C99: =-'CSS Settings'!$I$27 -> 0 | D99: =-'CSS Settings'!$I$27 -> 0 | E99: =-'CSS Settings'!$I$27 -> 0 | F99: =-'CSS Settings'!$I$27 -> 0 | G99: =-'CSS Settings'!$I$27 -> 0 | H99: =-'CSS Settings'!$I$27 -> 0 | I99: =-'CSS Settings'!$I$27 -> 0 | J99: =-'CSS Settings'!$I$27 -> 0 | ... AA99: =-'CSS Settings'!$I$27 -> 0 | AC99: =SUM(H99:AA99) -> 0 | AD99: =SUM(H99:O99) -> 0 | AE99: =SUM(P99:AA99) -> 0
A100: ='CSS Settings'!H30 -> Office Expense | B100: =Settings!$C$6 -> CAD | C100: =-'CSS Settings'!$I$30 -> -50 | D100: =-'CSS Settings'!$I$30 -> -50 | E100: =-'CSS Settings'!$I$30 -> -50 | F100: =-'CSS Settings'!$I$30 -> -50 | G100: =-'CSS Settings'!$I$30 -> -50 | H100: =-'CSS Settings'!$I$30 -> -50 | I100: =-'CSS Settings'!$I$30 -> -50 | J100: =-'CSS Settings'!$I$30 -> -50 | ... AA100: =-'CSS Settings'!$I$30 -> -50 | AC100: =SUM(H100:AA100) -> -1000 | AD100: =SUM(H100:O100) -> -400 | AE100: =SUM(P100:AA100) -> -600
A101: ='CSS Settings'!H31 -> Travel | B101: =Settings!$C$6 -> CAD | C101: =-'CSS Settings'!$I$31 -> 0 | D101: =-'CSS Settings'!$I$31 -> 0 | E101: =-'CSS Settings'!$I$31 -> 0 | F101: =-'CSS Settings'!$I$31 -> 0 | G101: =-'CSS Settings'!$I$31 -> 0 | H101: =-'CSS Settings'!$I$31 -> 0 | I101: =-'CSS Settings'!$I$31 -> 0 | J101: =-'CSS Settings'!$I$31 -> 0 | ... AA101: =-'CSS Settings'!$I$31 -> 0 | AC101: =SUM(H101:AA101) -> 0 | AD101: =SUM(H101:O101) -> 0 | AE101: =SUM(P101:AA101) -> 0
A102: ='CSS Settings'!H32 -> Meals and Entertainment | B102: =Settings!$C$6 -> CAD | C102: =-'CSS Settings'!$I$32 -> -50 | D102: =-'CSS Settings'!$I$32 -> -50 | E102: =-'CSS Settings'!$I$32 -> -50 | F102: =-'CSS Settings'!$I$32 -> -50 | G102: =-'CSS Settings'!$I$32 -> -50 | H102: =-'CSS Settings'!$I$32 -> -50 | I102: =-'CSS Settings'!$I$32 -> -50 | J102: =-'CSS Settings'!$I$32 -> -50 | ... AA102: =-'CSS Settings'!$I$32 -> -50 | AC102: =SUM(H102:AA102) -> -1000 | AD102: =SUM(H102:O102) -> -400 | AE102: =SUM(P102:AA102) -> -600
A103: Total Other Expenses | B103: =Settings!$C$6 -> CAD | C103: =SUM(C93:C100) -> -439.8867 | D103: =SUM(D93:D100) -> -439.8867 | E103: =SUM(E93:E100) -> -439.8867 | F103: =SUM(F93:F100) -> -439.8867 | G103: =SUM(G93:G100) -> -439.8867 | H103: =SUM(H93:H100) -> -439.8867 | I103: =SUM(I93:I100) -> -439.8867 | J103: =SUM(J93:J100) -> -439.8867 | ... AA103: =SUM(AA93:AA100) -> -439.8867 | AC103: =SUM(AC93:AC100) -> -8797.734 | AD103: =SUM(AD93:AD100) -> -3519.0936 | AE103: =SUM(AE93:AE100) -> -5278.6404

Sheet WK+CAPEX
A2: CAPEX & Working Capital
A3: =+TODAY() -> 44539
C6: ='FS-Month'!C6 -> 43831 | D6: ='FS-Month'!D6 -> 43862 | E6: ='FS-Month'!E6 -> 43891 | F6: ='FS-Month'!F6 -> 43922 | G6: ='FS-Month'!G6 -> 43952 | H6: ='FS-Month'!H6 -> 43983 | I6: ='FS-Month'!I6 -> 44013 | J6: ='FS-Month'!J6 -> 44044 | ... T6: ='FS-Month'!T6 -> 44348
B7: Unit | C7: ='FS-Month'!C7 -> 1 | D7: ='FS-Month'!D7 -> 2 | E7: ='FS-Month'!E7 -> 3 | F7: ='FS-Month'!F7 -> 4 | G7: ='FS-Month'!G7 -> 5 | H7: ='FS-Month'!H7 -> 1 | I7: ='FS-Month'!I7 -> 2 | J7: ='FS-Month'!J7 -> 3 | ... T7: ='FS-Month'!T7 -> 13
A9: KEY INDICATORS
A17: BALANCE SHEET ACCOUNTS
A19: Operating Cash
A20: Balance | B20: =Settings!$C$6 -> CAD | C20: =Settings!$C$29 -> 0 | D20: =C20 -> 0 | E20: =D20 -> 0 | F20: =E20 -> 0 | G20: =F20 -> 0 | H20: =G20 -> 0 | I20: =H20 -> 0 | J20: =I20 -> 0 | K20: =J20 -> 0 | ... T20: =S20 -> 0
A21: Percentage of revenues | B21: % | C21: =Settings!$C$30 -> 0.1 | D21: =C21 -> 0.1 | E21: =D21 -> 0.1 | F21: =E21 -> 0.1 | G21: =F21 -> 0.1 | H21: =G21 -> 0.1 | I21: =H21 -> 0.1 | J21: =I21 -> 0.1 | K21: =J21 -> 0.1 | ... T21: =S21 -> 0.1
A23: Accounts Receivable
A24: A/R from Revenues
A25: Balance | B25: =Settings!$C$6 -> CAD | C25: =C26*Revenue!#REF! -> #REF! | D25: =D26*Revenue!#REF! -> #REF! | E25: =E26*Revenue!#REF! -> #REF! | F25: =F26*Revenue!#REF! -> #REF! | G25: =G26*Revenue!#REF! -> #REF! | H25: =H26*Revenue!#REF! -> #REF! | I25: =I26*Revenue!#REF! -> #REF! | J25: =J26*Revenue!#REF! -> #REF! | ... T25: =T26*Revenue!#REF! -> #REF!
A26: Pending Income/Total Income | B26: % | C26: =Settings!C33 -> 0 | D26: =C26 -> 0 | E26: =D26 -> 0 | F26: =E26 -> 0 | G26: =F26 -> 0 | H26: =G26 -> 0 | I26: =H26 -> 0 | J26: =I26 -> 0 | K26: =J26 -> 0 | ... T26: =S26 -> 0
A27: Pre-paid expenses
A28: Balance | B28: =Settings!$C$6 -> CAD | C28: =HLOOKUP(C6+C30+1,$D$6:$T$30,16,TRUE) -> 0.1 | D28: =HLOOKUP(D6+D30+1,$D$6:$T$30,16,TRUE) -> 0.1 | E28: =HLOOKUP(E6+E30+1,$D$6:$T$30,16,TRUE) -> 0.1 | F28: =HLOOKUP(F6+F30+1,$D$6:$T$30,16,TRUE) -> 0.1 | G28: =HLOOKUP(G6+G30+1,$D$6:$T$30,16,TRUE) -> 0.1 | H28: =HLOOKUP(H6+H30+1,$D$6:$T$30,16,TRUE) -> 0.1 | I28: =HLOOKUP(I6+I30+1,$D$6:$T$30,16,TRUE) -> 0.1 | J28: =HLOOKUP(J6+J30+1,$D$6:$T$30,16,TRUE) -> 0.1 | ... T28: =HLOOKUP(T6+T30+1,$D$6:$T$30,16,TRUE) -> 0.1
A29: COS Accounts | B29: =Settings!$C$6 -> CAD | C29: ='COS and SG&A'!C23 -> 0 | D29: ='COS and SG&A'!D23 -> 0 | E29: ='COS and SG&A'!E23 -> 0 | F29: ='COS and SG&A'!F23 -> 0 | G29: ='COS and SG&A'!G23 -> 0 | H29: ='COS and SG&A'!H23 -> 0 | I29: ='COS and SG&A'!I23 -> 0 | J29: ='COS and SG&A'!J23 -> 0 | ... T29: ='COS and SG&A'!T23 -> 0
A30: Pre-paid Days Outstanding | B30: days | C30: =Settings!$C$36 -> 30 | D30: =Settings!$C$36 -> 30 | E30: =Settings!$C$36 -> 30 | F30: =Settings!$C$36 -> 30 | G30: =Settings!$C$36 -> 30 | H30: =Settings!$C$36 -> 30 | I30: =Settings!$C$36 -> 30 | J30: =Settings!$C$36 -> 30 | ... T30: =Settings!$C$36 -> 30
A32: Accounts Payable
A33: Balance | B33: =Settings!$C$6 -> CAD | C33: =C34*C29 -> 0 | D33: =D34*D29 -> 0 | E33: =E34*E29 -> 0 | F33: =F34*F29 -> 0 | G33: =G34*G29 -> 0 | H33: =H34*H29 -> 0 | I33: =I34*I29 -> 0 | J33: =J34*J29 -> 0 | ... T33: =T34*T29 -> 0
A34: A/P as % of total COGS | B34: % | C34: =Settings!$C$39 -> 0 | D34: =Settings!$C$39 -> 0 | E34: =Settings!$C$39 -> 0 | F34: =Settings!$C$39 -> 0 | G34: =Settings!$C$39 -> 0 | H34: =Settings!$C$39 -> 0 | I34: =Settings!$C$39 -> 0 | J34: =Settings!$C$39 -> 0 | ... T34: =Settings!$C$39 -> 0
A36: Assets
A37: Balance | B37: =Settings!$C$6 -> CAD | C37: =SUM(C38:C41) -> 0 | D37: =SUM(D38:D41) -> 0 | E37: =SUM(E38:E41) -> 0 | F37: =SUM(F38:F41) -> 0 | G37: =SUM(G38:G41) -> 0 | H37: =SUM(H38:H41) -> 0 | I37: =SUM(I38:I41) -> 0 | J37: =SUM(J38:J41) -> 0 | ... T37: =SUM(T38:T41) -> 0
A38: =A57 -> Office furniture | B38: USD | C38: =SUM($C57:C57)-SUM($C67:C67) -> 0 | D38: =SUM($C57:D57)-SUM($C67:D67) -> 0 | E38: =SUM($C57:E57)-SUM($C67:E67) -> 0 | F38: =SUM($C57:F57)-SUM($C67:F67) -> 0 | G38: =SUM($C57:G57)-SUM($C67:G67) -> 0 | H38: =SUM($C57:H57)-SUM($C67:H67) -> 0 | I38: =SUM($C57:I57)-SUM($C67:I67) -> 0 | J38: =SUM($C57:J57)-SUM($C67:J67) -> 0 | ... T38: =SUM($C57:T57)-SUM($C67:T67) -> 0
A39: =A58 -> Computers | B39: USD | C39: =SUM($C58:C58)-SUM($C68:C68) -> 0 | D39: =SUM($C58:D58)-SUM($C68:D68) -> 0 | E39: =SUM($C58:E58)-SUM($C68:E68) -> 0 | F39: =SUM($C58:F58)-SUM($C68:F68) -> 0 | G39: =SUM($C58:G58)-SUM($C68:G68) -> 0 | H39: =SUM($C58:H58)-SUM($C68:H68) -> 0 | I39: =SUM($C58:I58)-SUM($C68:I68) -> 0 | J39: =SUM($C58:J58)-SUM($C68:J68) -> 0 | ... T39: =SUM($C58:T58)-SUM($C68:T68) -> 0
A40: =A59 -> Servers & other tech infrastructure | B40: USD | C40: =SUM($C59:C59)-SUM($C69:C69) -> 0 | D40: =SUM($C59:D59)-SUM($C69:D69) -> 0 | E40: =SUM($C59:E59)-SUM($C69:E69) -> 0 | F40: =SUM($C59:F59)-SUM($C69:F69) -> 0 | G40: =SUM($C59:G59)-SUM($C69:G69) -> 0 | H40: =SUM($C59:H59)-SUM($C69:H69) -> 0 | I40: =SUM($C59:I59)-SUM($C69:I69) -> 0 | J40: =SUM($C59:J59)-SUM($C69:J69) -> 0 | ... T40: =SUM($C59:T59)-SUM($C69:T69) -> 0
A41: =A60 -> Other | B41: USD | C41: =SUM($C60:C60)-SUM($C70:C70) -> 0 | D41: =SUM($C60:D60)-SUM($C70:D70) -> 0 | E41: =SUM($C60:E60)-SUM($C70:E70) -> 0 | F41: =SUM($C60:F60)-SUM($C70:F70) -> 0 | G41: =SUM($C60:G60)-SUM($C70:G70) -> 0 | H41: =SUM($C60:H60)-SUM($C70:H70) -> 0 | I41: =SUM($C60:I60)-SUM($C70:I70) -> 0 | J41: =SUM($C60:J60)-SUM($C70:J70) -> 0 | ... T41: =SUM($C60:T60)-SUM($C70:T70) -> 0
A42: CAPEX | B42: =Settings!$C$6 -> CAD | C42: =C61 -> 0 | D42: =D61 -> 0 | E42: =E61 -> 0 | F42: =F61 -> 0 | G42: =G61 -> 0 | H42: =H61 -> 0 | I42: =I61 -> 0 | J42: =J61 -> 0 | ... T42: =T61 -> 0
A43: Depreciation | B43: =Settings!$C$6 -> CAD | C43: =SUM(C67:C70) -> 0 | D43: =SUM(D67:D70) -> 0 | E43: =SUM(E67:E70) -> 0 | F43: =SUM(F67:F70) -> 0 | G43: =SUM(G67:G70) -> 0 | H43: =SUM(H67:H70) -> 0 | I43: =SUM(I67:I70) -> 0 | J43: =SUM(J67:J70) -> 0 | ... T43: =SUM(T67:T70) -> 0
A46: WORKING CAPITAL
A48: Change in Operating Cash | B48: =Settings!$C$6 -> CAD | D48: =C20-D20 -> 0 | E48: =D20-E20 -> 0 | F48: =E20-F20 -> 0 | G48: =F20-G20 -> 0 | H48: =G20-H20 -> 0 | I48: =H20-I20 -> 0 | J48: =I20-J20 -> 0 | K48: =J20-K20 -> 0 | ... T48: =S20-T20 -> 0
A49: Change in Accounts Receivable | B49: =Settings!$C$6 -> CAD | D49: =SUM(C25,C28)-SUM(D25,D28) -> #REF! | E49: =SUM(D25,D28)-SUM(E25,E28) -> #REF! | F49: =SUM(E25,E28)-SUM(F25,F28) -> #REF! | G49: =SUM(F25,F28)-SUM(G25,G28) -> #REF! | H49: =SUM(G25,G28)-SUM(H25,H28) -> #REF! | I49: =SUM(H25,H28)-SUM(I25,I28) -> #REF! | J49: =SUM(I25,I28)-SUM(J25,J28) -> #REF! | K49: =SUM(J25,J28)-SUM(K25,K28) -> #REF! | ... T49: =SUM(S25,S28)-SUM(T25,T28) -> #REF!
A50: Change in Accounts Payable | B50: =Settings!$C$6 -> CAD | D50: =D33-C33 -> 0 | E50: =E33-D33 -> 0 | F50: =F33-E33 -> 0 | G50: =G33-F33 -> 0 | H50: =H33-G33 -> 0 | I50: =I33-H33 -> 0 | J50: =J33-I33 -> 0 | K50: =K33-J33 -> 0 | ... T50: =T33-S33 -> 0
A51: Total Working Capital | B51: =Settings!$C$6 -> CAD | D51: =SUM(D48:D50) -> #REF! | E51: =SUM(E48:E50) -> #REF! | F51: =SUM(F48:F50) -> #REF! | G51: =SUM(G48:G50) -> #REF! | H51: =SUM(H48:H50) -> #REF! | I51: =SUM(I48:I50) -> #REF! | J51: =SUM(J48:J50) -> #REF! | K51: =SUM(K48:K50) -> #REF! | ... T51: =SUM(T48:T50) -> #REF!
A54: CAPITAL EXPENDITURES
A56: By type of asset: | B56: =Settings!$C$6 -> CAD
A57: Office furniture | B57: =Settings!$C$6 -> CAD | C57: =IF(C$7>=(Settings!$C$47*12+1),HLOOKUP(C$7-Settings!$C$47*12,$C$7:$T$57,#REF!,FALSE)*(1+Settings!$C$17/12*(COUNT('WK+CAPEX'!$C$7:C$7)-1)),0) -> 0 | D57: =IF(D$7>=(Settings!$C$47*12+1),HLOOKUP(D$7-Settings!$C$47*12,$C$7:$T$57,#REF!,FALSE)*(1+Settings!$C$17/12*(COUNT('WK+CAPEX'!$C$7:D$7)-1)),0) -> 0 | E57: =IF(E$7>=(Settings!$C$47*12+1),HLOOKUP(E$7-Settings!$C$47*12,$C$7:$T$57,#REF!,FALSE)*(1+Settings!$C$17/12*(COUNT('WK+CAPEX'!$C$7:E$7)-1)),0) -> 0 | F57: =IF(F$7>=(Settings!$C$47*12+1),HLOOKUP(F$7-Settings!$C$47*12,$C$7:$T$57,#REF!,FALSE)*(1+Settings!$C$17/12*(COUNT('WK+CAPEX'!$C$7:F$7)-1)),0) -> 0 | G57: =IF(G$7>=(Settings!$C$47*12+1),HLOOKUP(G$7-Settings!$C$47*12,$C$7:$T$57,#REF!,FALSE)*(1+Settings!$C$17/12*(COUNT('WK+CAPEX'!$C$7:G$7)-1)),0) -> 0 | H57: =IF(H$7>=(Settings!$C$47*12+1),HLOOKUP(H$7-Settings!$C$47*12,$C$7:$T$57,#REF!,FALSE)*(1+Settings!$C$17/12*(COUNT('WK+CAPEX'!$C$7:H$7)-1)),0) -> 0 | I57: =IF(I$7>=(Settings!$C$47*12+1),HLOOKUP(I$7-Settings!$C$47*12,$C$7:$T$57,#REF!,FALSE)*(1+Settings!$C$17/12*(COUNT('WK+CAPEX'!$C$7:I$7)-1)),0) -> 0 | J57: =IF(J$7>=(Settings!$C$47*12+1),HLOOKUP(J$7-Settings!$C$47*12,$C$7:$T$57,#REF!,FALSE)*(1+Settings!$C$17/12*(COUNT('WK+CAPEX'!$C$7:J$7)-1)),0) -> 0 | ... T57: =IF(T$7>=(Settings!$C$47*12+1),HLOOKUP(T$7-Settings!$C$47*12,$C$7:$T$57,#REF!,FALSE)*(1+Settings!$C$17/12*(COUNT('WK+CAPEX'!$C$7:T$7)-1)),0) -> 0
A58: Computers | B58: =Settings!$C$6 -> CAD | C58: =IF(C$7>=(Settings!$C$50*12+1),HLOOKUP(C$7-Settings!$C$50*12,$C$7:$T$59,#REF!,FALSE)*(1+Settings!$C$17/12*(COUNT('WK+CAPEX'!$C$7:C$7)-1)),0) -> 0 | D58: =IF(D$7>=(Settings!$C$50*12+1),HLOOKUP(D$7-Settings!$C$50*12,$C$7:$T$59,#REF!,FALSE)*(1+Settings!$C$17/12*(COUNT('WK+CAPEX'!$C$7:D$7)-1)),0) -> 0 | E58: =IF(E$7>=(Settings!$C$50*12+1),HLOOKUP(E$7-Settings!$C$50*12,$C$7:$T$59,#REF!,FALSE)*(1+Settings!$C$17/12*(COUNT('WK+CAPEX'!$C$7:E$7)-1)),0) -> 0 | F58: =IF(F$7>=(Settings!$C$50*12+1),HLOOKUP(F$7-Settings!$C$50*12,$C$7:$T$59,#REF!,FALSE)*(1+Settings!$C$17/12*(COUNT('WK+CAPEX'!$C$7:F$7)-1)),0) -> 0 | G58: =IF(G$7>=(Settings!$C$50*12+1),HLOOKUP(G$7-Settings!$C$50*12,$C$7:$T$59,#REF!,FALSE)*(1+Settings!$C$17/12*(COUNT('WK+CAPEX'!$C$7:G$7)-1)),0) -> 0 | H58: =IF(H$7>=(Settings!$C$50*12+1),HLOOKUP(H$7-Settings!$C$50*12,$C$7:$T$59,#REF!,FALSE)*(1+Settings!$C$17/12*(COUNT('WK+CAPEX'!$C$7:H$7)-1)),0) -> 0 | I58: =IF(I$7>=(Settings!$C$50*12+1),HLOOKUP(I$7-Settings!$C$50*12,$C$7:$T$59,#REF!,FALSE)*(1+Settings!$C$17/12*(COUNT('WK+CAPEX'!$C$7:I$7)-1)),0) -> 0 | J58: =IF(J$7>=(Settings!$C$50*12+1),HLOOKUP(J$7-Settings!$C$50*12,$C$7:$T$59,#REF!,FALSE)*(1+Settings!$C$17/12*(COUNT('WK+CAPEX'!$C$7:J$7)-1)),0) -> 0 | ... T58: =IF(T$7>=(Settings!$C$50*12+1),HLOOKUP(T$7-Settings!$C$50*12,$C$7:$T$59,#REF!,FALSE)*(1+Settings!$C$17/12*(COUNT('WK+CAPEX'!$C$7:T$7)-1)),0) -> 0
A59: Servers & other tech infrastructure | B59: =Settings!$C$6 -> CAD | C59: =IF(C$7>=(Settings!$C$50*12+1),HLOOKUP(C$7-Settings!$C$50*12,$C$7:$T$59,#REF!,FALSE)*(1+Settings!$C$17/12*(COUNT('WK+CAPEX'!$C$7:C$7)-1)),0) -> 0 | D59: =IF(D$7>=(Settings!$C$50*12+1),HLOOKUP(D$7-Settings!$C$50*12,$C$7:$T$59,#REF!,FALSE)*(1+Settings!$C$17/12*(COUNT('WK+CAPEX'!$C$7:D$7)-1)),0) -> 0 | E59: =IF(E$7>=(Settings!$C$50*12+1),HLOOKUP(E$7-Settings!$C$50*12,$C$7:$T$59,#REF!,FALSE)*(1+Settings!$C$17/12*(COUNT('WK+CAPEX'!$C$7:E$7)-1)),0) -> 0 | F59: =IF(F$7>=(Settings!$C$50*12+1),HLOOKUP(F$7-Settings!$C$50*12,$C$7:$T$59,#REF!,FALSE)*(1+Settings!$C$17/12*(COUNT('WK+CAPEX'!$C$7:F$7)-1)),0) -> 0 | G59: =IF(G$7>=(Settings!$C$50*12+1),HLOOKUP(G$7-Settings!$C$50*12,$C$7:$T$59,#REF!,FALSE)*(1+Settings!$C$17/12*(COUNT('WK+CAPEX'!$C$7:G$7)-1)),0) -> 0 | H59: =IF(H$7>=(Settings!$C$50*12+1),HLOOKUP(H$7-Settings!$C$50*12,$C$7:$T$59,#REF!,FALSE)*(1+Settings!$C$17/12*(COUNT('WK+CAPEX'!$C$7:H$7)-1)),0) -> 0 | I59: =IF(I$7>=(Settings!$C$50*12+1),HLOOKUP(I$7-Settings!$C$50*12,$C$7:$T$59,#REF!,FALSE)*(1+Settings!$C$17/12*(COUNT('WK+CAPEX'!$C$7:I$7)-1)),0) -> 0 | J59: =IF(J$7>=(Settings!$C$50*12+1),HLOOKUP(J$7-Settings!$C$50*12,$C$7:$T$59,#REF!,FALSE)*(1+Settings!$C$17/12*(COUNT('WK+CAPEX'!$C$7:J$7)-1)),0) -> 0 | ... T59: =IF(T$7>=(Settings!$C$50*12+1),HLOOKUP(T$7-Settings!$C$50*12,$C$7:$T$59,#REF!,FALSE)*(1+Settings!$C$17/12*(COUNT('WK+CAPEX'!$C$7:T$7)-1)),0) -> 0
A60: Other | B60: =Settings!$C$6 -> CAD | C60: =IF(C$7>=(Settings!$C$51*12+1),HLOOKUP(C$7-Settings!$C$51*12,$C$7:$T$60,#REF!,FALSE)*(1+Settings!$C$17/12*(COUNT('WK+CAPEX'!$C$7:C$7)-1)),0) -> 0 | D60: =IF(D$7>=(Settings!$C$51*12+1),HLOOKUP(D$7-Settings!$C$51*12,$C$7:$T$60,#REF!,FALSE)*(1+Settings!$C$17/12*(COUNT('WK+CAPEX'!$C$7:D$7)-1)),0) -> 0 | E60: =IF(E$7>=(Settings!$C$51*12+1),HLOOKUP(E$7-Settings!$C$51*12,$C$7:$T$60,#REF!,FALSE)*(1+Settings!$C$17/12*(COUNT('WK+CAPEX'!$C$7:E$7)-1)),0) -> 0 | F60: =IF(F$7>=(Settings!$C$51*12+1),HLOOKUP(F$7-Settings!$C$51*12,$C$7:$T$60,#REF!,FALSE)*(1+Settings!$C$17/12*(COUNT('WK+CAPEX'!$C$7:F$7)-1)),0) -> 0 | G60: =IF(G$7>=(Settings!$C$51*12+1),HLOOKUP(G$7-Settings!$C$51*12,$C$7:$T$60,#REF!,FALSE)*(1+Settings!$C$17/12*(COUNT('WK+CAPEX'!$C$7:G$7)-1)),0) -> 0 | H60: 0 | I60: =IF(I$7>=(Settings!$C$51*12+1),HLOOKUP(I$7-Settings!$C$51*12,$C$7:$T$60,#REF!,FALSE)*(1+Settings!$C$17/12*(COUNT('WK+CAPEX'!$C$7:I$7)-1)),0) -> 0 | J60: =IF(J$7>=(Settings!$C$51*12+1),HLOOKUP(J$7-Settings!$C$51*12,$C$7:$T$60,#REF!,FALSE)*(1+Settings!$C$17/12*(COUNT('WK+CAPEX'!$C$7:J$7)-1)),0) -> 0 | K60: =IF(K$7>=(Settings!$C$51*12+1),HLOOKUP(K$7-Settings!$C$51*12,$C$7:$T$60,#REF!,FALSE)*(1+Settings!$C$17/12*(COUNT('WK+CAPEX'!$C$7:K$7)-1)),0) -> 0 | L60: =IF(L$7>=(Settings!$C$51*12+1),HLOOKUP(L$7-Settings!$C$51*12,$C$7:$T$60,#REF!,FALSE)*(1+Settings!$C$17/12*(COUNT('WK+CAPEX'!$C$7:L$7)-1)),0) -> 0 | M60: =IF(M$7>=(Settings!$C$51*12+1),HLOOKUP(M$7-Settings!$C$51*12,$C$7:$T$60,#REF!,FALSE)*(1+Settings!$C$17/12*(COUNT('WK+CAPEX'!$C$7:M$7)-1)),0) -> 0 | N60: =IF(N$7>=(Settings!$C$51*12+1),HLOOKUP(N$7-Settings!$C$51*12,$C$7:$T$60,#REF!,FALSE)*(1+Settings!$C$17/12*(COUNT('WK+CAPEX'!$C$7:N$7)-1)),0) -> 0 | O60: =IF(O$7>=(Settings!$C$51*12+1),HLOOKUP(O$7-Settings!$C$51*12,$C$7:$T$60,#REF!,FALSE)*(1+Settings!$C$17/12*(COUNT('WK+CAPEX'!$C$7:O$7)-1)),0) -> 0 | P60: =IF(P$7>=(Settings!$C$51*12+1),HLOOKUP(P$7-Settings!$C$51*12,$C$7:$T$60,#REF!,FALSE)*(1+Settings!$C$17/12*(COUNT('WK+CAPEX'!$C$7:P$7)-1)),0) -> 0 | ... T60: =IF(T$7>=(Settings!$C$51*12+1),HLOOKUP(T$7-Settings!$C$51*12,$C$7:$T$60,#REF!,FALSE)*(1+Settings!$C$17/12*(COUNT('WK+CAPEX'!$C$7:T$7)-1)),0) -> 0
A61: Total CAPEX | B61: =Settings!$C$6 -> CAD | C61: =SUM(C57:C60) -> 0 | D61: =SUM(D57:D60) -> 0 | E61: =SUM(E57:E60) -> 0 | F61: =SUM(F57:F60) -> 0 | G61: =SUM(G57:G60) -> 0 | H61: =SUM(H57:H60) -> 0 | I61: =SUM(I57:I60) -> 0 | J61: =SUM(J57:J60) -> 0 | ... T61: =SUM(T57:T60) -> 0
A64: DEPRECIATION & AMORTIZATION
A66: Depreciation
A67: Office furniture | B67: =Settings!$C$6 -> CAD | D67: =+IF((E$7-$D$7)<=(Settings!$C47*12),$C57/(Settings!$C47*12),0) -> 0 | E67: =IF((E$7-$D$7)<=(Settings!$C47*12),$D57/(Settings!$C47*12),0)+IF((E$7-$D$7)<=(Settings!$C47*12),$C57/(Settings!$C47*12),0) -> 0 | F67: =IF((F$7-$E$7)<=(Settings!$C47*12),$E57/(Settings!$C47*12),0)+IF((F$7-$D$7)<=(Settings!$C47*12),$D57/(Settings!$C47*12),0)+IF((E$7-$D$7)<=(Settings!$C47*12),$C57/(Settings!$C47*12),0) -> 0 | G67: =IF((G$7-$F$7)<=(Settings!$C47*12),$F57/(Settings!$C47*12),0)+IF((G$7-$E$7)<=(Settings!$C47*12),$E57/(Settings!$C47*12),0)+IF((G$7-$D$7)<=(Settings!$C47*12),$D57/(Settings!$C47*12),0)+IF((E$7-$D$7)<=(Settings!$C47*12),$C57/(Settings!$C47*12),0) -> 0 | H67: =IF((H$7-$G$7)<=(Settings!$C47*12),$G57/(Settings!$C47*12),0)+IF((H$7-$F$7)<=(Settings!$C47*12),$F57/(Settings!$C47*12),0)+IF((H$7-$E$7)<=(Settings!$C47*12),$E57/(Settings!$C47*12),0)+IF((H$7-$D$7)<=(Settings!$C47*12),$D57/(Settings!$C47*12),0)+IF((E$7-$D$7)<=(Settings!$C47*12),$C57/(Settings!$C47*12),0) -> 0 | I67: =IF((I$7-$H$7)<=(Settings!$C47*12),$H57/(Settings!$C47*12),0)+IF((I$7-$G$7)<=(Settings!$C47*12),$G57/(Settings!$C47*12),0)+IF((I$7-$F$7)<=(Settings!$C47*12),$F57/(Settings!$C47*12),0)+IF((I$7-$E$7)<=(Settings!$C47*12),$E57/(Settings!$C47*12),0)+IF((I$7-$D$7)<=(Settings!$C47*12),$D57/(Settings!$C47*12),0)+IF((E$7-$D$7)<=(Settings!$C47*12),$C57/(Settings!$C47*12),0) -> 0 | J67: =IF((J$7-$I$7)<=(Settings!$C47*12),$I57/(Settings!$C47*12),0)+IF((J$7-$H$7)<=(Settings!$C47*12),$H57/(Settings!$C47*12),0)+IF((J$7-$G$7)<=(Settings!$C47*12),$G57/(Settings!$C47*12),0)+IF((J$7-$F$7)<=(Settings!$C47*12),$F57/(Settings!$C47*12),0)+IF((J$7-$E$7)<=(Settings!$C47*12),$E57/(Settings!$C47*12),0)+IF((J$7-$D$7)<=(Settings!$C47*12),$D57/(Settings!$C47*12),0)+IF((E$7-$D$7)<=(Settings!$C47*12),$C57/(Settings!$C47*12),0) -> 0 | K67: =IF((K$7-$J$7)<=(Settings!$C47*12),$J57/(Settings!$C47*12),0)+IF((K$7-$I$7)<=(Settings!$C47*12),$I57/(Settings!$C47*12),0)+IF((K$7-$H$7)<=(Settings!$C47*12),$H57/(Settings!$C47*12),0)+IF((K$7-$G$7)<=(Settings!$C47*12),$G57/(Settings!$C47*12),0)+IF((K$7-$F$7)<=(Settings!$C47*12),$F57/(Settings!$C47*12),0)+IF((K$7-$E$7)<=(Settings!$C47*12),$E57/(Settings!$C47*12),0)+IF((K$7-$D$7)<=(Settings!$C47*12),$D57/(Settings!$C47*12),0)+IF((E$7-$D$7)<=(Settings!$C47*12),$C57/(Settings!$C47*12),0) -> 0 | L67: =IF((L$7-$K$7)<=(Settings!$C47*12),$K57/(Settings!$C47*12),0)+IF((L$7-$J$7)<=(Settings!$C47*12),$J57/(Settings!$C47*12),0)+IF((L$7-$I$7)<=(Settings!$C47*12),$I57/(Settings!$C47*12),0)+IF((L$7-$H$7)<=(Settings!$C47*12),$H57/(Settings!$C47*12),0)+IF((L$7-$G$7)<=(Settings!$C47*12),$G57/(Settings!$C47*12),0)+IF((L$7-$F$7)<=(Settings!$C47*12),$F57/(Settings!$C47*12),0)+IF((L$7-$E$7)<=(Settings!$C47*12),$E57/(Settings!$C47*12),0)+IF((L$7-$D$7)<=(Settings!$C47*12),$D57/(Settings!$C47*12),0)+IF((E$7-$D$7)<=(Settings!$C47*12),$C57/(Settings!$C47*12),0) -> 0 | M67: =IF((M$7-$L$7)<=(Settings!$C47*12),$L57/(Settings!$C47*12),0)+IF((M$7-$K$7)<=(Settings!$C47*12),$K57/(Settings!$C47*12),0)+IF((M$7-$J$7)<=(Settings!$C47*12),$J57/(Settings!$C47*12),0)+IF((M$7-$I$7)<=(Settings!$C47*12),$I57/(Settings!$C47*12),0)+IF((M$7-$H$7)<=(Settings!$C47*12),$H57/(Settings!$C47*12),0)+IF((M$7-$G$7)<=(Settings!$C47*12),$G57/(Settings!$C47*12),0)+IF((M$7-$F$7)<=(Settings!$C47*12),$F57/(Settings!$C47*12),0)+IF((M$7-$E$7)<=(Settings!$C47*12),$E57/(Settings!$C47*12),0)+IF((M$7-$D$7)<=(Settings!$C47*12),$D57/(Settings!$C47*12),0)+IF((E$7-$D$7)<=(Settings!$C47*12),$C57/(Settings!$C47*12),0) -> 0 | N67: =IF((N$7-$M$7)<=(Settings!$C47*12),$M57/(Settings!$C47*12),0)+IF((N$7-$L$7)<=(Settings!$C47*12),$L57/(Settings!$C47*12),0)+IF((N$7-$K$7)<=(Settings!$C47*12),$K57/(Settings!$C47*12),0)+IF((N$7-$J$7)<=(Settings!$C47*12),$J57/(Settings!$C47*12),0)+IF((N$7-$I$7)<=(Settings!$C47*12),$I57/(Settings!$C47*12),0)+IF((N$7-$H$7)<=(Settings!$C47*12),$H57/(Settings!$C47*12),0)+IF((N$7-$G$7)<=(Settings!$C47*12),$G57/(Settings!$C47*12),0)+IF((N$7-$F$7)<=(Settings!$C47*12),$F57/(Settings!$C47*12),0)+IF((N$7-$E$7)<=(Settings!$C47*12),$E57/(Settings!$C47*12),0)+IF((N$7-$D$7)<=(Settings!$C47*12),$D57/(Settings!$C47*12),0)+IF((E$7-$D$7)<=(Settings!$C47*12),$C57/(Settings!$C47*12),0) -> 0 | O67: =IF((O$7-$N$7)<=(Settings!$C47*12),$N57/(Settings!$C47*12),0)+IF((O$7-$M$7)<=(Settings!$C47*12),$M57/(Settings!$C47*12),0)+IF((O$7-$L$7)<=(Settings!$C47*12),$L57/(Settings!$C47*12),0)+IF((O$7-$K$7)<=(Settings!$C47*12),$K57/(Settings!$C47*12),0)+IF((O$7-$J$7)<=(Settings!$C47*12),$J57/(Settings!$C47*12),0)+IF((O$7-$I$7)<=(Settings!$C47*12),$I57/(Settings!$C47*12),0)+IF((O$7-$H$7)<=(Settings!$C47*12),$H57/(Settings!$C47*12),0)+IF((O$7-$G$7)<=(Settings!$C47*12),$G57/(Settings!$C47*12),0)+IF((O$7-$F$7)<=(Settings!$C47*12),$F57/(Settings!$C47*12),0)+IF((O$7-$E$7)<=(Settings!$C47*12),$E57/(Settings!$C47*12),0)+IF((O$7-$D$7)<=(Settings!$C47*12),$D57/(Settings!$C47*12),0)+IF((E$7-$D$7)<=(Settings!$C47*12),$C57/(Settings!$C47*12),0) -> 0 | P67: =IF((P$7-$O$7)<=(Settings!$C47*12),$O57/(Settings!$C47*12),0)+IF((P$7-$N$7)<=(Settings!$C47*12),$N57/(Settings!$C47*12),0)+IF((P$7-$M$7)<=(Settings!$C47*12),$M57/(Settings!$C47*12),0)+IF((P$7-$L$7)<=(Settings!$C47*12),$L57/(Settings!$C47*12),0)+IF((P$7-$K$7)<=(Settings!$C47*12),$K57/(Settings!$C47*12),0)+IF((P$7-$J$7)<=(Settings!$C47*12),$J57/(Settings!$C47*12),0)+IF((P$7-$I$7)<=(Settings!$C47*12),$I57/(Settings!$C47*12),0)+IF((P$7-$H$7)<=(Settings!$C47*12),$H57/(Settings!$C47*12),0)+IF((P$7-$G$7)<=(Settings!$C47*12),$G57/(Settings!$C47*12),0)+IF((P$7-$F$7)<=(Settings!$C47*12),$F57/(Settings!$C47*12),0)+IF((P$7-$E$7)<=(Settings!$C47*12),$E57/(Settings!$C47*12),0)+IF((P$7-$D$7)<=(Settings!$C47*12),$D57/(Settings!$C47*12),0)+IF((E$7-$D$7)<=(Settings!$C47*12),$C57/(Settings!$C47*12),0) -> 0 | Q67: =IF((Q$7-$P$7)<=(Settings!$C47*12),$P57/(Settings!$C47*12),0)+IF((Q$7-$O$7)<=(Settings!$C47*12),$O57/(Settings!$C47*12),0)+IF((Q$7-$N$7)<=(Settings!$C47*12),$N57/(Settings!$C47*12),0)+IF((Q$7-$M$7)<=(Settings!$C47*12),$M57/(Settings!$C47*12),0)+IF((Q$7-$L$7)<=(Settings!$C47*12),$L57/(Settings!$C47*12),0)+IF((Q$7-$K$7)<=(Settings!$C47*12),$K57/(Settings!$C47*12),0)+IF((Q$7-$J$7)<=(Settings!$C47*12),$J57/(Settings!$C47*12),0)+IF((Q$7-$I$7)<=(Settings!$C47*12),$I57/(Settings!$C47*12),0)+IF((Q$7-$H$7)<=(Settings!$C47*12),$H57/(Settings!$C47*12),0)+IF((Q$7-$G$7)<=(Settings!$C47*12),$G57/(Settings!$C47*12),0)+IF((Q$7-$F$7)<=(Settings!$C47*12),$F57/(Settings!$C47*12),0)+IF((Q$7-$E$7)<=(Settings!$C47*12),$E57/(Settings!$C47*12),0)+IF((Q$7-$D$7)<=(Settings!$C47*12),$D57/(Settings!$C47*12),0)+IF((E$7-$D$7)<=(Settings!$C47*12),$C57/(Settings!$C47*12),0) -> 0 | R67: =IF((R$7-$Q$7)<=(Settings!$C47*12),$Q57/(Settings!$C47*12),0)+IF((R$7-$P$7)<=(Settings!$C47*12),$P57/(Settings!$C47*12),0)+IF((R$7-$O$7)<=(Settings!$C47*12),$O57/(Settings!$C47*12),0)+IF((R$7-$N$7)<=(Settings!$C47*12),$N57/(Settings!$C47*12),0)+IF((R$7-$M$7)<=(Settings!$C47*12),$M57/(Settings!$C47*12),0)+IF((R$7-$L$7)<=(Settings!$C47*12),$L57/(Settings!$C47*12),0)+IF((R$7-$K$7)<=(Settings!$C47*12),$K57/(Settings!$C47*12),0)+IF((R$7-$J$7)<=(Settings!$C47*12),$J57/(Settings!$C47*12),0)+IF((R$7-$I$7)<=(Settings!$C47*12),$I57/(Settings!$C47*12),0)+IF((R$7-$H$7)<=(Settings!$C47*12),$H57/(Settings!$C47*12),0)+IF((R$7-$G$7)<=(Settings!$C47*12),$G57/(Settings!$C47*12),0)+IF((R$7-$F$7)<=(Settings!$C47*12),$F57/(Settings!$C47*12),0)+IF((R$7-$E$7)<=(Settings!$C47*12),$E57/(Settings!$C47*12),0)+IF((R$7-$D$7)<=(Settings!$C47*12),$D57/(Settings!$C47*12),0)+IF((E$7-$D$7)<=(Settings!$C47*12),$C57/(Settings!$C47*12),0) -> 0 | S67: =IF((S$7-$R$7)<=(Settings!$C47*12),$R57/(Settings!$C47*12),0)+IF((S$7-$Q$7)<=(Settings!$C47*12),$Q57/(Settings!$C47*12),0)+IF((S$7-$P$7)<=(Settings!$C47*12),$P57/(Settings!$C47*12),0)+IF((S$7-$O$7)<=(Settings!$C47*12),$O57/(Settings!$C47*12),0)+IF((S$7-$N$7)<=(Settings!$C47*12),$N57/(Settings!$C47*12),0)+IF((S$7-$M$7)<=(Settings!$C47*12),$M57/(Settings!$C47*12),0)+IF((S$7-$L$7)<=(Settings!$C47*12),$L57/(Settings!$C47*12),0)+IF((S$7-$K$7)<=(Settings!$C47*12),$K57/(Settings!$C47*12),0)+IF((S$7-$J$7)<=(Settings!$C47*12),$J57/(Settings!$C47*12),0)+IF((S$7-$I$7)<=(Settings!$C47*12),$I57/(Settings!$C47*12),0)+IF((S$7-$H$7)<=(Settings!$C47*12),$H57/(Settings!$C47*12),0)+IF((S$7-$G$7)<=(Settings!$C47*12),$G57/(Settings!$C47*12),0)+IF((S$7-$F$7)<=(Settings!$C47*12),$F57/(Settings!$C47*12),0)+IF((S$7-$E$7)<=(Settings!$C47*12),$E57/(Settings!$C47*12),0)+IF((S$7-$D$7)<=(Settings!$C47*12),$D57/(Settings!$C47*12),0)+IF((E$7-$D$7)<=(Settings!$C47*12),$C57/(Settings!$C47*12),0) -> 0 | T67: =IF((T$7-$S$7)<=(Settings!$C47*12),$S57/(Settings!$C47*12),0)+IF((T$7-$R$7)<=(Settings!$C47*12),$R57/(Settings!$C47*12),0)+IF((T$7-$Q$7)<=(Settings!$C47*12),$Q57/(Settings!$C47*12),0)+IF((T$7-$P$7)<=(Settings!$C47*12),$P57/(Settings!$C47*12),0)+IF((T$7-$O$7)<=(Settings!$C47*12),$O57/(Settings!$C47*12),0)+IF((T$7-$N$7)<=(Settings!$C47*12),$N57/(Settings!$C47*12),0)+IF((T$7-$M$7)<=(Settings!$C47*12),$M57/(Settings!$C47*12),0)+IF((T$7-$L$7)<=(Settings!$C47*12),$L57/(Settings!$C47*12),0)+IF((T$7-$K$7)<=(Settings!$C47*12),$K57/(Settings!$C47*12),0)+IF((T$7-$J$7)<=(Settings!$C47*12),$J57/(Settings!$C47*12),0)+IF((T$7-$I$7)<=(Settings!$C47*12),$I57/(Settings!$C47*12),0)+IF((T$7-$H$7)<=(Settings!$C47*12),$H57/(Settings!$C47*12),0)+IF((T$7-$G$7)<=(Settings!$C47*12),$G57/(Settings!$C47*12),0)+IF((T$7-$F$7)<=(Settings!$C47*12),$F57/(Settings!$C47*12),0)+IF((T$7-$E$7)<=(Settings!$C47*12),$E57/(Settings!$C47*12),0)+IF((T$7-$D$7)<=(Settings!$C47*12),$D57/(Settings!$C47*12),0)+IF((E$7-$D$7)<=(Settings!$C47*12),$C57/(Settings!$C47*12),0) -> 0
A68: Computers | B68: =Settings!$C$6 -> CAD | D68: =+IF((E$7-$D$7)<=(Settings!$C48*12),$C58/(Settings!$C48*12),0) -> 0 | E68: =IF((E$7-$D$7)<=(Settings!$C48*12),$D58/(Settings!$C48*12),0)+IF((E$7-$D$7)<=(Settings!$C48*12),$C58/(Settings!$C48*12),0) -> 0 | F68: =IF((F$7-$E$7)<=(Settings!$C48*12),$E58/(Settings!$C48*12),0)+IF((F$7-$D$7)<=(Settings!$C48*12),$D58/(Settings!$C48*12),0)+IF((E$7-$D$7)<=(Settings!$C48*12),$C58/(Settings!$C48*12),0) -> 0 | G68: =IF((G$7-$F$7)<=(Settings!$C48*12),$F58/(Settings!$C48*12),0)+IF((G$7-$E$7)<=(Settings!$C48*12),$E58/(Settings!$C48*12),0)+IF((G$7-$D$7)<=(Settings!$C48*12),$D58/(Settings!$C48*12),0)+IF((E$7-$D$7)<=(Settings!$C48*12),$C58/(Settings!$C48*12),0) -> 0 | H68: =IF((H$7-$G$7)<=(Settings!$C48*12),$G58/(Settings!$C48*12),0)+IF((H$7-$F$7)<=(Settings!$C48*12),$F58/(Settings!$C48*12),0)+IF((H$7-$E$7)<=(Settings!$C48*12),$E58/(Settings!$C48*12),0)+IF((H$7-$D$7)<=(Settings!$C48*12),$D58/(Settings!$C48*12),0)+IF((E$7-$D$7)<=(Settings!$C48*12),$C58/(Settings!$C48*12),0) -> 0 | I68: =IF((I$7-$H$7)<=(Settings!$C48*12),$H58/(Settings!$C48*12),0)+IF((I$7-$G$7)<=(Settings!$C48*12),$G58/(Settings!$C48*12),0)+IF((I$7-$F$7)<=(Settings!$C48*12),$F58/(Settings!$C48*12),0)+IF((I$7-$E$7)<=(Settings!$C48*12),$E58/(Settings!$C48*12),0)+IF((I$7-$D$7)<=(Settings!$C48*12),$D58/(Settings!$C48*12),0)+IF((E$7-$D$7)<=(Settings!$C48*12),$C58/(Settings!$C48*12),0) -> 0 | J68: =IF((J$7-$I$7)<=(Settings!$C48*12),$I58/(Settings!$C48*12),0)+IF((J$7-$H$7)<=(Settings!$C48*12),$H58/(Settings!$C48*12),0)+IF((J$7-$G$7)<=(Settings!$C48*12),$G58/(Settings!$C48*12),0)+IF((J$7-$F$7)<=(Settings!$C48*12),$F58/(Settings!$C48*12),0)+IF((J$7-$E$7)<=(Settings!$C48*12),$E58/(Settings!$C48*12),0)+IF((J$7-$D$7)<=(Settings!$C48*12),$D58/(Settings!$C48*12),0)+IF((E$7-$D$7)<=(Settings!$C48*12),$C58/(Settings!$C48*12),0) -> 0 | K68: =IF((K$7-$J$7)<=(Settings!$C48*12),$J58/(Settings!$C48*12),0)+IF((K$7-$I$7)<=(Settings!$C48*12),$I58/(Settings!$C48*12),0)+IF((K$7-$H$7)<=(Settings!$C48*12),$H58/(Settings!$C48*12),0)+IF((K$7-$G$7)<=(Settings!$C48*12),$G58/(Settings!$C48*12),0)+IF((K$7-$F$7)<=(Settings!$C48*12),$F58/(Settings!$C48*12),0)+IF((K$7-$E$7)<=(Settings!$C48*12),$E58/(Settings!$C48*12),0)+IF((K$7-$D$7)<=(Settings!$C48*12),$D58/(Settings!$C48*12),0)+IF((E$7-$D$7)<=(Settings!$C48*12),$C58/(Settings!$C48*12),0) -> 0 | L68: =IF((L$7-$K$7)<=(Settings!$C48*12),$K58/(Settings!$C48*12),0)+IF((L$7-$J$7)<=(Settings!$C48*12),$J58/(Settings!$C48*12),0)+IF((L$7-$I$7)<=(Settings!$C48*12),$I58/(Settings!$C48*12),0)+IF((L$7-$H$7)<=(Settings!$C48*12),$H58/(Settings!$C48*12),0)+IF((L$7-$G$7)<=(Settings!$C48*12),$G58/(Settings!$C48*12),0)+IF((L$7-$F$7)<=(Settings!$C48*12),$F58/(Settings!$C48*12),0)+IF((L$7-$E$7)<=(Settings!$C48*12),$E58/(Settings!$C48*12),0)+IF((L$7-$D$7)<=(Settings!$C48*12),$D58/(Settings!$C48*12),0)+IF((E$7-$D$7)<=(Settings!$C48*12),$C58/(Settings!$C48*12),0) -> 0 | M68: =IF((M$7-$L$7)<=(Settings!$C48*12),$L58/(Settings!$C48*12),0)+IF((M$7-$K$7)<=(Settings!$C48*12),$K58/(Settings!$C48*12),0)+IF((M$7-$J$7)<=(Settings!$C48*12),$J58/(Settings!$C48*12),0)+IF((M$7-$I$7)<=(Settings!$C48*12),$I58/(Settings!$C48*12),0)+IF((M$7-$H$7)<=(Settings!$C48*12),$H58/(Settings!$C48*12),0)+IF((M$7-$G$7)<=(Settings!$C48*12),$G58/(Settings!$C48*12),0)+IF((M$7-$F$7)<=(Settings!$C48*12),$F58/(Settings!$C48*12),0)+IF((M$7-$E$7)<=(Settings!$C48*12),$E58/(Settings!$C48*12),0)+IF((M$7-$D$7)<=(Settings!$C48*12),$D58/(Settings!$C48*12),0)+IF((E$7-$D$7)<=(Settings!$C48*12),$C58/(Settings!$C48*12),0) -> 0 | N68: =IF((N$7-$M$7)<=(Settings!$C48*12),$M58/(Settings!$C48*12),0)+IF((N$7-$L$7)<=(Settings!$C48*12),$L58/(Settings!$C48*12),0)+IF((N$7-$K$7)<=(Settings!$C48*12),$K58/(Settings!$C48*12),0)+IF((N$7-$J$7)<=(Settings!$C48*12),$J58/(Settings!$C48*12),0)+IF((N$7-$I$7)<=(Settings!$C48*12),$I58/(Settings!$C48*12),0)+IF((N$7-$H$7)<=(Settings!$C48*12),$H58/(Settings!$C48*12),0)+IF((N$7-$G$7)<=(Settings!$C48*12),$G58/(Settings!$C48*12),0)+IF((N$7-$F$7)<=(Settings!$C48*12),$F58/(Settings!$C48*12),0)+IF((N$7-$E$7)<=(Settings!$C48*12),$E58/(Settings!$C48*12),0)+IF((N$7-$D$7)<=(Settings!$C48*12),$D58/(Settings!$C48*12),0)+IF((E$7-$D$7)<=(Settings!$C48*12),$C58/(Settings!$C48*12),0) -> 0 | O68: =IF((O$7-$N$7)<=(Settings!$C48*12),$N58/(Settings!$C48*12),0)+IF((O$7-$M$7)<=(Settings!$C48*12),$M58/(Settings!$C48*12),0)+IF((O$7-$L$7)<=(Settings!$C48*12),$L58/(Settings!$C48*12),0)+IF((O$7-$K$7)<=(Settings!$C48*12),$K58/(Settings!$C48*12),0)+IF((O$7-$J$7)<=(Settings!$C48*12),$J58/(Settings!$C48*12),0)+IF((O$7-$I$7)<=(Settings!$C48*12),$I58/(Settings!$C48*12),0)+IF((O$7-$H$7)<=(Settings!$C48*12),$H58/(Settings!$C48*12),0)+IF((O$7-$G$7)<=(Settings!$C48*12),$G58/(Settings!$C48*12),0)+IF((O$7-$F$7)<=(Settings!$C48*12),$F58/(Settings!$C48*12),0)+IF((O$7-$E$7)<=(Settings!$C48*12),$E58/(Settings!$C48*12),0)+IF((O$7-$D$7)<=(Settings!$C48*12),$D58/(Settings!$C48*12),0)+IF((E$7-$D$7)<=(Settings!$C48*12),$C58/(Settings!$C48*12),0) -> 0 | P68: =IF((P$7-$O$7)<=(Settings!$C48*12),$O58/(Settings!$C48*12),0)+IF((P$7-$N$7)<=(Settings!$C48*12),$N58/(Settings!$C48*12),0)+IF((P$7-$M$7)<=(Settings!$C48*12),$M58/(Settings!$C48*12),0)+IF((P$7-$L$7)<=(Settings!$C48*12),$L58/(Settings!$C48*12),0)+IF((P$7-$K$7)<=(Settings!$C48*12),$K58/(Settings!$C48*12),0)+IF((P$7-$J$7)<=(Settings!$C48*12),$J58/(Settings!$C48*12),0)+IF((P$7-$I$7)<=(Settings!$C48*12),$I58/(Settings!$C48*12),0)+IF((P$7-$H$7)<=(Settings!$C48*12),$H58/(Settings!$C48*12),0)+IF((P$7-$G$7)<=(Settings!$C48*12),$G58/(Settings!$C48*12),0)+IF((P$7-$F$7)<=(Settings!$C48*12),$F58/(Settings!$C48*12),0)+IF((P$7-$E$7)<=(Settings!$C48*12),$E58/(Settings!$C48*12),0)+IF((P$7-$D$7)<=(Settings!$C48*12),$D58/(Settings!$C48*12),0)+IF((E$7-$D$7)<=(Settings!$C48*12),$C58/(Settings!$C48*12),0) -> 0 | Q68: =IF((Q$7-$P$7)<=(Settings!$C48*12),$P58/(Settings!$C48*12),0)+IF((Q$7-$O$7)<=(Settings!$C48*12),$O58/(Settings!$C48*12),0)+IF((Q$7-$N$7)<=(Settings!$C48*12),$N58/(Settings!$C48*12),0)+IF((Q$7-$M$7)<=(Settings!$C48*12),$M58/(Settings!$C48*12),0)+IF((Q$7-$L$7)<=(Settings!$C48*12),$L58/(Settings!$C48*12),0)+IF((Q$7-$K$7)<=(Settings!$C48*12),$K58/(Settings!$C48*12),0)+IF((Q$7-$J$7)<=(Settings!$C48*12),$J58/(Settings!$C48*12),0)+IF((Q$7-$I$7)<=(Settings!$C48*12),$I58/(Settings!$C48*12),0)+IF((Q$7-$H$7)<=(Settings!$C48*12),$H58/(Settings!$C48*12),0)+IF((Q$7-$G$7)<=(Settings!$C48*12),$G58/(Settings!$C48*12),0)+IF((Q$7-$F$7)<=(Settings!$C48*12),$F58/(Settings!$C48*12),0)+IF((Q$7-$E$7)<=(Settings!$C48*12),$E58/(Settings!$C48*12),0)+IF((Q$7-$D$7)<=(Settings!$C48*12),$D58/(Settings!$C48*12),0)+IF((E$7-$D$7)<=(Settings!$C48*12),$C58/(Settings!$C48*12),0) -> 0 | R68: =IF((R$7-$Q$7)<=(Settings!$C48*12),$Q58/(Settings!$C48*12),0)+IF((R$7-$P$7)<=(Settings!$C48*12),$P58/(Settings!$C48*12),0)+IF((R$7-$O$7)<=(Settings!$C48*12),$O58/(Settings!$C48*12),0)+IF((R$7-$N$7)<=(Settings!$C48*12),$N58/(Settings!$C48*12),0)+IF((R$7-$M$7)<=(Settings!$C48*12),$M58/(Settings!$C48*12),0)+IF((R$7-$L$7)<=(Settings!$C48*12),$L58/(Settings!$C48*12),0)+IF((R$7-$K$7)<=(Settings!$C48*12),$K58/(Settings!$C48*12),0)+IF((R$7-$J$7)<=(Settings!$C48*12),$J58/(Settings!$C48*12),0)+IF((R$7-$I$7)<=(Settings!$C48*12),$I58/(Settings!$C48*12),0)+IF((R$7-$H$7)<=(Settings!$C48*12),$H58/(Settings!$C48*12),0)+IF((R$7-$G$7)<=(Settings!$C48*12),$G58/(Settings!$C48*12),0)+IF((R$7-$F$7)<=(Settings!$C48*12),$F58/(Settings!$C48*12),0)+IF((R$7-$E$7)<=(Settings!$C48*12),$E58/(Settings!$C48*12),0)+IF((R$7-$D$7)<=(Settings!$C48*12),$D58/(Settings!$C48*12),0)+IF((E$7-$D$7)<=(Settings!$C48*12),$C58/(Settings!$C48*12),0) -> 0 | S68: =IF((S$7-$R$7)<=(Settings!$C48*12),$R58/(Settings!$C48*12),0)+IF((S$7-$Q$7)<=(Settings!$C48*12),$Q58/(Settings!$C48*12),0)+IF((S$7-$P$7)<=(Settings!$C48*12),$P58/(Settings!$C48*12),0)+IF((S$7-$O$7)<=(Settings!$C48*12),$O58/(Settings!$C48*12),0)+IF((S$7-$N$7)<=(Settings!$C48*12),$N58/(Settings!$C48*12),0)+IF((S$7-$M$7)<=(Settings!$C48*12),$M58/(Settings!$C48*12),0)+IF((S$7-$L$7)<=(Settings!$C48*12),$L58/(Settings!$C48*12),0)+IF((S$7-$K$7)<=(Settings!$C48*12),$K58/(Settings!$C48*12),0)+IF((S$7-$J$7)<=(Settings!$C48*12),$J58/(Settings!$C48*12),0)+IF((S$7-$I$7)<=(Settings!$C48*12),$I58/(Settings!$C48*12),0)+IF((S$7-$H$7)<=(Settings!$C48*12),$H58/(Settings!$C48*12),0)+IF((S$7-$G$7)<=(Settings!$C48*12),$G58/(Settings!$C48*12),0)+IF((S$7-$F$7)<=(Settings!$C48*12),$F58/(Settings!$C48*12),0)+IF((S$7-$E$7)<=(Settings!$C48*12),$E58/(Settings!$C48*12),0)+IF((S$7-$D$7)<=(Settings!$C48*12),$D58/(Settings!$C48*12),0)+IF((E$7-$D$7)<=(Settings!$C48*12),$C58/(Settings!$C48*12),0) -> 0 | T68: =IF((T$7-$S$7)<=(Settings!$C48*12),$S58/(Settings!$C48*12),0)+IF((T$7-$R$7)<=(Settings!$C48*12),$R58/(Settings!$C48*12),0)+IF((T$7-$Q$7)<=(Settings!$C48*12),$Q58/(Settings!$C48*12),0)+IF((T$7-$P$7)<=(Settings!$C48*12),$P58/(Settings!$C48*12),0)+IF((T$7-$O$7)<=(Settings!$C48*12),$O58/(Settings!$C48*12),0)+IF((T$7-$N$7)<=(Settings!$C48*12),$N58/(Settings!$C48*12),0)+IF((T$7-$M$7)<=(Settings!$C48*12),$M58/(Settings!$C48*12),0)+IF((T$7-$L$7)<=(Settings!$C48*12),$L58/(Settings!$C48*12),0)+IF((T$7-$K$7)<=(Settings!$C48*12),$K58/(Settings!$C48*12),0)+IF((T$7-$J$7)<=(Settings!$C48*12),$J58/(Settings!$C48*12),0)+IF((T$7-$I$7)<=(Settings!$C48*12),$I58/(Settings!$C48*12),0)+IF((T$7-$H$7)<=(Settings!$C48*12),$H58/(Settings!$C48*12),0)+IF((T$7-$G$7)<=(Settings!$C48*12),$G58/(Settings!$C48*12),0)+IF((T$7-$F$7)<=(Settings!$C48*12),$F58/(Settings!$C48*12),0)+IF((T$7-$E$7)<=(Settings!$C48*12),$E58/(Settings!$C48*12),0)+IF((T$7-$D$7)<=(Settings!$C48*12),$D58/(Settings!$C48*12),0)+IF((E$7-$D$7)<=(Settings!$C48*12),$C58/(Settings!$C48*12),0) -> 0
A69: Servers & other tech infrastructure | B69: =Settings!$C$6 -> CAD | D69: =+IF((E$7-$D$7)<=(Settings!$C50*12),$C59/(Settings!$C50*12),0) -> 0 | E69: =IF((E$7-$D$7)<=(Settings!$C50*12),$D59/(Settings!$C50*12),0)+IF((E$7-$D$7)<=(Settings!$C50*12),$C59/(Settings!$C50*12),0) -> 0 | F69: =IF((F$7-$E$7)<=(Settings!$C50*12),$E59/(Settings!$C50*12),0)+IF((F$7-$D$7)<=(Settings!$C50*12),$D59/(Settings!$C50*12),0)+IF((E$7-$D$7)<=(Settings!$C50*12),$C59/(Settings!$C50*12),0) -> 0 | G69: =IF((G$7-$F$7)<=(Settings!$C50*12),$F59/(Settings!$C50*12),0)+IF((G$7-$E$7)<=(Settings!$C50*12),$E59/(Settings!$C50*12),0)+IF((G$7-$D$7)<=(Settings!$C50*12),$D59/(Settings!$C50*12),0)+IF((E$7-$D$7)<=(Settings!$C50*12),$C59/(Settings!$C50*12),0) -> 0 | H69: =IF((H$7-$G$7)<=(Settings!$C50*12),$G59/(Settings!$C50*12),0)+IF((H$7-$F$7)<=(Settings!$C50*12),$F59/(Settings!$C50*12),0)+IF((H$7-$E$7)<=(Settings!$C50*12),$E59/(Settings!$C50*12),0)+IF((H$7-$D$7)<=(Settings!$C50*12),$D59/(Settings!$C50*12),0)+IF((E$7-$D$7)<=(Settings!$C50*12),$C59/(Settings!$C50*12),0) -> 0 | I69: =IF((I$7-$H$7)<=(Settings!$C50*12),$H59/(Settings!$C50*12),0)+IF((I$7-$G$7)<=(Settings!$C50*12),$G59/(Settings!$C50*12),0)+IF((I$7-$F$7)<=(Settings!$C50*12),$F59/(Settings!$C50*12),0)+IF((I$7-$E$7)<=(Settings!$C50*12),$E59/(Settings!$C50*12),0)+IF((I$7-$D$7)<=(Settings!$C50*12),$D59/(Settings!$C50*12),0)+IF((E$7-$D$7)<=(Settings!$C50*12),$C59/(Settings!$C50*12),0) -> 0 | J69: =IF((J$7-$I$7)<=(Settings!$C50*12),$I59/(Settings!$C50*12),0)+IF((J$7-$H$7)<=(Settings!$C50*12),$H59/(Settings!$C50*12),0)+IF((J$7-$G$7)<=(Settings!$C50*12),$G59/(Settings!$C50*12),0)+IF((J$7-$F$7)<=(Settings!$C50*12),$F59/(Settings!$C50*12),0)+IF((J$7-$E$7)<=(Settings!$C50*12),$E59/(Settings!$C50*12),0)+IF((J$7-$D$7)<=(Settings!$C50*12),$D59/(Settings!$C50*12),0)+IF((E$7-$D$7)<=(Settings!$C50*12),$C59/(Settings!$C50*12),0) -> 0 | K69: =IF((K$7-$J$7)<=(Settings!$C50*12),$J59/(Settings!$C50*12),0)+IF((K$7-$I$7)<=(Settings!$C50*12),$I59/(Settings!$C50*12),0)+IF((K$7-$H$7)<=(Settings!$C50*12),$H59/(Settings!$C50*12),0)+IF((K$7-$G$7)<=(Settings!$C50*12),$G59/(Settings!$C50*12),0)+IF((K$7-$F$7)<=(Settings!$C50*12),$F59/(Settings!$C50*12),0)+IF((K$7-$E$7)<=(Settings!$C50*12),$E59/(Settings!$C50*12),0)+IF((K$7-$D$7)<=(Settings!$C50*12),$D59/(Settings!$C50*12),0)+IF((E$7-$D$7)<=(Settings!$C50*12),$C59/(Settings!$C50*12),0) -> 0 | L69: =IF((L$7-$K$7)<=(Settings!$C50*12),$K59/(Settings!$C50*12),0)+IF((L$7-$J$7)<=(Settings!$C50*12),$J59/(Settings!$C50*12),0)+IF((L$7-$I$7)<=(Settings!$C50*12),$I59/(Settings!$C50*12),0)+IF((L$7-$H$7)<=(Settings!$C50*12),$H59/(Settings!$C50*12),0)+IF((L$7-$G$7)<=(Settings!$C50*12),$G59/(Settings!$C50*12),0)+IF((L$7-$F$7)<=(Settings!$C50*12),$F59/(Settings!$C50*12),0)+IF((L$7-$E$7)<=(Settings!$C50*12),$E59/(Settings!$C50*12),0)+IF((L$7-$D$7)<=(Settings!$C50*12),$D59/(Settings!$C50*12),0)+IF((E$7-$D$7)<=(Settings!$C50*12),$C59/(Settings!$C50*12),0) -> 0 | M69: =IF((M$7-$L$7)<=(Settings!$C50*12),$L59/(Settings!$C50*12),0)+IF((M$7-$K$7)<=(Settings!$C50*12),$K59/(Settings!$C50*12),0)+IF((M$7-$J$7)<=(Settings!$C50*12),$J59/(Settings!$C50*12),0)+IF((M$7-$I$7)<=(Settings!$C50*12),$I59/(Settings!$C50*12),0)+IF((M$7-$H$7)<=(Settings!$C50*12),$H59/(Settings!$C50*12),0)+IF((M$7-$G$7)<=(Settings!$C50*12),$G59/(Settings!$C50*12),0)+IF((M$7-$F$7)<=(Settings!$C50*12),$F59/(Settings!$C50*12),0)+IF((M$7-$E$7)<=(Settings!$C50*12),$E59/(Settings!$C50*12),0)+IF((M$7-$D$7)<=(Settings!$C50*12),$D59/(Settings!$C50*12),0)+IF((E$7-$D$7)<=(Settings!$C50*12),$C59/(Settings!$C50*12),0) -> 0 | N69: =IF((N$7-$M$7)<=(Settings!$C50*12),$M59/(Settings!$C50*12),0)+IF((N$7-$L$7)<=(Settings!$C50*12),$L59/(Settings!$C50*12),0)+IF((N$7-$K$7)<=(Settings!$C50*12),$K59/(Settings!$C50*12),0)+IF((N$7-$J$7)<=(Settings!$C50*12),$J59/(Settings!$C50*12),0)+IF((N$7-$I$7)<=(Settings!$C50*12),$I59/(Settings!$C50*12),0)+IF((N$7-$H$7)<=(Settings!$C50*12),$H59/(Settings!$C50*12),0)+IF((N$7-$G$7)<=(Settings!$C50*12),$G59/(Settings!$C50*12),0)+IF((N$7-$F$7)<=(Settings!$C50*12),$F59/(Settings!$C50*12),0)+IF((N$7-$E$7)<=(Settings!$C50*12),$E59/(Settings!$C50*12),0)+IF((N$7-$D$7)<=(Settings!$C50*12),$D59/(Settings!$C50*12),0)+IF((E$7-$D$7)<=(Settings!$C50*12),$C59/(Settings!$C50*12),0) -> 0 | O69: =IF((O$7-$N$7)<=(Settings!$C50*12),$N59/(Settings!$C50*12),0)+IF((O$7-$M$7)<=(Settings!$C50*12),$M59/(Settings!$C50*12),0)+IF((O$7-$L$7)<=(Settings!$C50*12),$L59/(Settings!$C50*12),0)+IF((O$7-$K$7)<=(Settings!$C50*12),$K59/(Settings!$C50*12),0)+IF((O$7-$J$7)<=(Settings!$C50*12),$J59/(Settings!$C50*12),0)+IF((O$7-$I$7)<=(Settings!$C50*12),$I59/(Settings!$C50*12),0)+IF((O$7-$H$7)<=(Settings!$C50*12),$H59/(Settings!$C50*12),0)+IF((O$7-$G$7)<=(Settings!$C50*12),$G59/(Settings!$C50*12),0)+IF((O$7-$F$7)<=(Settings!$C50*12),$F59/(Settings!$C50*12),0)+IF((O$7-$E$7)<=(Settings!$C50*12),$E59/(Settings!$C50*12),0)+IF((O$7-$D$7)<=(Settings!$C50*12),$D59/(Settings!$C50*12),0)+IF((E$7-$D$7)<=(Settings!$C50*12),$C59/(Settings!$C50*12),0) -> 0 | P69: =IF((P$7-$O$7)<=(Settings!$C50*12),$O59/(Settings!$C50*12),0)+IF((P$7-$N$7)<=(Settings!$C50*12),$N59/(Settings!$C50*12),0)+IF((P$7-$M$7)<=(Settings!$C50*12),$M59/(Settings!$C50*12),0)+IF((P$7-$L$7)<=(Settings!$C50*12),$L59/(Settings!$C50*12),0)+IF((P$7-$K$7)<=(Settings!$C50*12),$K59/(Settings!$C50*12),0)+IF((P$7-$J$7)<=(Settings!$C50*12),$J59/(Settings!$C50*12),0)+IF((P$7-$I$7)<=(Settings!$C50*12),$I59/(Settings!$C50*12),0)+IF((P$7-$H$7)<=(Settings!$C50*12),$H59/(Settings!$C50*12),0)+IF((P$7-$G$7)<=(Settings!$C50*12),$G59/(Settings!$C50*12),0)+IF((P$7-$F$7)<=(Settings!$C50*12),$F59/(Settings!$C50*12),0)+IF((P$7-$E$7)<=(Settings!$C50*12),$E59/(Settings!$C50*12),0)+IF((P$7-$D$7)<=(Settings!$C50*12),$D59/(Settings!$C50*12),0)+IF((E$7-$D$7)<=(Settings!$C50*12),$C59/(Settings!$C50*12),0) -> 0 | Q69: =IF((Q$7-$P$7)<=(Settings!$C50*12),$P59/(Settings!$C50*12),0)+IF((Q$7-$O$7)<=(Settings!$C50*12),$O59/(Settings!$C50*12),0)+IF((Q$7-$N$7)<=(Settings!$C50*12),$N59/(Settings!$C50*12),0)+IF((Q$7-$M$7)<=(Settings!$C50*12),$M59/(Settings!$C50*12),0)+IF((Q$7-$L$7)<=(Settings!$C50*12),$L59/(Settings!$C50*12),0)+IF((Q$7-$K$7)<=(Settings!$C50*12),$K59/(Settings!$C50*12),0)+IF((Q$7-$J$7)<=(Settings!$C50*12),$J59/(Settings!$C50*12),0)+IF((Q$7-$I$7)<=(Settings!$C50*12),$I59/(Settings!$C50*12),0)+IF((Q$7-$H$7)<=(Settings!$C50*12),$H59/(Settings!$C50*12),0)+IF((Q$7-$G$7)<=(Settings!$C50*12),$G59/(Settings!$C50*12),0)+IF((Q$7-$F$7)<=(Settings!$C50*12),$F59/(Settings!$C50*12),0)+IF((Q$7-$E$7)<=(Settings!$C50*12),$E59/(Settings!$C50*12),0)+IF((Q$7-$D$7)<=(Settings!$C50*12),$D59/(Settings!$C50*12),0)+IF((E$7-$D$7)<=(Settings!$C50*12),$C59/(Settings!$C50*12),0) -> 0 | R69: =IF((R$7-$Q$7)<=(Settings!$C50*12),$Q59/(Settings!$C50*12),0)+IF((R$7-$P$7)<=(Settings!$C50*12),$P59/(Settings!$C50*12),0)+IF((R$7-$O$7)<=(Settings!$C50*12),$O59/(Settings!$C50*12),0)+IF((R$7-$N$7)<=(Settings!$C50*12),$N59/(Settings!$C50*12),0)+IF((R$7-$M$7)<=(Settings!$C50*12),$M59/(Settings!$C50*12),0)+IF((R$7-$L$7)<=(Settings!$C50*12),$L59/(Settings!$C50*12),0)+IF((R$7-$K$7)<=(Settings!$C50*12),$K59/(Settings!$C50*12),0)+IF((R$7-$J$7)<=(Settings!$C50*12),$J59/(Settings!$C50*12),0)+IF((R$7-$I$7)<=(Settings!$C50*12),$I59/(Settings!$C50*12),0)+IF((R$7-$H$7)<=(Settings!$C50*12),$H59/(Settings!$C50*12),0)+IF((R$7-$G$7)<=(Settings!$C50*12),$G59/(Settings!$C50*12),0)+IF((R$7-$F$7)<=(Settings!$C50*12),$F59/(Settings!$C50*12),0)+IF((R$7-$E$7)<=(Settings!$C50*12),$E59/(Settings!$C50*12),0)+IF((R$7-$D$7)<=(Settings!$C50*12),$D59/(Settings!$C50*12),0)+IF((E$7-$D$7)<=(Settings!$C50*12),$C59/(Settings!$C50*12),0) -> 0 | S69: =IF((S$7-$R$7)<=(Settings!$C50*12),$R59/(Settings!$C50*12),0)+IF((S$7-$Q$7)<=(Settings!$C50*12),$Q59/(Settings!$C50*12),0)+IF((S$7-$P$7)<=(Settings!$C50*12),$P59/(Settings!$C50*12),0)+IF((S$7-$O$7)<=(Settings!$C50*12),$O59/(Settings!$C50*12),0)+IF((S$7-$N$7)<=(Settings!$C50*12),$N59/(Settings!$C50*12),0)+IF((S$7-$M$7)<=(Settings!$C50*12),$M59/(Settings!$C50*12),0)+IF((S$7-$L$7)<=(Settings!$C50*12),$L59/(Settings!$C50*12),0)+IF((S$7-$K$7)<=(Settings!$C50*12),$K59/(Settings!$C50*12),0)+IF((S$7-$J$7)<=(Settings!$C50*12),$J59/(Settings!$C50*12),0)+IF((S$7-$I$7)<=(Settings!$C50*12),$I59/(Settings!$C50*12),0)+IF((S$7-$H$7)<=(Settings!$C50*12),$H59/(Settings!$C50*12),0)+IF((S$7-$G$7)<=(Settings!$C50*12),$G59/(Settings!$C50*12),0)+IF((S$7-$F$7)<=(Settings!$C50*12),$F59/(Settings!$C50*12),0)+IF((S$7-$E$7)<=(Settings!$C50*12),$E59/(Settings!$C50*12),0)+IF((S$7-$D$7)<=(Settings!$C50*12),$D59/(Settings!$C50*12),0)+IF((E$7-$D$7)<=(Settings!$C50*12),$C59/(Settings!$C50*12),0) -> 0 | T69: =IF((T$7-$S$7)<=(Settings!$C50*12),$S59/(Settings!$C50*12),0)+IF((T$7-$R$7)<=(Settings!$C50*12),$R59/(Settings!$C50*12),0)+IF((T$7-$Q$7)<=(Settings!$C50*12),$Q59/(Settings!$C50*12),0)+IF((T$7-$P$7)<=(Settings!$C50*12),$P59/(Settings!$C50*12),0)+IF((T$7-$O$7)<=(Settings!$C50*12),$O59/(Settings!$C50*12),0)+IF((T$7-$N$7)<=(Settings!$C50*12),$N59/(Settings!$C50*12),0)+IF((T$7-$M$7)<=(Settings!$C50*12),$M59/(Settings!$C50*12),0)+IF((T$7-$L$7)<=(Settings!$C50*12),$L59/(Settings!$C50*12),0)+IF((T$7-$K$7)<=(Settings!$C50*12),$K59/(Settings!$C50*12),0)+IF((T$7-$J$7)<=(Settings!$C50*12),$J59/(Settings!$C50*12),0)+IF((T$7-$I$7)<=(Settings!$C50*12),$I59/(Settings!$C50*12),0)+IF((T$7-$H$7)<=(Settings!$C50*12),$H59/(Settings!$C50*12),0)+IF((T$7-$G$7)<=(Settings!$C50*12),$G59/(Settings!$C50*12),0)+IF((T$7-$F$7)<=(Settings!$C50*12),$F59/(Settings!$C50*12),0)+IF((T$7-$E$7)<=(Settings!$C50*12),$E59/(Settings!$C50*12),0)+IF((T$7-$D$7)<=(Settings!$C50*12),$D59/(Settings!$C50*12),0)+IF((E$7-$D$7)<=(Settings!$C50*12),$C59/(Settings!$C50*12),0) -> 0
A70: Other | B70: =Settings!$C$6 -> CAD | D70: =+IF((E$7-$D$7)<=(Settings!$C51*12),$C60/(Settings!$C51*12),0) -> 0 | E70: =IF((E$7-$D$7)<=(Settings!$C51*12),$D60/(Settings!$C51*12),0)+IF((E$7-$D$7)<=(Settings!$C51*12),$C60/(Settings!$C51*12),0) -> 0 | F70: =IF((F$7-$E$7)<=(Settings!$C51*12),$E60/(Settings!$C51*12),0)+IF((F$7-$D$7)<=(Settings!$C51*12),$D60/(Settings!$C51*12),0)+IF((E$7-$D$7)<=(Settings!$C51*12),$C60/(Settings!$C51*12),0) -> 0 | G70: =IF((G$7-$F$7)<=(Settings!$C51*12),$F60/(Settings!$C51*12),0)+IF((G$7-$E$7)<=(Settings!$C51*12),$E60/(Settings!$C51*12),0)+IF((G$7-$D$7)<=(Settings!$C51*12),$D60/(Settings!$C51*12),0)+IF((E$7-$D$7)<=(Settings!$C51*12),$C60/(Settings!$C51*12),0) -> 0 | H70: =IF((H$7-$G$7)<=(Settings!$C51*12),$G60/(Settings!$C51*12),0)+IF((H$7-$F$7)<=(Settings!$C51*12),$F60/(Settings!$C51*12),0)+IF((H$7-$E$7)<=(Settings!$C51*12),$E60/(Settings!$C51*12),0)+IF((H$7-$D$7)<=(Settings!$C51*12),$D60/(Settings!$C51*12),0)+IF((E$7-$D$7)<=(Settings!$C51*12),$C60/(Settings!$C51*12),0) -> 0 | I70: =IF((I$7-$H$7)<=(Settings!$C51*12),$H60/(Settings!$C51*12),0)+IF((I$7-$G$7)<=(Settings!$C51*12),$G60/(Settings!$C51*12),0)+IF((I$7-$F$7)<=(Settings!$C51*12),$F60/(Settings!$C51*12),0)+IF((I$7-$E$7)<=(Settings!$C51*12),$E60/(Settings!$C51*12),0)+IF((I$7-$D$7)<=(Settings!$C51*12),$D60/(Settings!$C51*12),0)+IF((E$7-$D$7)<=(Settings!$C51*12),$C60/(Settings!$C51*12),0) -> 0 | J70: =IF((J$7-$I$7)<=(Settings!$C51*12),$I60/(Settings!$C51*12),0)+IF((J$7-$H$7)<=(Settings!$C51*12),$H60/(Settings!$C51*12),0)+IF((J$7-$G$7)<=(Settings!$C51*12),$G60/(Settings!$C51*12),0)+IF((J$7-$F$7)<=(Settings!$C51*12),$F60/(Settings!$C51*12),0)+IF((J$7-$E$7)<=(Settings!$C51*12),$E60/(Settings!$C51*12),0)+IF((J$7-$D$7)<=(Settings!$C51*12),$D60/(Settings!$C51*12),0)+IF((E$7-$D$7)<=(Settings!$C51*12),$C60/(Settings!$C51*12),0) -> 0 | K70: =IF((K$7-$J$7)<=(Settings!$C51*12),$J60/(Settings!$C51*12),0)+IF((K$7-$I$7)<=(Settings!$C51*12),$I60/(Settings!$C51*12),0)+IF((K$7-$H$7)<=(Settings!$C51*12),$H60/(Settings!$C51*12),0)+IF((K$7-$G$7)<=(Settings!$C51*12),$G60/(Settings!$C51*12),0)+IF((K$7-$F$7)<=(Settings!$C51*12),$F60/(Settings!$C51*12),0)+IF((K$7-$E$7)<=(Settings!$C51*12),$E60/(Settings!$C51*12),0)+IF((K$7-$D$7)<=(Settings!$C51*12),$D60/(Settings!$C51*12),0)+IF((E$7-$D$7)<=(Settings!$C51*12),$C60/(Settings!$C51*12),0) -> 0 | L70: =IF((L$7-$K$7)<=(Settings!$C51*12),$K60/(Settings!$C51*12),0)+IF((L$7-$J$7)<=(Settings!$C51*12),$J60/(Settings!$C51*12),0)+IF((L$7-$I$7)<=(Settings!$C51*12),$I60/(Settings!$C51*12),0)+IF((L$7-$H$7)<=(Settings!$C51*12),$H60/(Settings!$C51*12),0)+IF((L$7-$G$7)<=(Settings!$C51*12),$G60/(Settings!$C51*12),0)+IF((L$7-$F$7)<=(Settings!$C51*12),$F60/(Settings!$C51*12),0)+IF((L$7-$E$7)<=(Settings!$C51*12),$E60/(Settings!$C51*12),0)+IF((L$7-$D$7)<=(Settings!$C51*12),$D60/(Settings!$C51*12),0)+IF((E$7-$D$7)<=(Settings!$C51*12),$C60/(Settings!$C51*12),0) -> 0 | M70: =IF((M$7-$L$7)<=(Settings!$C51*12),$L60/(Settings!$C51*12),0)+IF((M$7-$K$7)<=(Settings!$C51*12),$K60/(Settings!$C51*12),0)+IF((M$7-$J$7)<=(Settings!$C51*12),$J60/(Settings!$C51*12),0)+IF((M$7-$I$7)<=(Settings!$C51*12),$I60/(Settings!$C51*12),0)+IF((M$7-$H$7)<=(Settings!$C51*12),$H60/(Settings!$C51*12),0)+IF((M$7-$G$7)<=(Settings!$C51*12),$G60/(Settings!$C51*12),0)+IF((M$7-$F$7)<=(Settings!$C51*12),$F60/(Settings!$C51*12),0)+IF((M$7-$E$7)<=(Settings!$C51*12),$E60/(Settings!$C51*12),0)+IF((M$7-$D$7)<=(Settings!$C51*12),$D60/(Settings!$C51*12),0)+IF((E$7-$D$7)<=(Settings!$C51*12),$C60/(Settings!$C51*12),0) -> 0 | N70: =IF((N$7-$M$7)<=(Settings!$C51*12),$M60/(Settings!$C51*12),0)+IF((N$7-$L$7)<=(Settings!$C51*12),$L60/(Settings!$C51*12),0)+IF((N$7-$K$7)<=(Settings!$C51*12),$K60/(Settings!$C51*12),0)+IF((N$7-$J$7)<=(Settings!$C51*12),$J60/(Settings!$C51*12),0)+IF((N$7-$I$7)<=(Settings!$C51*12),$I60/(Settings!$C51*12),0)+IF((N$7-$H$7)<=(Settings!$C51*12),$H60/(Settings!$C51*12),0)+IF((N$7-$G$7)<=(Settings!$C51*12),$G60/(Settings!$C51*12),0)+IF((N$7-$F$7)<=(Settings!$C51*12),$F60/(Settings!$C51*12),0)+IF((N$7-$E$7)<=(Settings!$C51*12),$E60/(Settings!$C51*12),0)+IF((N$7-$D$7)<=(Settings!$C51*12),$D60/(Settings!$C51*12),0)+IF((E$7-$D$7)<=(Settings!$C51*12),$C60/(Settings!$C51*12),0) -> 0 | O70: =IF((O$7-$N$7)<=(Settings!$C51*12),$N60/(Settings!$C51*12),0)+IF((O$7-$M$7)<=(Settings!$C51*12),$M60/(Settings!$C51*12),0)+IF((O$7-$L$7)<=(Settings!$C51*12),$L60/(Settings!$C51*12),0)+IF((O$7-$K$7)<=(Settings!$C51*12),$K60/(Settings!$C51*12),0)+IF((O$7-$J$7)<=(Settings!$C51*12),$J60/(Settings!$C51*12),0)+IF((O$7-$I$7)<=(Settings!$C51*12),$I60/(Settings!$C51*12),0)+IF((O$7-$H$7)<=(Settings!$C51*12),$H60/(Settings!$C51*12),0)+IF((O$7-$G$7)<=(Settings!$C51*12),$G60/(Settings!$C51*12),0)+IF((O$7-$F$7)<=(Settings!$C51*12),$F60/(Settings!$C51*12),0)+IF((O$7-$E$7)<=(Settings!$C51*12),$E60/(Settings!$C51*12),0)+IF((O$7-$D$7)<=(Settings!$C51*12),$D60/(Settings!$C51*12),0)+IF((E$7-$D$7)<=(Settings!$C51*12),$C60/(Settings!$C51*12),0) -> 0 | P70: =IF((P$7-$O$7)<=(Settings!$C51*12),$O60/(Settings!$C51*12),0)+IF((P$7-$N$7)<=(Settings!$C51*12),$N60/(Settings!$C51*12),0)+IF((P$7-$M$7)<=(Settings!$C51*12),$M60/(Settings!$C51*12),0)+IF((P$7-$L$7)<=(Settings!$C51*12),$L60/(Settings!$C51*12),0)+IF((P$7-$K$7)<=(Settings!$C51*12),$K60/(Settings!$C51*12),0)+IF((P$7-$J$7)<=(Settings!$C51*12),$J60/(Settings!$C51*12),0)+IF((P$7-$I$7)<=(Settings!$C51*12),$I60/(Settings!$C51*12),0)+IF((P$7-$H$7)<=(Settings!$C51*12),$H60/(Settings!$C51*12),0)+IF((P$7-$G$7)<=(Settings!$C51*12),$G60/(Settings!$C51*12),0)+IF((P$7-$F$7)<=(Settings!$C51*12),$F60/(Settings!$C51*12),0)+IF((P$7-$E$7)<=(Settings!$C51*12),$E60/(Settings!$C51*12),0)+IF((P$7-$D$7)<=(Settings!$C51*12),$D60/(Settings!$C51*12),0)+IF((E$7-$D$7)<=(Settings!$C51*12),$C60/(Settings!$C51*12),0) -> 0 | Q70: =IF((Q$7-$P$7)<=(Settings!$C51*12),$P60/(Settings!$C51*12),0)+IF((Q$7-$O$7)<=(Settings!$C51*12),$O60/(Settings!$C51*12),0)+IF((Q$7-$N$7)<=(Settings!$C51*12),$N60/(Settings!$C51*12),0)+IF((Q$7-$M$7)<=(Settings!$C51*12),$M60/(Settings!$C51*12),0)+IF((Q$7-$L$7)<=(Settings!$C51*12),$L60/(Settings!$C51*12),0)+IF((Q$7-$K$7)<=(Settings!$C51*12),$K60/(Settings!$C51*12),0)+IF((Q$7-$J$7)<=(Settings!$C51*12),$J60/(Settings!$C51*12),0)+IF((Q$7-$I$7)<=(Settings!$C51*12),$I60/(Settings!$C51*12),0)+IF((Q$7-$H$7)<=(Settings!$C51*12),$H60/(Settings!$C51*12),0)+IF((Q$7-$G$7)<=(Settings!$C51*12),$G60/(Settings!$C51*12),0)+IF((Q$7-$F$7)<=(Settings!$C51*12),$F60/(Settings!$C51*12),0)+IF((Q$7-$E$7)<=(Settings!$C51*12),$E60/(Settings!$C51*12),0)+IF((Q$7-$D$7)<=(Settings!$C51*12),$D60/(Settings!$C51*12),0)+IF((E$7-$D$7)<=(Settings!$C51*12),$C60/(Settings!$C51*12),0) -> 0 | R70: =IF((R$7-$Q$7)<=(Settings!$C51*12),$Q60/(Settings!$C51*12),0)+IF((R$7-$P$7)<=(Settings!$C51*12),$P60/(Settings!$C51*12),0)+IF((R$7-$O$7)<=(Settings!$C51*12),$O60/(Settings!$C51*12),0)+IF((R$7-$N$7)<=(Settings!$C51*12),$N60/(Settings!$C51*12),0)+IF((R$7-$M$7)<=(Settings!$C51*12),$M60/(Settings!$C51*12),0)+IF((R$7-$L$7)<=(Settings!$C51*12),$L60/(Settings!$C51*12),0)+IF((R$7-$K$7)<=(Settings!$C51*12),$K60/(Settings!$C51*12),0)+IF((R$7-$J$7)<=(Settings!$C51*12),$J60/(Settings!$C51*12),0)+IF((R$7-$I$7)<=(Settings!$C51*12),$I60/(Settings!$C51*12),0)+IF((R$7-$H$7)<=(Settings!$C51*12),$H60/(Settings!$C51*12),0)+IF((R$7-$G$7)<=(Settings!$C51*12),$G60/(Settings!$C51*12),0)+IF((R$7-$F$7)<=(Settings!$C51*12),$F60/(Settings!$C51*12),0)+IF((R$7-$E$7)<=(Settings!$C51*12),$E60/(Settings!$C51*12),0)+IF((R$7-$D$7)<=(Settings!$C51*12),$D60/(Settings!$C51*12),0)+IF((E$7-$D$7)<=(Settings!$C51*12),$C60/(Settings!$C51*12),0) -> 0 | S70: =IF((S$7-$R$7)<=(Settings!$C51*12),$R60/(Settings!$C51*12),0)+IF((S$7-$Q$7)<=(Settings!$C51*12),$Q60/(Settings!$C51*12),0)+IF((S$7-$P$7)<=(Settings!$C51*12),$P60/(Settings!$C51*12),0)+IF((S$7-$O$7)<=(Settings!$C51*12),$O60/(Settings!$C51*12),0)+IF((S$7-$N$7)<=(Settings!$C51*12),$N60/(Settings!$C51*12),0)+IF((S$7-$M$7)<=(Settings!$C51*12),$M60/(Settings!$C51*12),0)+IF((S$7-$L$7)<=(Settings!$C51*12),$L60/(Settings!$C51*12),0)+IF((S$7-$K$7)<=(Settings!$C51*12),$K60/(Settings!$C51*12),0)+IF((S$7-$J$7)<=(Settings!$C51*12),$J60/(Settings!$C51*12),0)+IF((S$7-$I$7)<=(Settings!$C51*12),$I60/(Settings!$C51*12),0)+IF((S$7-$H$7)<=(Settings!$C51*12),$H60/(Settings!$C51*12),0)+IF((S$7-$G$7)<=(Settings!$C51*12),$G60/(Settings!$C51*12),0)+IF((S$7-$F$7)<=(Settings!$C51*12),$F60/(Settings!$C51*12),0)+IF((S$7-$E$7)<=(Settings!$C51*12),$E60/(Settings!$C51*12),0)+IF((S$7-$D$7)<=(Settings!$C51*12),$D60/(Settings!$C51*12),0)+IF((E$7-$D$7)<=(Settings!$C51*12),$C60/(Settings!$C51*12),0) -> 0 | T70: =IF((T$7-$S$7)<=(Settings!$C51*12),$S60/(Settings!$C51*12),0)+IF((T$7-$R$7)<=(Settings!$C51*12),$R60/(Settings!$C51*12),0)+IF((T$7-$Q$7)<=(Settings!$C51*12),$Q60/(Settings!$C51*12),0)+IF((T$7-$P$7)<=(Settings!$C51*12),$P60/(Settings!$C51*12),0)+IF((T$7-$O$7)<=(Settings!$C51*12),$O60/(Settings!$C51*12),0)+IF((T$7-$N$7)<=(Settings!$C51*12),$N60/(Settings!$C51*12),0)+IF((T$7-$M$7)<=(Settings!$C51*12),$M60/(Settings!$C51*12),0)+IF((T$7-$L$7)<=(Settings!$C51*12),$L60/(Settings!$C51*12),0)+IF((T$7-$K$7)<=(Settings!$C51*12),$K60/(Settings!$C51*12),0)+IF((T$7-$J$7)<=(Settings!$C51*12),$J60/(Settings!$C51*12),0)+IF((T$7-$I$7)<=(Settings!$C51*12),$I60/(Settings!$C51*12),0)+IF((T$7-$H$7)<=(Settings!$C51*12),$H60/(Settings!$C51*12),0)+IF((T$7-$G$7)<=(Settings!$C51*12),$G60/(Settings!$C51*12),0)+IF((T$7-$F$7)<=(Settings!$C51*12),$F60/(Settings!$C51*12),0)+IF((T$7-$E$7)<=(Settings!$C51*12),$E60/(Settings!$C51*12),0)+IF((T$7-$D$7)<=(Settings!$C51*12),$D60/(Settings!$C51*12),0)+IF((E$7-$D$7)<=(Settings!$C51*12),$C60/(Settings!$C51*12),0) -> 0
A71: Total | B71: =Settings!$C$6 -> CAD | D71: =SUM(D67:D70) -> 0 | E71: =SUM(E67:E70) -> 0 | F71: =SUM(F67:F70) -> 0 | G71: =SUM(G67:G70) -> 0 | H71: =SUM(H67:H70) -> 0 | I71: =SUM(I67:I70) -> 0 | J71: =SUM(J67:J70) -> 0 | K71: =SUM(K67:K70) -> 0 | ... T71: =SUM(T67:T70) -> 0

Sheet Use of funds
A3: Senario | D3: 5000000 | E3: 50000000
A4: Total Funds | C4: 2000000 | D4: 7000000 | E4: 52000000
C6: =+C7/C4 -> 0.025 | D6: =+D7/D4 -> 0.078571429 | E6: =+E7/E4 -> 0.092692308
A7: Regulatory | C7: =SUM(C8:C15) -> 50000 | D7: =SUM(D8:D15) -> 550000 | E7: =SUM(E8:E15) -> 4820000
A8: Reg A Prep | C8: 50000 | D8: =+C8 -> 50000 | E8: =+C8 -> 50000
A9: Reg A Marketing 5% Raise | B9: 0.05 | D9: =+D3*0.05 -> 250000 | E9: =+E3*0.05 -> 2500000
A10: Form 1-A | E10: 50000
A11: Audit | E11: 20000
A12: Legal Fees | D12: 50000 | E12: 200000
A13: Ongoing Legal | D13: =+(D3/1000)*25 -> 125000 | E13: =+(E3/1000)*25 -> 1250000
A14: Broker Dealer | B14: 0.01 | C14: =+C3*$B$14 -> 0 | D14: =+D3*$B$14 -> 50000 | E14: =+E3*$B$14 -> 500000
A15: Transfer/Escrow | B15: 0.005 | C15: =+C3*$B$15 -> 0 | D15: =+D3*$B$15 -> 25000 | E15: =+E3*$B$15 -> 250000
C17: =+C18/C4 -> 0.4534 | D17: =+D18/D4 -> 0.32197143 | E17: =+E18/E4 -> 0.21936154
A18: Operating & Admin | C18: =SUM(C19:C24) -> 906800 | D18: =SUM(D19:D24) -> 2253800 | E18: =SUM(E19:E24) -> 11406800
A19: Salaries | C19: =+(25000*12)*C42+(15000*12) -> 480000 | D19: =+(25000*12)*D42+(15000*12) -> 1380000 | E19: =+(25000*12)*E42+(15000*12) -> 7980000
A20: SG&A (Non Sal) | C20: 120000 | D20: 300000 | E20: 450000
A21: Interest (On $2M) | C21: 200000 | D21: =+C21 -> 200000 | E21: =+D21 -> 200000
A22: Foundation | B22: 0.01 | C22: =+C41*$B$22 -> 10000 | D22: =+D41*$B$22 -> 35000 | E22: =+E41*$B$22 -> 260000
A23: LPP | C23: =+C41*0.4*0.042 -> 16800 | D23: =+D41*0.4*0.042 -> 58800 | E23: =+E41*0.4*0.042 -> 436800
A24: AFDA | B24: 0.08 | C24: =+C41*$B$24 -> 80000 | D24: =+D41*$B$24 -> 280000 | E24: =+E41*$B$24 -> 2080000
C26: =C27/C4 -> 0.035 | D26: =D27/D4 -> 0.038571429 | E26: =E27/E4 -> 0.035480769
A27: Customer | C27: =+SUM(C28:C30) -> 70000 | D27: =+SUM(D28:D30) -> 270000 | E27: =+SUM(E28:E30) -> 1845000
A28: Marketing (5% Funds) | B28: 0.025 | C28: =+C4*$B$28 -> 50000 | D28: =+D4*$B$28 -> 175000 | E28: =+E4*$B$28 -> 1300000
A29: Raise Marketing Strategy | D29: 25000 | E29: 25000
A30: Sisterhood (Comm + Mark) 2% Loans | B30: 0.02 | C30: =+C41*$B$30 -> 20000 | D30: =+D41*$B$30 -> 70000 | E30: =+E41*$B$30 -> 520000
C32: =C33/C4 -> 0.012 | D32: =D33/D4 -> 0.020571429 | E32: =E33/E4 -> 0.010461538
A33: Product/Tech | C33: =SUM(C34:C36) -> 24000 | D33: =SUM(D34:D36) -> 144000 | E33: =SUM(E34:E36) -> 544000
A34: FLS | C34: 24000 | D34: 24000 | E34: 24000
A35: FLS Development | D35: 60000 | E35: 260000
A36: App Development | D36: 60000 | E36: 260000
A38: TOTAL | C38: =+C33+C27+C18+C7 -> 1050800 | D38: =+D33+D27+D18+D7 -> 3217800 | E38: =+E33+E27+E18+E7 -> 18615800
C40: =+B41 -> 0.5 | D40: =+C40 -> 0.5 | E40: =+D40 -> 0.5
A41: Loans | B41: 0.5 | C41: =+C4*C40 -> 1000000 | D41: =+D4*D40 -> 3500000 | E41: =+E4*E40 -> 26000000
A42: Villages | C42: =ROUNDUP(C41/1000000,0) -> 1 | D42: =ROUNDUP(D41/1000000,0) -> 4 | E42: =ROUNDUP(E41/1000000,0) -> 26
A43: Ladies | C43: =+C42*400 -> 400 | D43: =+D42*400 -> 1600 | E43: =+E42*400 -> 10400
A45: Total with loans | C45: =+C41+C38 -> 2050800 | D45: =+D41+D38 -> 6717800 | E45: =+E41+E38 -> 44615800
C47: =+C40+C32+C26+C17+C6 -> 1.0254 | D47: =+D40+D32+D26+D17+D6 -> 0.95968571 | E47: =+E40+E32+E26+E17+E6 -> 0.85799615

Sheet Valuation
A2: Company | B2: GroundFloor | C2: Gatsby | D2: Caliber | E2: Vital | F2: Hundy
A4: Year Founded | B4: 2016 | C4: 43800 | D4: 2009 | E4: 2017 | F4: 2016
A5: 2018 Loans | B5: 18671601
A6: 2019 Loans | B6: 40097871 | F6: 1132250
A7: 2018 Revenue | B7: 2889961 | C7: 0 | D7: 70672140 | E7: 0
A8: 2019 Revenue | B8: 6403115 | C8: 186000 | D8: 77867868 | E8: 0 | F8: 6929
A10: Employees | B10: 5 | C10: 7 | D10: 100+ | E10: 10 | F10: 5
A11: Past Funding | B11: 22000000 | C11: 3152121 | D11: 14000000 | E11: =999999+1095000+95999+20966+65176+500000+135000+250000 -> 3162140 | F11: =150000+330000+295000+87000+136000 -> 998000
A13: Seed | B13: 568,796 Prefferd | C13: 11,651,963 Preferred
A14: Series A | B14: 747,373 Preferred | D14: 2,564,103 Preferred
A15: Other | B15: 1,732,585 Common | C15: 11,466,966 Common | D15: 15,000,000 Class B 10x Vote
A17: Raise
A18: Type | B18: Reg A+ Tier 2 | C18: Reg A+ Tier 2 | D18: Reg A+ Tier 2 | E18: Reg CF | F18: Reg CF
A19: Pre Money Valuation | B19: 73900000 | C19: 25000000 | D19: 130000000 | E19: 10022952 | F19: 4000000
A20: Multiplier | B20: =B19/B8 -> 11.541258 | C20: =C19/C8 -> 134.4086 | D20: =D19/D8 -> 1.6694948 | F20: =F19/F8 -> 577.28388
B21: =B19/B6 -> 1.8429906 | F21: =F19/F6 -> 3.5327887
A22: Round Size | B22: 9999993 | C22: 5000000 | D22: 50000000 | E22: 1069999 | F22: 396724
A23: Security Type | B23: Preferred Equity | C23: Preferred Equity | D23: Preferred Equity | E23: Common Equity | F23: Convertible Note
B24: Voting | C24: Voting | D24: Voting | E24: Voting | F24: 6% Interest, 20% Discount, $5.75 Cap
A26: Security | B26: 548,546 Series B (Common) | C26: 5,434,782 Series A (Preferred) | D26: 12,500,000 Series B (Preferred) | E26: 50000000
A27: Price per share | B27: 18.23 | C27: 0.92 | D27: 4 | E27: 1.03
A28: Min Investment | B28: 984 | C28: 999.12 | D28: 2000 | F28: 200
A30: Platform | B30: Seed Invest (SI Securities) | C30: Seed Invest (SI Securities) | D30: Seed Invest (SI Securities) | E30: StartEngine
A31: Reg Filed | B31: 43739 | C31: 44044 | D31: 43983 | E31: 44136
A33: Notes: | C33: 10,000 Accounts | D33: $440M assets under management | E33: $2500/account | F33: P2P Microloans
C34: Limited to no Revenue | D34: 2019 EBITA $8M | F34: Loan of $500 in a few minutes
C35: Comparables Method Valuation - Purchase $ / Accounts | D35: Seed 2015 - $2.165M Val $20M | F35: 31 day repayment + 60 days grace
D36: Series A 2016 - $1.82M Val $37.2M | F36: Repay for access to more
D37: Series B 2016 - $9.6m Val $52M | F37: 10,000 loan, 1.1M Loan Book
F38: 1/3 pay off early or ontime
F39: 177% AOR fior 31 days, 60% if extended to 90 days
F40: 300 loans per month

Sheet Funding - Equity Round Calculat
A1: =Settings!C5 -> CosignSimple
A2: Cap Table Calculator - Equity Round
A3: =+TODAY() -> 44539
A7: Compant Details
A8: 1. How many shares of stock have been issued? | B8: 10000000
A9: You can find this information on your incorporation documents. If you haven't incorporated, use the default 10,000,000.
A12: 2. What is the initial % ownership | B12: Percentage (pre-funding) | C12: Stock
A13: Founder 1 | B13: 0.33 | C13: =B13*B$8 -> 3300000
A14: Founder 2 | B14: 0.33 | C14: =B14*B$8 -> 3300000
A15: Founder 3 | B15: 0.33 | C15: =B15*B$8 -> 3300000
A16: Other Founders or employees | B16: 0.01 | C16: =B16*B$8 -> 100000
A17: Total | B17: =SUM(B13:B16) -> 1 | C17: =B17*B$8 -> 10000000
A20: 3. How much money are you looking to raise? | B20: 500000
A22: 4. What is your pre-money valuation? | B22: 4000000
A25: Results
A26: Basics
A27: Post-Money Valuation | B27: =B22+B20 -> 4500000 | C27: USD
A28: Stock that needs to be issued | B28: =B20*B8/B22 -> 1250000 | C28: shares
A29: Total company stock after funding | B29: =B28+B8 -> 11250000 | C29: shares
A30: Investor's ownership | B30: =B28/B29 -> 0.11111111 | C30: percentage
A33: Cap Table | B33: Percentage (pre-funding) | C33: Percentage Ownership
A34: =A13 -> Founder 1 | B34: =C13 -> 3300000 | C34: =B34/$B$29 -> 0.29333333
A35: =A14 -> Founder 2 | B35: =C14 -> 3300000 | C35: =B35/$B$29 -> 0.29333333
A36: =A15 -> Founder 3 | B36: =C15 -> 3300000 | C36: =B36/$B$29 -> 0.29333333
A37: =A16 -> Other Founders or employees | B37: =C16 -> 100000 | C37: =B37/$B$29 -> 0.0088888889
A38: Investors | B38: =B28 -> 1250000 | C38: =B38/$B$29 -> 0.11111111

Sheet Funding - Convertible Note Calc
A1: =Settings!C5 -> CosignSimple
A2: Cap Table Calculator - Convertible Note
A3: =+TODAY() -> 44539
A7: Compant Details
A8: 1. How many shares of stock have been issued? | B8: 10000000
A9: You can find this information on your incorporation documents. If you haven't incorporated, use the default 1,000,000.
A12: 2. What is the initial % ownership | B12: Percentage (pre-funding) | C12: Stock
A13: Founder 1 | B13: 0.33 | C13: =B13*B$8 -> 3300000
A14: Founder 2 | B14: 0.33 | C14: =B14*B$8 -> 3300000
A15: Founder 3 | B15: 0.33 | C15: =B15*B$8 -> 3300000
A16: Other Founders or employees | B16: 0.01 | C16: =B16*B$8 -> 100000
A17: Total | B17: =SUM(B13:B16) -> 1 | C17: =B17*B$8 -> 10000000
A20: 3. How much money are you looking to raise on the convertible note? | B20: 1000000
A22: 4. What are the convertible note terms?
A23: Discount | B23: 0.2
A24: Interest Rate | B24: 0.05
A25: Cap | B25: 7000000
A27: 5. What are your expectations for a Series A?
A28: Valuation | B28: 5000000 | C28: pre-money
A29: Time after convertible note | B29: 18 | C29: months
A30: Investment size | B30: 1000000
A35: Results
A36: Convertible Note
A37: Accrued interest before conversion | B37: =B24/12*B29*B20 -> 75000 | C37: =B29&" months" -> 18 months
A38: Withstanding Convertible Note investment | B38: =B37+B20 -> 1075000 | C38: including interest
A39: Applicable valuation for Convertible Note | B39: =IF(B25>0,(MIN(B28*(1-B23),B25)),B28*(1-B23)) -> 4000000 | C39: =IF(B25=B39,"based on cap","based on discount") -> based on discount
A40: Shares issued to Convertible Note Investors | B40: =B38*B8/B39 -> 2687500
A41: Total shares issued after Convertible Note | B41: =B40+B8 -> 12687500
A42: Convertible Note Investors Ownership | B42: =B40/B41 -> 0.21182266 | C42: percentage
A45: Series A
A46: Stock that needs to be issued for Series A | B46: =B30*B41/B28 -> 2537500
A47: Total Company Stock after Series A | B47: =B46+B41 -> 15225000
A48: Post-Money Valuation | B48: =B28+B30 -> 6000000 | C48: USD
A49: Percentage Onwership of Series A Investors | B49: =B46/B47 -> 0.16666667
A52: Cap Table after Series A | B52: Stock | C52: Percentage Ownership
A53: =A13 -> Founder 1 | B53: =C13 -> 3300000 | C53: =B53/$B$59 -> 0.21674877
A54: =A14 -> Founder 2 | B54: =C14 -> 3300000 | C54: =B54/$B$59 -> 0.21674877
A55: =A15 -> Founder 3 | B55: =C15 -> 3300000 | C55: =B55/$B$59 -> 0.21674877
A56: =A16 -> Other Founders or employees | B56: =C16 -> 100000 | C56: =B56/$B$59 -> 0.0065681445
A57: Convertible Note Investors | B57: =B40 -> 2687500 | C57: =B57/$B$59 -> 0.17651888
A58: Series A Investors | B58: =B46 -> 2537500 | C58: =B58/$B$59 -> 0.16666667
A59: Total | B59: =B47 -> 15225000
